Workbook

Sheet PB_CACHE
A1: H4sIAAAAAAAEAM2QvU7DMBSF3QZEEDyEdyIrLQ2lQxYCAokORYlYqqo41hWx6tjBP0jpY/DC4EQpDCyM3MH32tL57vFBI4TQp6+ud3U+9sfTiltW3Si1w0XbgMFLXmqq2wg/gzZcyXQaTxMyIzGJI5w5YZ2GVIKzmooIr1wpOHuEtlA7kKl0Qhx3/Pwbu+2x2wFLctCcCr6npYCMsgp+v1wUqlnCO4j+dsuZ9Ta8NvDck8FVmKm6oRp0+EBNlfM9oACFH6O8NRZqkikhoNcZcg/Sb2CHfvfm/DbbHgAvk/V6UOVWc/ka4dowpQUvfzLov/+XAMr5nCYsuZosLmcQXy82m3A8xH0aDMNRN/xHq525sy/9GUvhJwIAAA==

Sheet Portfolio Metrics 
A1: Global xUS Opp Value
A2: ='xUS Opp Value'!A2 -> as of 4/13/2026
H4: Total Number fo Stocks
B5: Portfolio Metrics | C5: Gbl xUS Opp Value (tgt) | D5: Gbl xUS Opp Value (d) | E5: BM | H5: % EM
B6: Forward P/E | C6: {=SUMPRODUCT('xUS Opp Value'!G4:G2041, --('xUS Opp Value'!$L4:$L2041>0)) / SUMPRODUCT(IF('xUS Opp Value'!$L4:$L2041>0, 'xUS Opp Value'!G4:G2041/'xUS Opp Value'!$L4:$L2041, 0))} -> 13.418169 | D6: {=SUMPRODUCT('xUS Opp Value'!H4:H2041, --('xUS Opp Value'!$L4:$L2041>0)) / SUMPRODUCT(IF('xUS Opp Value'!$L4:$L2041>0, 'xUS Opp Value'!H4:H2041/'xUS Opp Value'!$L4:$L2041, 0))} -> 13.450315 | E6: {=SUMPRODUCT('xUS Opp Value'!I4:I2041, --('xUS Opp Value'!$L4:$L2041>0)) / SUMPRODUCT(IF('xUS Opp Value'!$L4:$L2041>0, 'xUS Opp Value'!I4:I2041/'xUS Opp Value'!$L4:$L2041, 0))} -> 12.726655 | H6: %DM
B7: P/FV | C7: {=SUMPRODUCT('xUS Opp Value'!G4:G2165, --('xUS Opp Value'!J4:J2165>0)) / SUMPRODUCT(IF('xUS Opp Value'!J4:J2165>0, 'xUS Opp Value'!G4:G2165/'xUS Opp Value'!J4:J2165, 0))} -> 0.79580336 | D7: {=SUMPRODUCT('xUS Opp Value'!H4:H2041, --('xUS Opp Value'!J4:J2041>0)) / SUMPRODUCT(IF('xUS Opp Value'!J4:J2041>0, 'xUS Opp Value'!H4:H2041/'xUS Opp Value'!J4:J2041, 0))} -> 0.80392045 | E7: {=SUMPRODUCT('xUS Opp Value'!I4:I2041, --('xUS Opp Value'!J4:J2041>0)) / SUMPRODUCT(IF('xUS Opp Value'!J4:J2041>0, 'xUS Opp Value'!I4:I2041/'xUS Opp Value'!J4:J2041, 0))} -> 0.89279149
B8: MER Upside | C8: =(1/C7)-1 -> 0.25659183 | D8: =(1/D7)-1 -> 0.24390417 | E8: =(1/E7)-1 -> 0.12008237
M12: Forward P/E | P12: MER Upside | S12: MER P/FV
B13: Country | C13: Gbl xUS Opp Value (tgt) | D13: Gbl xUS Opp Value (d) | E13: BM | F13: Algo | G13: vs. BM | H13: vs. Algo | I13: Exp Algp | J13: vs Exp Algo | L13: Country | M13: Gbl xUS Opp Value (tgt) | N13: Gbl xUS Opp Value (d) | O13: BM | P13: xUS Opp Value (tgt) | Q13: xUS Opp Value (d) | R13: BM | S13: xUS Opp Value (tgt) | T13: xUS Opp Value (d) | U13: BM
A14: JP EQ | B14: Japan | C14: =SUMIF('xUS Opp Value'!E:E,'Portfolio Metrics '!B14,'xUS Opp Value'!G:G)/100 -> 0.1475 | D14: =SUMIF('xUS Opp Value'!E:E,'Portfolio Metrics '!B14,'xUS Opp Value'!H:H)/100 -> 0.14568342 | E14: =SUMIF('xUS Opp Value'!E:E,'Portfolio Metrics '!B14,'xUS Opp Value'!I:I)/100 -> 0.1442 | F14: =INDEX(Algo!$D:$D,MATCH('Portfolio Metrics '!A14,Algo!A:A,0)) -> 0.0816 | G14: =C14-E14 -> 0.0033 | H14: =C14-F14 -> 0.0659 | I14: =INDEX(#REF!,MATCH('Portfolio Metrics '!A14,#REF!,0)) -> #REF! | J14: =C14-I14 -> #REF! | L14: Japan | M14: {=IFERROR(SUMPRODUCT('xUS Opp Value'!G$4:G$2041, --('xUS Opp Value'!$L$4:$L$2041>0), --( ('xUS Opp Value'!$E$4:$E$2041=$L14) + ('xUS Opp Value'!$E$4:$E$2041="") > 0 )) / SUMPRODUCT(IF( ('xUS Opp Value'!$L$4:$L$2041>0) * ( ('xUS Opp Value'!$E$4:$E$2041=$L14) + ('xUS Opp Value'!$E$4:$E$2041="") > 0 ), 'xUS Opp Value'!G$4:G$2041/'xUS Opp Value'!$L$4:$L$2041, 0)),"")} | N14: {=IFERROR(SUMPRODUCT('xUS Opp Value'!H$4:H$2041, --('xUS Opp Value'!$L$4:$L$2041>0), --( ('xUS Opp Value'!$E$4:$E$2041=$L14) + ('xUS Opp Value'!$E$4:$E$2041="") > 0 )) / SUMPRODUCT(IF( ('xUS Opp Value'!$L$4:$L$2041>0) * ( ('xUS Opp Value'!$E$4:$E$2041=$L14) + ('xUS Opp Value'!$E$4:$E$2041="") > 0 ), 'xUS Opp Value'!H$4:H$2041/'xUS Opp Value'!$L$4:$L$2041, 0)),"")} | O14: {=IFERROR(SUMPRODUCT('xUS Opp Value'!I$4:I$2041, --('xUS Opp Value'!$L$4:$L$2041>0), --( ('xUS Opp Value'!$E$4:$E$2041=$L14) + ('xUS Opp Value'!$E$4:$E$2041="") > 0 )) / SUMPRODUCT(IF( ('xUS Opp Value'!$L$4:$L$2041>0) * ( ('xUS Opp Value'!$E$4:$E$2041=$L14) + ('xUS Opp Value'!$E$4:$E$2041="") > 0 ), 'xUS Opp Value'!I$4:I$2041/'xUS Opp Value'!$L$4:$L$2041, 0)),"")} | P14: =IFERROR((1/S14)-1,"") | Q14: =IFERROR((1/T14)-1,"") | R14: =IFERROR((1/U14)-1,"") | S14: {=IFERROR(SUMPRODUCT('xUS Opp Value'!G$4:G$2041, --('xUS Opp Value'!$J$4:$J$2041>0), --( ('xUS Opp Value'!$E$4:$E$2041=$L14) + ('xUS Opp Value'!$E$4:$E$2041="") > 0 )) / SUMPRODUCT(IF( ('xUS Opp Value'!$J$4:$J$2041>0) * ( ('xUS Opp Value'!$E$4:$E$2041=$L14) + ('xUS Opp Value'!$E$4:$E$2041="") > 0 ), 'xUS Opp Value'!G$4:G$2041/'xUS Opp Value'!$J$4:$J$2041, 0)),"")} | T14: {=IFERROR(SUMPRODUCT('xUS Opp Value'!H$4:H$2041, --('xUS Opp Value'!$J$4:$J$2041>0), --( ('xUS Opp Value'!$E$4:$E$2041=$L14) + ('xUS Opp Value'!$E$4:$E$2041="") > 0 )) / SUMPRODUCT(IF( ('xUS Opp Value'!$J$4:$J$2041>0) * ( ('xUS Opp Value'!$E$4:$E$2041=$L14) + ('xUS Opp Value'!$E$4:$E$2041="") > 0 ), 'xUS Opp Value'!H$4:H$2041/'xUS Opp Value'!$J$4:$J$2041, 0)),"")} | U14: {=IFERROR(SUMPRODUCT('xUS Opp Value'!I$4:I$2041, --('xUS Opp Value'!$J$4:$J$2041>0), --( ('xUS Opp Value'!$E$4:$E$2041=$L14) + ('xUS Opp Value'!$E$4:$E$2041="") > 0 )) / SUMPRODUCT(IF( ('xUS Opp Value'!$J$4:$J$2041>0) * ( ('xUS Opp Value'!$E$4:$E$2041=$L14) + ('xUS Opp Value'!$E$4:$E$2041="") > 0 ), 'xUS Opp Value'!I$4:I$2041/'xUS Opp Value'!$J$4:$J$2041, 0)),"")}
A15: UK EQ | B15: United Kingdom | C15: =SUMIF('xUS Opp Value'!E:E,'Portfolio Metrics '!B15,'xUS Opp Value'!G:G)/100 -> 0.1275 | D15: =SUMIF('xUS Opp Value'!E:E,'Portfolio Metrics '!B15,'xUS Opp Value'!H:H)/100 -> 0.13161007 | E15: =SUMIF('xUS Opp Value'!E:E,'Portfolio Metrics '!B15,'xUS Opp Value'!I:I)/100 -> 0.0866 | F15: =INDEX(Algo!$D:$D,MATCH('Portfolio Metrics '!A15,Algo!A:A,0)) -> 0.0867 | G15: =C15-E15 -> 0.0409 | H15: =C15-F15 -> 0.0408 | I15: =INDEX(#REF!,MATCH('Portfolio Metrics '!A15,#REF!,0)) -> #REF! | J15: =C15-I15 -> #REF! | L15: United Kingdom | M15: {=IFERROR(SUMPRODUCT('xUS Opp Value'!G$4:G$2041, --('xUS Opp Value'!$L$4:$L$2041>0), --( ('xUS Opp Value'!$E$4:$E$2041=$L15) + ('xUS Opp Value'!$E$4:$E$2041="") > 0 )) / SUMPRODUCT(IF( ('xUS Opp Value'!$L$4:$L$2041>0) * ( ('xUS Opp Value'!$E$4:$E$2041=$L15) + ('xUS Opp Value'!$E$4:$E$2041="") > 0 ), 'xUS Opp Value'!G$4:G$2041/'xUS Opp Value'!$L$4:$L$2041, 0)),"")} | N15: {=IFERROR(SUMPRODUCT('xUS Opp Value'!H$4:H$2041, --('xUS Opp Value'!$L$4:$L$2041>0), --( ('xUS Opp Value'!$E$4:$E$2041=$L15) + ('xUS Opp Value'!$E$4:$E$2041="") > 0 )) / SUMPRODUCT(IF( ('xUS Opp Value'!$L$4:$L$2041>0) * ( ('xUS Opp Value'!$E$4:$E$2041=$L15) + ('xUS Opp Value'!$E$4:$E$2041="") > 0 ), 'xUS Opp Value'!H$4:H$2041/'xUS Opp Value'!$L$4:$L$2041, 0)),"")} | O15: {=IFERROR(SUMPRODUCT('xUS Opp Value'!I$4:I$2041, --('xUS Opp Value'!$L$4:$L$2041>0), --( ('xUS Opp Value'!$E$4:$E$2041=$L15) + ('xUS Opp Value'!$E$4:$E$2041="") > 0 )) / SUMPRODUCT(IF( ('xUS Opp Value'!$L$4:$L$2041>0) * ( ('xUS Opp Value'!$E$4:$E$2041=$L15) + ('xUS Opp Value'!$E$4:$E$2041="") > 0 ), 'xUS Opp Value'!I$4:I$2041/'xUS Opp Value'!$L$4:$L$2041, 0)),"")} | P15: =IFERROR((1/S15)-1,"") | Q15: =IFERROR((1/T15)-1,"") | R15: =IFERROR((1/U15)-1,"") | S15: {=IFERROR(SUMPRODUCT('xUS Opp Value'!G$4:G$2041, --('xUS Opp Value'!$J$4:$J$2041>0), --( ('xUS Opp Value'!$E$4:$E$2041=$L15) + ('xUS Opp Value'!$E$4:$E$2041="") > 0 )) / SUMPRODUCT(IF( ('xUS Opp Value'!$J$4:$J$2041>0) * ( ('xUS Opp Value'!$E$4:$E$2041=$L15) + ('xUS Opp Value'!$E$4:$E$2041="") > 0 ), 'xUS Opp Value'!G$4:G$2041/'xUS Opp Value'!$J$4:$J$2041, 0)),"")} | T15: {=IFERROR(SUMPRODUCT('xUS Opp Value'!H$4:H$2041, --('xUS Opp Value'!$J$4:$J$2041>0), --( ('xUS Opp Value'!$E$4:$E$2041=$L15) + ('xUS Opp Value'!$E$4:$E$2041="") > 0 )) / SUMPRODUCT(IF( ('xUS Opp Value'!$J$4:$J$2041>0) * ( ('xUS Opp Value'!$E$4:$E$2041=$L15) + ('xUS Opp Value'!$E$4:$E$2041="") > 0 ), 'xUS Opp Value'!H$4:H$2041/'xUS Opp Value'!$J$4:$J$2041, 0)),"")} | U15: {=IFERROR(SUMPRODUCT('xUS Opp Value'!I$4:I$2041, --('xUS Opp Value'!$J$4:$J$2041>0), --( ('xUS Opp Value'!$E$4:$E$2041=$L15) + ('xUS Opp Value'!$E$4:$E$2041="") > 0 )) / SUMPRODUCT(IF( ('xUS Opp Value'!$J$4:$J$2041>0) * ( ('xUS Opp Value'!$E$4:$E$2041=$L15) + ('xUS Opp Value'!$E$4:$E$2041="") > 0 ), 'xUS Opp Value'!I$4:I$2041/'xUS Opp Value'!$J$4:$J$2041, 0)),"")}
A16: CA EQ | B16: Canada | C16: =SUMIF('xUS Opp Value'!E:E,'Portfolio Metrics '!B16,'xUS Opp Value'!G:G)/100 -> 0.0275 | D16: =SUMIF('xUS Opp Value'!E:E,'Portfolio Metrics '!B16,'xUS Opp Value'!H:H)/100 -> 0.028217641 | E16: =SUMIF('xUS Opp Value'!E:E,'Portfolio Metrics '!B16,'xUS Opp Value'!I:I)/100 -> 0.0835 | F16: =INDEX(Algo!$D:$D,MATCH('Portfolio Metrics '!A16,Algo!A:A,0)) -> 0.0424 | G16: =C16-E16 -> -0.056 | H16: =C16-F16 -> -0.0149 | I16: =INDEX(#REF!,MATCH('Portfolio Metrics '!A16,#REF!,0)) -> #REF! | J16: =C16-I16 -> #REF! | L16: Canada | M16: {=IFERROR(SUMPRODUCT('xUS Opp Value'!G$4:G$2041, --('xUS Opp Value'!$L$4:$L$2041>0), --( ('xUS Opp Value'!$E$4:$E$2041=$L16) + ('xUS Opp Value'!$E$4:$E$2041="") > 0 )) / SUMPRODUCT(IF( ('xUS Opp Value'!$L$4:$L$2041>0) * ( ('xUS Opp Value'!$E$4:$E$2041=$L16) + ('xUS Opp Value'!$E$4:$E$2041="") > 0 ), 'xUS Opp Value'!G$4:G$2041/'xUS Opp Value'!$L$4:$L$2041, 0)),"")} | N16: {=IFERROR(SUMPRODUCT('xUS Opp Value'!H$4:H$2041, --('xUS Opp Value'!$L$4:$L$2041>0), --( ('xUS Opp Value'!$E$4:$E$2041=$L16) + ('xUS Opp Value'!$E$4:$E$2041="") > 0 )) / SUMPRODUCT(IF( ('xUS Opp Value'!$L$4:$L$2041>0) * ( ('xUS Opp Value'!$E$4:$E$2041=$L16) + ('xUS Opp Value'!$E$4:$E$2041="") > 0 ), 'xUS Opp Value'!H$4:H$2041/'xUS Opp Value'!$L$4:$L$2041, 0)),"")} | O16: {=IFERROR(SUMPRODUCT('xUS Opp Value'!I$4:I$2041, --('xUS Opp Value'!$L$4:$L$2041>0), --( ('xUS Opp Value'!$E$4:$E$2041=$L16) + ('xUS Opp Value'!$E$4:$E$2041="") > 0 )) / SUMPRODUCT(IF( ('xUS Opp Value'!$L$4:$L$2041>0) * ( ('xUS Opp Value'!$E$4:$E$2041=$L16) + ('xUS Opp Value'!$E$4:$E$2041="") > 0 ), 'xUS Opp Value'!I$4:I$2041/'xUS Opp Value'!$L$4:$L$2041, 0)),"")} | P16: =IFERROR((1/S16)-1,"") | Q16: =IFERROR((1/T16)-1,"") | R16: =IFERROR((1/U16)-1,"") | S16: {=IFERROR(SUMPRODUCT('xUS Opp Value'!G$4:G$2041, --('xUS Opp Value'!$J$4:$J$2041>0), --( ('xUS Opp Value'!$E$4:$E$2041=$L16) + ('xUS Opp Value'!$E$4:$E$2041="") > 0 )) / SUMPRODUCT(IF( ('xUS Opp Value'!$J$4:$J$2041>0) * ( ('xUS Opp Value'!$E$4:$E$2041=$L16) + ('xUS Opp Value'!$E$4:$E$2041="") > 0 ), 'xUS Opp Value'!G$4:G$2041/'xUS Opp Value'!$J$4:$J$2041, 0)),"")} | T16: {=IFERROR(SUMPRODUCT('xUS Opp Value'!H$4:H$2041, --('xUS Opp Value'!$J$4:$J$2041>0), --( ('xUS Opp Value'!$E$4:$E$2041=$L16) + ('xUS Opp Value'!$E$4:$E$2041="") > 0 )) / SUMPRODUCT(IF( ('xUS Opp Value'!$J$4:$J$2041>0) * ( ('xUS Opp Value'!$E$4:$E$2041=$L16) + ('xUS Opp Value'!$E$4:$E$2041="") > 0 ), 'xUS Opp Value'!H$4:H$2041/'xUS Opp Value'!$J$4:$J$2041, 0)),"")} | U16: {=IFERROR(SUMPRODUCT('xUS Opp Value'!I$4:I$2041, --('xUS Opp Value'!$J$4:$J$2041>0), --( ('xUS Opp Value'!$E$4:$E$2041=$L16) + ('xUS Opp Value'!$E$4:$E$2041="") > 0 )) / SUMPRODUCT(IF( ('xUS Opp Value'!$J$4:$J$2041>0) * ( ('xUS Opp Value'!$E$4:$E$2041=$L16) + ('xUS Opp Value'!$E$4:$E$2041="") > 0 ), 'xUS Opp Value'!I$4:I$2041/'xUS Opp Value'!$J$4:$J$2041, 0)),"")}
A17: CH EQ | B17: Switzerland | C17: =SUMIF('xUS Opp Value'!E:E,'Portfolio Metrics '!B17,'xUS Opp Value'!G:G)/100 -> 0.05 | D17: =SUMIF('xUS Opp Value'!E:E,'Portfolio Metrics '!B17,'xUS Opp Value'!H:H)/100 -> 0.049099167 | E17: =SUMIF('xUS Opp Value'!E:E,'Portfolio Metrics '!B17,'xUS Opp Value'!I:I)/100 -> 0.048 | F17: =INDEX(Algo!$D:$D,MATCH('Portfolio Metrics '!A17,Algo!A:A,0)) -> 0.05 | G17: =C17-E17 -> 0.002 | H17: =C17-F17 -> 0 | I17: =INDEX(#REF!,MATCH('Portfolio Metrics '!A17,#REF!,0)) -> #REF! | J17: =C17-I17 -> #REF! | L17: Switzerland | M17: {=IFERROR(SUMPRODUCT('xUS Opp Value'!G$4:G$2041, --('xUS Opp Value'!$L$4:$L$2041>0), --( ('xUS Opp Value'!$E$4:$E$2041=$L17) + ('xUS Opp Value'!$E$4:$E$2041="") > 0 )) / SUMPRODUCT(IF( ('xUS Opp Value'!$L$4:$L$2041>0) * ( ('xUS Opp Value'!$E$4:$E$2041=$L17) + ('xUS Opp Value'!$E$4:$E$2041="") > 0 ), 'xUS Opp Value'!G$4:G$2041/'xUS Opp Value'!$L$4:$L$2041, 0)),"")} | N17: {=IFERROR(SUMPRODUCT('xUS Opp Value'!H$4:H$2041, --('xUS Opp Value'!$L$4:$L$2041>0), --( ('xUS Opp Value'!$E$4:$E$2041=$L17) + ('xUS Opp Value'!$E$4:$E$2041="") > 0 )) / SUMPRODUCT(IF( ('xUS Opp Value'!$L$4:$L$2041>0) * ( ('xUS Opp Value'!$E$4:$E$2041=$L17) + ('xUS Opp Value'!$E$4:$E$2041="") > 0 ), 'xUS Opp Value'!H$4:H$2041/'xUS Opp Value'!$L$4:$L$2041, 0)),"")} | O17: {=IFERROR(SUMPRODUCT('xUS Opp Value'!I$4:I$2041, --('xUS Opp Value'!$L$4:$L$2041>0), --( ('xUS Opp Value'!$E$4:$E$2041=$L17) + ('xUS Opp Value'!$E$4:$E$2041="") > 0 )) / SUMPRODUCT(IF( ('xUS Opp Value'!$L$4:$L$2041>0) * ( ('xUS Opp Value'!$E$4:$E$2041=$L17) + ('xUS Opp Value'!$E$4:$E$2041="") > 0 ), 'xUS Opp Value'!I$4:I$2041/'xUS Opp Value'!$L$4:$L$2041, 0)),"")} | P17: =IFERROR((1/S17)-1,"") | Q17: =IFERROR((1/T17)-1,"") | R17: =IFERROR((1/U17)-1,"") | S17: {=IFERROR(SUMPRODUCT('xUS Opp Value'!G$4:G$2041, --('xUS Opp Value'!$J$4:$J$2041>0), --( ('xUS Opp Value'!$E$4:$E$2041=$L17) + ('xUS Opp Value'!$E$4:$E$2041="") > 0 )) / SUMPRODUCT(IF( ('xUS Opp Value'!$J$4:$J$2041>0) * ( ('xUS Opp Value'!$E$4:$E$2041=$L17) + ('xUS Opp Value'!$E$4:$E$2041="") > 0 ), 'xUS Opp Value'!G$4:G$2041/'xUS Opp Value'!$J$4:$J$2041, 0)),"")} | T17: {=IFERROR(SUMPRODUCT('xUS Opp Value'!H$4:H$2041, --('xUS Opp Value'!$J$4:$J$2041>0), --( ('xUS Opp Value'!$E$4:$E$2041=$L17) + ('xUS Opp Value'!$E$4:$E$2041="") > 0 )) / SUMPRODUCT(IF( ('xUS Opp Value'!$J$4:$J$2041>0) * ( ('xUS Opp Value'!$E$4:$E$2041=$L17) + ('xUS Opp Value'!$E$4:$E$2041="") > 0 ), 'xUS Opp Value'!H$4:H$2041/'xUS Opp Value'!$J$4:$J$2041, 0)),"")} | U17: {=IFERROR(SUMPRODUCT('xUS Opp Value'!I$4:I$2041, --('xUS Opp Value'!$J$4:$J$2041>0), --( ('xUS Opp Value'!$E$4:$E$2041=$L17) + ('xUS Opp Value'!$E$4:$E$2041="") > 0 )) / SUMPRODUCT(IF( ('xUS Opp Value'!$J$4:$J$2041>0) * ( ('xUS Opp Value'!$E$4:$E$2041=$L17) + ('xUS Opp Value'!$E$4:$E$2041="") > 0 ), 'xUS Opp Value'!I$4:I$2041/'xUS Opp Value'!$J$4:$J$2041, 0)),"")}
A18: FR EQ | B18: France | C18: =SUMIF('xUS Opp Value'!E:E,'Portfolio Metrics '!B18,'xUS Opp Value'!G:G)/100 -> 0.0875 | D18: =SUMIF('xUS Opp Value'!E:E,'Portfolio Metrics '!B18,'xUS Opp Value'!H:H)/100 -> 0.086059471 | E18: =SUMIF('xUS Opp Value'!E:E,'Portfolio Metrics '!B18,'xUS Opp Value'!I:I)/100 -> 0.0539 | F18: =INDEX(Algo!$D:$D,MATCH('Portfolio Metrics '!A18,Algo!A:A,0)) -> 0.0546 | G18: =C18-E18 -> 0.0336 | H18: =C18-F18 -> 0.0329 | I18: =INDEX(#REF!,MATCH('Portfolio Metrics '!A18,#REF!,0)) -> #REF! | J18: =C18-I18 -> #REF! | L18: France | M18: {=IFERROR(SUMPRODUCT('xUS Opp Value'!G$4:G$2041, --('xUS Opp Value'!$L$4:$L$2041>0), --( ('xUS Opp Value'!$E$4:$E$2041=$L18) + ('xUS Opp Value'!$E$4:$E$2041="") > 0 )) / SUMPRODUCT(IF( ('xUS Opp Value'!$L$4:$L$2041>0) * ( ('xUS Opp Value'!$E$4:$E$2041=$L18) + ('xUS Opp Value'!$E$4:$E$2041="") > 0 ), 'xUS Opp Value'!G$4:G$2041/'xUS Opp Value'!$L$4:$L$2041, 0)),"")} | N18: {=IFERROR(SUMPRODUCT('xUS Opp Value'!H$4:H$2041, --('xUS Opp Value'!$L$4:$L$2041>0), --( ('xUS Opp Value'!$E$4:$E$2041=$L18) + ('xUS Opp Value'!$E$4:$E$2041="") > 0 )) / SUMPRODUCT(IF( ('xUS Opp Value'!$L$4:$L$2041>0) * ( ('xUS Opp Value'!$E$4:$E$2041=$L18) + ('xUS Opp Value'!$E$4:$E$2041="") > 0 ), 'xUS Opp Value'!H$4:H$2041/'xUS Opp Value'!$L$4:$L$2041, 0)),"")} | O18: {=IFERROR(SUMPRODUCT('xUS Opp Value'!I$4:I$2041, --('xUS Opp Value'!$L$4:$L$2041>0), --( ('xUS Opp Value'!$E$4:$E$2041=$L18) + ('xUS Opp Value'!$E$4:$E$2041="") > 0 )) / SUMPRODUCT(IF( ('xUS Opp Value'!$L$4:$L$2041>0) * ( ('xUS Opp Value'!$E$4:$E$2041=$L18) + ('xUS Opp Value'!$E$4:$E$2041="") > 0 ), 'xUS Opp Value'!I$4:I$2041/'xUS Opp Value'!$L$4:$L$2041, 0)),"")} | P18: =IFERROR((1/S18)-1,"") | Q18: =IFERROR((1/T18)-1,"") | R18: =IFERROR((1/U18)-1,"") | S18: {=IFERROR(SUMPRODUCT('xUS Opp Value'!G$4:G$2041, --('xUS Opp Value'!$J$4:$J$2041>0), --( ('xUS Opp Value'!$E$4:$E$2041=$L18) + ('xUS Opp Value'!$E$4:$E$2041="") > 0 )) / SUMPRODUCT(IF( ('xUS Opp Value'!$J$4:$J$2041>0) * ( ('xUS Opp Value'!$E$4:$E$2041=$L18) + ('xUS Opp Value'!$E$4:$E$2041="") > 0 ), 'xUS Opp Value'!G$4:G$2041/'xUS Opp Value'!$J$4:$J$2041, 0)),"")} | T18: {=IFERROR(SUMPRODUCT('xUS Opp Value'!H$4:H$2041, --('xUS Opp Value'!$J$4:$J$2041>0), --( ('xUS Opp Value'!$E$4:$E$2041=$L18) + ('xUS Opp Value'!$E$4:$E$2041="") > 0 )) / SUMPRODUCT(IF( ('xUS Opp Value'!$J$4:$J$2041>0) * ( ('xUS Opp Value'!$E$4:$E$2041=$L18) + ('xUS Opp Value'!$E$4:$E$2041="") > 0 ), 'xUS Opp Value'!H$4:H$2041/'xUS Opp Value'!$J$4:$J$2041, 0)),"")} | U18: {=IFERROR(SUMPRODUCT('xUS Opp Value'!I$4:I$2041, --('xUS Opp Value'!$J$4:$J$2041>0), --( ('xUS Opp Value'!$E$4:$E$2041=$L18) + ('xUS Opp Value'!$E$4:$E$2041="") > 0 )) / SUMPRODUCT(IF( ('xUS Opp Value'!$J$4:$J$2041>0) * ( ('xUS Opp Value'!$E$4:$E$2041=$L18) + ('xUS Opp Value'!$E$4:$E$2041="") > 0 ), 'xUS Opp Value'!I$4:I$2041/'xUS Opp Value'!$J$4:$J$2041, 0)),"")}
A19: AU EQ | B19: Australia | C19: =SUMIF('xUS Opp Value'!E:E,'Portfolio Metrics '!B19,'xUS Opp Value'!G:G)/100 -> 0.03 | D19: =SUMIF('xUS Opp Value'!E:E,'Portfolio Metrics '!B19,'xUS Opp Value'!H:H)/100 -> 0.032184788 | E19: =SUMIF('xUS Opp Value'!E:E,'Portfolio Metrics '!B19,'xUS Opp Value'!I:I)/100 -> 0.0404 | F19: =INDEX(Algo!$D:$D,MATCH('Portfolio Metrics '!A19,Algo!A:A,0)) -> 0.0399 | G19: =C19-E19 -> -0.0104 | H19: =C19-F19 -> -0.0099 | I19: =INDEX(#REF!,MATCH('Portfolio Metrics '!A19,#REF!,0)) -> #REF! | J19: =C19-I19 -> #REF! | L19: Australia | M19: {=IFERROR(SUMPRODUCT('xUS Opp Value'!G$4:G$2041, --('xUS Opp Value'!$L$4:$L$2041>0), --( ('xUS Opp Value'!$E$4:$E$2041=$L19) + ('xUS Opp Value'!$E$4:$E$2041="") > 0 )) / SUMPRODUCT(IF( ('xUS Opp Value'!$L$4:$L$2041>0) * ( ('xUS Opp Value'!$E$4:$E$2041=$L19) + ('xUS Opp Value'!$E$4:$E$2041="") > 0 ), 'xUS Opp Value'!G$4:G$2041/'xUS Opp Value'!$L$4:$L$2041, 0)),"")} | N19: {=IFERROR(SUMPRODUCT('xUS Opp Value'!H$4:H$2041, --('xUS Opp Value'!$L$4:$L$2041>0), --( ('xUS Opp Value'!$E$4:$E$2041=$L19) + ('xUS Opp Value'!$E$4:$E$2041="") > 0 )) / SUMPRODUCT(IF( ('xUS Opp Value'!$L$4:$L$2041>0) * ( ('xUS Opp Value'!$E$4:$E$2041=$L19) + ('xUS Opp Value'!$E$4:$E$2041="") > 0 ), 'xUS Opp Value'!H$4:H$2041/'xUS Opp Value'!$L$4:$L$2041, 0)),"")} | O19: {=IFERROR(SUMPRODUCT('xUS Opp Value'!I$4:I$2041, --('xUS Opp Value'!$L$4:$L$2041>0), --( ('xUS Opp Value'!$E$4:$E$2041=$L19) + ('xUS Opp Value'!$E$4:$E$2041="") > 0 )) / SUMPRODUCT(IF( ('xUS Opp Value'!$L$4:$L$2041>0) * ( ('xUS Opp Value'!$E$4:$E$2041=$L19) + ('xUS Opp Value'!$E$4:$E$2041="") > 0 ), 'xUS Opp Value'!I$4:I$2041/'xUS Opp Value'!$L$4:$L$2041, 0)),"")} | P19: =IFERROR((1/S19)-1,"") | Q19: =IFERROR((1/T19)-1,"") | R19: =IFERROR((1/U19)-1,"") | S19: {=IFERROR(SUMPRODUCT('xUS Opp Value'!G$4:G$2041, --('xUS Opp Value'!$J$4:$J$2041>0), --( ('xUS Opp Value'!$E$4:$E$2041=$L19) + ('xUS Opp Value'!$E$4:$E$2041="") > 0 )) / SUMPRODUCT(IF( ('xUS Opp Value'!$J$4:$J$2041>0) * ( ('xUS Opp Value'!$E$4:$E$2041=$L19) + ('xUS Opp Value'!$E$4:$E$2041="") > 0 ), 'xUS Opp Value'!G$4:G$2041/'xUS Opp Value'!$J$4:$J$2041, 0)),"")} | T19: {=IFERROR(SUMPRODUCT('xUS Opp Value'!H$4:H$2041, --('xUS Opp Value'!$J$4:$J$2041>0), --( ('xUS Opp Value'!$E$4:$E$2041=$L19) + ('xUS Opp Value'!$E$4:$E$2041="") > 0 )) / SUMPRODUCT(IF( ('xUS Opp Value'!$J$4:$J$2041>0) * ( ('xUS Opp Value'!$E$4:$E$2041=$L19) + ('xUS Opp Value'!$E$4:$E$2041="") > 0 ), 'xUS Opp Value'!H$4:H$2041/'xUS Opp Value'!$J$4:$J$2041, 0)),"")} | U19: {=IFERROR(SUMPRODUCT('xUS Opp Value'!I$4:I$2041, --('xUS Opp Value'!$J$4:$J$2041>0), --( ('xUS Opp Value'!$E$4:$E$2041=$L19) + ('xUS Opp Value'!$E$4:$E$2041="") > 0 )) / SUMPRODUCT(IF( ('xUS Opp Value'!$J$4:$J$2041>0) * ( ('xUS Opp Value'!$E$4:$E$2041=$L19) + ('xUS Opp Value'!$E$4:$E$2041="") > 0 ), 'xUS Opp Value'!I$4:I$2041/'xUS Opp Value'!$J$4:$J$2041, 0)),"")}
A20: DE EQ | B20: Germany | C20: =SUMIF('xUS Opp Value'!E:E,'Portfolio Metrics '!B20,'xUS Opp Value'!G:G)/100 -> 0.06 | D20: =SUMIF('xUS Opp Value'!E:E,'Portfolio Metrics '!B20,'xUS Opp Value'!H:H)/100 -> 0.062956637 | E20: =SUMIF('xUS Opp Value'!E:E,'Portfolio Metrics '!B20,'xUS Opp Value'!I:I)/100 -> 0.0508 | F20: =INDEX(Algo!$D:$D,MATCH('Portfolio Metrics '!A20,Algo!A:A,0)) -> 0.0487 | G20: =C20-E20 -> 0.0092 | H20: =C20-F20 -> 0.0113 | I20: =INDEX(#REF!,MATCH('Portfolio Metrics '!A20,#REF!,0)) -> #REF! | J20: =C20-I20 -> #REF! | L20: Germany | M20: {=IFERROR(SUMPRODUCT('xUS Opp Value'!G$4:G$2041, --('xUS Opp Value'!$L$4:$L$2041>0), --( ('xUS Opp Value'!$E$4:$E$2041=$L20) + ('xUS Opp Value'!$E$4:$E$2041="") > 0 )) / SUMPRODUCT(IF( ('xUS Opp Value'!$L$4:$L$2041>0) * ( ('xUS Opp Value'!$E$4:$E$2041=$L20) + ('xUS Opp Value'!$E$4:$E$2041="") > 0 ), 'xUS Opp Value'!G$4:G$2041/'xUS Opp Value'!$L$4:$L$2041, 0)),"")} | N20: {=IFERROR(SUMPRODUCT('xUS Opp Value'!H$4:H$2041, --('xUS Opp Value'!$L$4:$L$2041>0), --( ('xUS Opp Value'!$E$4:$E$2041=$L20) + ('xUS Opp Value'!$E$4:$E$2041="") > 0 )) / SUMPRODUCT(IF( ('xUS Opp Value'!$L$4:$L$2041>0) * ( ('xUS Opp Value'!$E$4:$E$2041=$L20) + ('xUS Opp Value'!$E$4:$E$2041="") > 0 ), 'xUS Opp Value'!H$4:H$2041/'xUS Opp Value'!$L$4:$L$2041, 0)),"")} | O20: {=IFERROR(SUMPRODUCT('xUS Opp Value'!I$4:I$2041, --('xUS Opp Value'!$L$4:$L$2041>0), --( ('xUS Opp Value'!$E$4:$E$2041=$L20) + ('xUS Opp Value'!$E$4:$E$2041="") > 0 )) / SUMPRODUCT(IF( ('xUS Opp Value'!$L$4:$L$2041>0) * ( ('xUS Opp Value'!$E$4:$E$2041=$L20) + ('xUS Opp Value'!$E$4:$E$2041="") > 0 ), 'xUS Opp Value'!I$4:I$2041/'xUS Opp Value'!$L$4:$L$2041, 0)),"")} | P20: =IFERROR((1/S20)-1,"") | Q20: =IFERROR((1/T20)-1,"") | R20: =IFERROR((1/U20)-1,"") | S20: {=IFERROR(SUMPRODUCT('xUS Opp Value'!G$4:G$2041, --('xUS Opp Value'!$J$4:$J$2041>0), --( ('xUS Opp Value'!$E$4:$E$2041=$L20) + ('xUS Opp Value'!$E$4:$E$2041="") > 0 )) / SUMPRODUCT(IF( ('xUS Opp Value'!$J$4:$J$2041>0) * ( ('xUS Opp Value'!$E$4:$E$2041=$L20) + ('xUS Opp Value'!$E$4:$E$2041="") > 0 ), 'xUS Opp Value'!G$4:G$2041/'xUS Opp Value'!$J$4:$J$2041, 0)),"")} | T20: {=IFERROR(SUMPRODUCT('xUS Opp Value'!H$4:H$2041, --('xUS Opp Value'!$J$4:$J$2041>0), --( ('xUS Opp Value'!$E$4:$E$2041=$L20) + ('xUS Opp Value'!$E$4:$E$2041="") > 0 )) / SUMPRODUCT(IF( ('xUS Opp Value'!$J$4:$J$2041>0) * ( ('xUS Opp Value'!$E$4:$E$2041=$L20) + ('xUS Opp Value'!$E$4:$E$2041="") > 0 ), 'xUS Opp Value'!H$4:H$2041/'xUS Opp Value'!$J$4:$J$2041, 0)),"")} | U20: {=IFERROR(SUMPRODUCT('xUS Opp Value'!I$4:I$2041, --('xUS Opp Value'!$J$4:$J$2041>0), --( ('xUS Opp Value'!$E$4:$E$2041=$L20) + ('xUS Opp Value'!$E$4:$E$2041="") > 0 )) / SUMPRODUCT(IF( ('xUS Opp Value'!$J$4:$J$2041>0) * ( ('xUS Opp Value'!$E$4:$E$2041=$L20) + ('xUS Opp Value'!$E$4:$E$2041="") > 0 ), 'xUS Opp Value'!I$4:I$2041/'xUS Opp Value'!$J$4:$J$2041, 0)),"")}
A21: AT EQ | B21: Austria | C21: =SUMIF('xUS Opp Value'!E:E,'Portfolio Metrics '!B21,'xUS Opp Value'!G:G)/100 -> 0 | D21: =SUMIF('xUS Opp Value'!E:E,'Portfolio Metrics '!B21,'xUS Opp Value'!H:H)/100 -> 0 | E21: =SUMIF('xUS Opp Value'!E:E,'Portfolio Metrics '!B21,'xUS Opp Value'!I:I)/100 -> 0.0021 | F21: =INDEX(Algo!$D:$D,MATCH('Portfolio Metrics '!A21,Algo!A:A,0)) -> 0.0104 | G21: =C21-E21 -> -0.0021 | H21: =C21-F21 -> -0.0104 | I21: =INDEX(#REF!,MATCH('Portfolio Metrics '!A21,#REF!,0)) -> #REF! | J21: =C21-I21 -> #REF! | L21: Austria | M21: {=IFERROR(SUMPRODUCT('xUS Opp Value'!G$4:G$2041, --('xUS Opp Value'!$L$4:$L$2041>0), --( ('xUS Opp Value'!$E$4:$E$2041=$L21) + ('xUS Opp Value'!$E$4:$E$2041="") > 0 )) / SUMPRODUCT(IF( ('xUS Opp Value'!$L$4:$L$2041>0) * ( ('xUS Opp Value'!$E$4:$E$2041=$L21) + ('xUS Opp Value'!$E$4:$E$2041="") > 0 ), 'xUS Opp Value'!G$4:G$2041/'xUS Opp Value'!$L$4:$L$2041, 0)),"")} | N21: {=IFERROR(SUMPRODUCT('xUS Opp Value'!H$4:H$2041, --('xUS Opp Value'!$L$4:$L$2041>0), --( ('xUS Opp Value'!$E$4:$E$2041=$L21) + ('xUS Opp Value'!$E$4:$E$2041="") > 0 )) / SUMPRODUCT(IF( ('xUS Opp Value'!$L$4:$L$2041>0) * ( ('xUS Opp Value'!$E$4:$E$2041=$L21) + ('xUS Opp Value'!$E$4:$E$2041="") > 0 ), 'xUS Opp Value'!H$4:H$2041/'xUS Opp Value'!$L$4:$L$2041, 0)),"")} | O21: {=IFERROR(SUMPRODUCT('xUS Opp Value'!I$4:I$2041, --('xUS Opp Value'!$L$4:$L$2041>0), --( ('xUS Opp Value'!$E$4:$E$2041=$L21) + ('xUS Opp Value'!$E$4:$E$2041="") > 0 )) / SUMPRODUCT(IF( ('xUS Opp Value'!$L$4:$L$2041>0) * ( ('xUS Opp Value'!$E$4:$E$2041=$L21) + ('xUS Opp Value'!$E$4:$E$2041="") > 0 ), 'xUS Opp Value'!I$4:I$2041/'xUS Opp Value'!$L$4:$L$2041, 0)),"")} | P21: =IFERROR((1/S21)-1,"") | Q21: =IFERROR((1/T21)-1,"") | R21: =IFERROR((1/U21)-1,"") | S21: {=IFERROR(SUMPRODUCT('xUS Opp Value'!G$4:G$2041, --('xUS Opp Value'!$J$4:$J$2041>0), --( ('xUS Opp Value'!$E$4:$E$2041=$L21) + ('xUS Opp Value'!$E$4:$E$2041="") > 0 )) / SUMPRODUCT(IF( ('xUS Opp Value'!$J$4:$J$2041>0) * ( ('xUS Opp Value'!$E$4:$E$2041=$L21) + ('xUS Opp Value'!$E$4:$E$2041="") > 0 ), 'xUS Opp Value'!G$4:G$2041/'xUS Opp Value'!$J$4:$J$2041, 0)),"")} | T21: {=IFERROR(SUMPRODUCT('xUS Opp Value'!H$4:H$2041, --('xUS Opp Value'!$J$4:$J$2041>0), --( ('xUS Opp Value'!$E$4:$E$2041=$L21) + ('xUS Opp Value'!$E$4:$E$2041="") > 0 )) / SUMPRODUCT(IF( ('xUS Opp Value'!$J$4:$J$2041>0) * ( ('xUS Opp Value'!$E$4:$E$2041=$L21) + ('xUS Opp Value'!$E$4:$E$2041="") > 0 ), 'xUS Opp Value'!H$4:H$2041/'xUS Opp Value'!$J$4:$J$2041, 0)),"")} | U21: {=IFERROR(SUMPRODUCT('xUS Opp Value'!I$4:I$2041, --('xUS Opp Value'!$J$4:$J$2041>0), --( ('xUS Opp Value'!$E$4:$E$2041=$L21) + ('xUS Opp Value'!$E$4:$E$2041="") > 0 )) / SUMPRODUCT(IF( ('xUS Opp Value'!$J$4:$J$2041>0) * ( ('xUS Opp Value'!$E$4:$E$2041=$L21) + ('xUS Opp Value'!$E$4:$E$2041="") > 0 ), 'xUS Opp Value'!I$4:I$2041/'xUS Opp Value'!$J$4:$J$2041, 0)),"")}
A22: BE EQ | B22: Belgium | C22: =SUMIF('xUS Opp Value'!E:E,'Portfolio Metrics '!B22,'xUS Opp Value'!G:G)/100 -> 0 | D22: =SUMIF('xUS Opp Value'!E:E,'Portfolio Metrics '!B22,'xUS Opp Value'!H:H)/100 -> 0 | E22: =SUMIF('xUS Opp Value'!E:E,'Portfolio Metrics '!B22,'xUS Opp Value'!I:I)/100 -> 0.0055 | F22: =INDEX(Algo!$D:$D,MATCH('Portfolio Metrics '!A22,Algo!A:A,0)) -> 0.0156 | G22: =C22-E22 -> -0.0055 | H22: =C22-F22 -> -0.0156 | I22: =INDEX(#REF!,MATCH('Portfolio Metrics '!A22,#REF!,0)) -> #REF! | J22: =C22-I22 -> #REF! | L22: Belgium | M22: {=IFERROR(SUMPRODUCT('xUS Opp Value'!G$4:G$2041, --('xUS Opp Value'!$L$4:$L$2041>0), --( ('xUS Opp Value'!$E$4:$E$2041=$L22) + ('xUS Opp Value'!$E$4:$E$2041="") > 0 )) / SUMPRODUCT(IF( ('xUS Opp Value'!$L$4:$L$2041>0) * ( ('xUS Opp Value'!$E$4:$E$2041=$L22) + ('xUS Opp Value'!$E$4:$E$2041="") > 0 ), 'xUS Opp Value'!G$4:G$2041/'xUS Opp Value'!$L$4:$L$2041, 0)),"")} | N22: {=IFERROR(SUMPRODUCT('xUS Opp Value'!H$4:H$2041, --('xUS Opp Value'!$L$4:$L$2041>0), --( ('xUS Opp Value'!$E$4:$E$2041=$L22) + ('xUS Opp Value'!$E$4:$E$2041="") > 0 )) / SUMPRODUCT(IF( ('xUS Opp Value'!$L$4:$L$2041>0) * ( ('xUS Opp Value'!$E$4:$E$2041=$L22) + ('xUS Opp Value'!$E$4:$E$2041="") > 0 ), 'xUS Opp Value'!H$4:H$2041/'xUS Opp Value'!$L$4:$L$2041, 0)),"")} | O22: {=IFERROR(SUMPRODUCT('xUS Opp Value'!I$4:I$2041, --('xUS Opp Value'!$L$4:$L$2041>0), --( ('xUS Opp Value'!$E$4:$E$2041=$L22) + ('xUS Opp Value'!$E$4:$E$2041="") > 0 )) / SUMPRODUCT(IF( ('xUS Opp Value'!$L$4:$L$2041>0) * ( ('xUS Opp Value'!$E$4:$E$2041=$L22) + ('xUS Opp Value'!$E$4:$E$2041="") > 0 ), 'xUS Opp Value'!I$4:I$2041/'xUS Opp Value'!$L$4:$L$2041, 0)),"")} | P22: =IFERROR((1/S22)-1,"") | Q22: =IFERROR((1/T22)-1,"") | R22: =IFERROR((1/U22)-1,"") | S22: {=IFERROR(SUMPRODUCT('xUS Opp Value'!G$4:G$2041, --('xUS Opp Value'!$J$4:$J$2041>0), --( ('xUS Opp Value'!$E$4:$E$2041=$L22) + ('xUS Opp Value'!$E$4:$E$2041="") > 0 )) / SUMPRODUCT(IF( ('xUS Opp Value'!$J$4:$J$2041>0) * ( ('xUS Opp Value'!$E$4:$E$2041=$L22) + ('xUS Opp Value'!$E$4:$E$2041="") > 0 ), 'xUS Opp Value'!G$4:G$2041/'xUS Opp Value'!$J$4:$J$2041, 0)),"")} | T22: {=IFERROR(SUMPRODUCT('xUS Opp Value'!H$4:H$2041, --('xUS Opp Value'!$J$4:$J$2041>0), --( ('xUS Opp Value'!$E$4:$E$2041=$L22) + ('xUS Opp Value'!$E$4:$E$2041="") > 0 )) / SUMPRODUCT(IF( ('xUS Opp Value'!$J$4:$J$2041>0) * ( ('xUS Opp Value'!$E$4:$E$2041=$L22) + ('xUS Opp Value'!$E$4:$E$2041="") > 0 ), 'xUS Opp Value'!H$4:H$2041/'xUS Opp Value'!$J$4:$J$2041, 0)),"")} | U22: {=IFERROR(SUMPRODUCT('xUS Opp Value'!I$4:I$2041, --('xUS Opp Value'!$J$4:$J$2041>0), --( ('xUS Opp Value'!$E$4:$E$2041=$L22) + ('xUS Opp Value'!$E$4:$E$2041="") > 0 )) / SUMPRODUCT(IF( ('xUS Opp Value'!$J$4:$J$2041>0) * ( ('xUS Opp Value'!$E$4:$E$2041=$L22) + ('xUS Opp Value'!$E$4:$E$2041="") > 0 ), 'xUS Opp Value'!I$4:I$2041/'xUS Opp Value'!$J$4:$J$2041, 0)),"")}
A23: DK EQ | B23: Denmark | C23: =SUMIF('xUS Opp Value'!E:E,'Portfolio Metrics '!B23,'xUS Opp Value'!G:G)/100 -> 0.0225 | D23: =SUMIF('xUS Opp Value'!E:E,'Portfolio Metrics '!B23,'xUS Opp Value'!H:H)/100 -> 0.015934018 | E23: =SUMIF('xUS Opp Value'!E:E,'Portfolio Metrics '!B23,'xUS Opp Value'!I:I)/100 -> 0.0095 | F23: =INDEX(Algo!$D:$D,MATCH('Portfolio Metrics '!A23,Algo!A:A,0)) -> 0.0345 | G23: =C23-E23 -> 0.013 | H23: =C23-F23 -> -0.012 | I23: =INDEX(#REF!,MATCH('Portfolio Metrics '!A23,#REF!,0)) -> #REF! | J23: =C23-I23 -> #REF! | L23: Denmark | M23: {=IFERROR(SUMPRODUCT('xUS Opp Value'!G$4:G$2041, --('xUS Opp Value'!$L$4:$L$2041>0), --( ('xUS Opp Value'!$E$4:$E$2041=$L23) + ('xUS Opp Value'!$E$4:$E$2041="") > 0 )) / SUMPRODUCT(IF( ('xUS Opp Value'!$L$4:$L$2041>0) * ( ('xUS Opp Value'!$E$4:$E$2041=$L23) + ('xUS Opp Value'!$E$4:$E$2041="") > 0 ), 'xUS Opp Value'!G$4:G$2041/'xUS Opp Value'!$L$4:$L$2041, 0)),"")} | N23: {=IFERROR(SUMPRODUCT('xUS Opp Value'!H$4:H$2041, --('xUS Opp Value'!$L$4:$L$2041>0), --( ('xUS Opp Value'!$E$4:$E$2041=$L23) + ('xUS Opp Value'!$E$4:$E$2041="") > 0 )) / SUMPRODUCT(IF( ('xUS Opp Value'!$L$4:$L$2041>0) * ( ('xUS Opp Value'!$E$4:$E$2041=$L23) + ('xUS Opp Value'!$E$4:$E$2041="") > 0 ), 'xUS Opp Value'!H$4:H$2041/'xUS Opp Value'!$L$4:$L$2041, 0)),"")} | O23: {=IFERROR(SUMPRODUCT('xUS Opp Value'!I$4:I$2041, --('xUS Opp Value'!$L$4:$L$2041>0), --( ('xUS Opp Value'!$E$4:$E$2041=$L23) + ('xUS Opp Value'!$E$4:$E$2041="") > 0 )) / SUMPRODUCT(IF( ('xUS Opp Value'!$L$4:$L$2041>0) * ( ('xUS Opp Value'!$E$4:$E$2041=$L23) + ('xUS Opp Value'!$E$4:$E$2041="") > 0 ), 'xUS Opp Value'!I$4:I$2041/'xUS Opp Value'!$L$4:$L$2041, 0)),"")} | P23: =IFERROR((1/S23)-1,"") | Q23: =IFERROR((1/T23)-1,"") | R23: =IFERROR((1/U23)-1,"") | S23: {=IFERROR(SUMPRODUCT('xUS Opp Value'!G$4:G$2041, --('xUS Opp Value'!$J$4:$J$2041>0), --( ('xUS Opp Value'!$E$4:$E$2041=$L23) + ('xUS Opp Value'!$E$4:$E$2041="") > 0 )) / SUMPRODUCT(IF( ('xUS Opp Value'!$J$4:$J$2041>0) * ( ('xUS Opp Value'!$E$4:$E$2041=$L23) + ('xUS Opp Value'!$E$4:$E$2041="") > 0 ), 'xUS Opp Value'!G$4:G$2041/'xUS Opp Value'!$J$4:$J$2041, 0)),"")} | T23: {=IFERROR(SUMPRODUCT('xUS Opp Value'!H$4:H$2041, --('xUS Opp Value'!$J$4:$J$2041>0), --( ('xUS Opp Value'!$E$4:$E$2041=$L23) + ('xUS Opp Value'!$E$4:$E$2041="") > 0 )) / SUMPRODUCT(IF( ('xUS Opp Value'!$J$4:$J$2041>0) * ( ('xUS Opp Value'!$E$4:$E$2041=$L23) + ('xUS Opp Value'!$E$4:$E$2041="") > 0 ), 'xUS Opp Value'!H$4:H$2041/'xUS Opp Value'!$J$4:$J$2041, 0)),"")} | U23: {=IFERROR(SUMPRODUCT('xUS Opp Value'!I$4:I$2041, --('xUS Opp Value'!$J$4:$J$2041>0), --( ('xUS Opp Value'!$E$4:$E$2041=$L23) + ('xUS Opp Value'!$E$4:$E$2041="") > 0 )) / SUMPRODUCT(IF( ('xUS Opp Value'!$J$4:$J$2041>0) * ( ('xUS Opp Value'!$E$4:$E$2041=$L23) + ('xUS Opp Value'!$E$4:$E$2041="") > 0 ), 'xUS Opp Value'!I$4:I$2041/'xUS Opp Value'!$J$4:$J$2041, 0)),"")}
A24: ES EQ | B24: Spain | C24: =SUMIF('xUS Opp Value'!E:E,'Portfolio Metrics '!B24,'xUS Opp Value'!G:G)/100 -> 0.0125 | D24: =SUMIF('xUS Opp Value'!E:E,'Portfolio Metrics '!B24,'xUS Opp Value'!H:H)/100 -> 0.012613893 | E24: =SUMIF('xUS Opp Value'!E:E,'Portfolio Metrics '!B24,'xUS Opp Value'!I:I)/100 -> 0.021 | F24: =INDEX(Algo!$D:$D,MATCH('Portfolio Metrics '!A24,Algo!A:A,0)) -> 0.0145 | G24: =C24-E24 -> -0.0085 | H24: =C24-F24 -> -0.002 | I24: =INDEX(#REF!,MATCH('Portfolio Metrics '!A24,#REF!,0)) -> #REF! | J24: =C24-I24 -> #REF! | L24: Spain | M24: {=IFERROR(SUMPRODUCT('xUS Opp Value'!G$4:G$2041, --('xUS Opp Value'!$L$4:$L$2041>0), --( ('xUS Opp Value'!$E$4:$E$2041=$L24) + ('xUS Opp Value'!$E$4:$E$2041="") > 0 )) / SUMPRODUCT(IF( ('xUS Opp Value'!$L$4:$L$2041>0) * ( ('xUS Opp Value'!$E$4:$E$2041=$L24) + ('xUS Opp Value'!$E$4:$E$2041="") > 0 ), 'xUS Opp Value'!G$4:G$2041/'xUS Opp Value'!$L$4:$L$2041, 0)),"")} | N24: {=IFERROR(SUMPRODUCT('xUS Opp Value'!H$4:H$2041, --('xUS Opp Value'!$L$4:$L$2041>0), --( ('xUS Opp Value'!$E$4:$E$2041=$L24) + ('xUS Opp Value'!$E$4:$E$2041="") > 0 )) / SUMPRODUCT(IF( ('xUS Opp Value'!$L$4:$L$2041>0) * ( ('xUS Opp Value'!$E$4:$E$2041=$L24) + ('xUS Opp Value'!$E$4:$E$2041="") > 0 ), 'xUS Opp Value'!H$4:H$2041/'xUS Opp Value'!$L$4:$L$2041, 0)),"")} | O24: {=IFERROR(SUMPRODUCT('xUS Opp Value'!I$4:I$2041, --('xUS Opp Value'!$L$4:$L$2041>0), --( ('xUS Opp Value'!$E$4:$E$2041=$L24) + ('xUS Opp Value'!$E$4:$E$2041="") > 0 )) / SUMPRODUCT(IF( ('xUS Opp Value'!$L$4:$L$2041>0) * ( ('xUS Opp Value'!$E$4:$E$2041=$L24) + ('xUS Opp Value'!$E$4:$E$2041="") > 0 ), 'xUS Opp Value'!I$4:I$2041/'xUS Opp Value'!$L$4:$L$2041, 0)),"")} | P24: =IFERROR((1/S24)-1,"") | Q24: =IFERROR((1/T24)-1,"") | R24: =IFERROR((1/U24)-1,"") | S24: {=IFERROR(SUMPRODUCT('xUS Opp Value'!G$4:G$2041, --('xUS Opp Value'!$J$4:$J$2041>0), --( ('xUS Opp Value'!$E$4:$E$2041=$L24) + ('xUS Opp Value'!$E$4:$E$2041="") > 0 )) / SUMPRODUCT(IF( ('xUS Opp Value'!$J$4:$J$2041>0) * ( ('xUS Opp Value'!$E$4:$E$2041=$L24) + ('xUS Opp Value'!$E$4:$E$2041="") > 0 ), 'xUS Opp Value'!G$4:G$2041/'xUS Opp Value'!$J$4:$J$2041, 0)),"")} | T24: {=IFERROR(SUMPRODUCT('xUS Opp Value'!H$4:H$2041, --('xUS Opp Value'!$J$4:$J$2041>0), --( ('xUS Opp Value'!$E$4:$E$2041=$L24) + ('xUS Opp Value'!$E$4:$E$2041="") > 0 )) / SUMPRODUCT(IF( ('xUS Opp Value'!$J$4:$J$2041>0) * ( ('xUS Opp Value'!$E$4:$E$2041=$L24) + ('xUS Opp Value'!$E$4:$E$2041="") > 0 ), 'xUS Opp Value'!H$4:H$2041/'xUS Opp Value'!$J$4:$J$2041, 0)),"")} | U24: {=IFERROR(SUMPRODUCT('xUS Opp Value'!I$4:I$2041, --('xUS Opp Value'!$J$4:$J$2041>0), --( ('xUS Opp Value'!$E$4:$E$2041=$L24) + ('xUS Opp Value'!$E$4:$E$2041="") > 0 )) / SUMPRODUCT(IF( ('xUS Opp Value'!$J$4:$J$2041>0) * ( ('xUS Opp Value'!$E$4:$E$2041=$L24) + ('xUS Opp Value'!$E$4:$E$2041="") > 0 ), 'xUS Opp Value'!I$4:I$2041/'xUS Opp Value'!$J$4:$J$2041, 0)),"")}
A25: FI EQ | B25: Finland | C25: =SUMIF('xUS Opp Value'!E:E,'Portfolio Metrics '!B25,'xUS Opp Value'!G:G)/100 -> 0 | D25: =SUMIF('xUS Opp Value'!E:E,'Portfolio Metrics '!B25,'xUS Opp Value'!H:H)/100 -> 0 | E25: =SUMIF('xUS Opp Value'!E:E,'Portfolio Metrics '!B25,'xUS Opp Value'!I:I)/100 -> 0.0059 | F25: =INDEX(Algo!$D:$D,MATCH('Portfolio Metrics '!A25,Algo!A:A,0)) -> 0.0187 | G25: =C25-E25 -> -0.0059 | H25: =C25-F25 -> -0.0187 | I25: =INDEX(#REF!,MATCH('Portfolio Metrics '!A25,#REF!,0)) -> #REF! | J25: =C25-I25 -> #REF! | L25: Finland | M25: {=IFERROR(SUMPRODUCT('xUS Opp Value'!G$4:G$2041, --('xUS Opp Value'!$L$4:$L$2041>0), --( ('xUS Opp Value'!$E$4:$E$2041=$L25) + ('xUS Opp Value'!$E$4:$E$2041="") > 0 )) / SUMPRODUCT(IF( ('xUS Opp Value'!$L$4:$L$2041>0) * ( ('xUS Opp Value'!$E$4:$E$2041=$L25) + ('xUS Opp Value'!$E$4:$E$2041="") > 0 ), 'xUS Opp Value'!G$4:G$2041/'xUS Opp Value'!$L$4:$L$2041, 0)),"")} | N25: {=IFERROR(SUMPRODUCT('xUS Opp Value'!H$4:H$2041, --('xUS Opp Value'!$L$4:$L$2041>0), --( ('xUS Opp Value'!$E$4:$E$2041=$L25) + ('xUS Opp Value'!$E$4:$E$2041="") > 0 )) / SUMPRODUCT(IF( ('xUS Opp Value'!$L$4:$L$2041>0) * ( ('xUS Opp Value'!$E$4:$E$2041=$L25) + ('xUS Opp Value'!$E$4:$E$2041="") > 0 ), 'xUS Opp Value'!H$4:H$2041/'xUS Opp Value'!$L$4:$L$2041, 0)),"")} | O25: {=IFERROR(SUMPRODUCT('xUS Opp Value'!I$4:I$2041, --('xUS Opp Value'!$L$4:$L$2041>0), --( ('xUS Opp Value'!$E$4:$E$2041=$L25) + ('xUS Opp Value'!$E$4:$E$2041="") > 0 )) / SUMPRODUCT(IF( ('xUS Opp Value'!$L$4:$L$2041>0) * ( ('xUS Opp Value'!$E$4:$E$2041=$L25) + ('xUS Opp Value'!$E$4:$E$2041="") > 0 ), 'xUS Opp Value'!I$4:I$2041/'xUS Opp Value'!$L$4:$L$2041, 0)),"")} | P25: =IFERROR((1/S25)-1,"") | Q25: =IFERROR((1/T25)-1,"") | R25: =IFERROR((1/U25)-1,"") | S25: {=IFERROR(SUMPRODUCT('xUS Opp Value'!G$4:G$2041, --('xUS Opp Value'!$J$4:$J$2041>0), --( ('xUS Opp Value'!$E$4:$E$2041=$L25) + ('xUS Opp Value'!$E$4:$E$2041="") > 0 )) / SUMPRODUCT(IF( ('xUS Opp Value'!$J$4:$J$2041>0) * ( ('xUS Opp Value'!$E$4:$E$2041=$L25) + ('xUS Opp Value'!$E$4:$E$2041="") > 0 ), 'xUS Opp Value'!G$4:G$2041/'xUS Opp Value'!$J$4:$J$2041, 0)),"")} | T25: {=IFERROR(SUMPRODUCT('xUS Opp Value'!H$4:H$2041, --('xUS Opp Value'!$J$4:$J$2041>0), --( ('xUS Opp Value'!$E$4:$E$2041=$L25) + ('xUS Opp Value'!$E$4:$E$2041="") > 0 )) / SUMPRODUCT(IF( ('xUS Opp Value'!$J$4:$J$2041>0) * ( ('xUS Opp Value'!$E$4:$E$2041=$L25) + ('xUS Opp Value'!$E$4:$E$2041="") > 0 ), 'xUS Opp Value'!H$4:H$2041/'xUS Opp Value'!$J$4:$J$2041, 0)),"")} | U25: {=IFERROR(SUMPRODUCT('xUS Opp Value'!I$4:I$2041, --('xUS Opp Value'!$J$4:$J$2041>0), --( ('xUS Opp Value'!$E$4:$E$2041=$L25) + ('xUS Opp Value'!$E$4:$E$2041="") > 0 )) / SUMPRODUCT(IF( ('xUS Opp Value'!$J$4:$J$2041>0) * ( ('xUS Opp Value'!$E$4:$E$2041=$L25) + ('xUS Opp Value'!$E$4:$E$2041="") > 0 ), 'xUS Opp Value'!I$4:I$2041/'xUS Opp Value'!$J$4:$J$2041, 0)),"")}
... A40: BR EQ | B40: Brazil | C40: =SUMIF('xUS Opp Value'!E:E,'Portfolio Metrics '!B40,'xUS Opp Value'!G:G)/100 -> 0.04 | D40: =SUMIF('xUS Opp Value'!E:E,'Portfolio Metrics '!B40,'xUS Opp Value'!H:H)/100 -> 0.048627233 | E40: =SUMIF('xUS Opp Value'!E:E,'Portfolio Metrics '!B40,'xUS Opp Value'!I:I)/100 -> 0.0137 | F40: =INDEX(Algo!$D:$D,MATCH('Portfolio Metrics '!A40,Algo!A:A,0)) -> 0.0496 | G40: =C40-E40 -> 0.0263 | H40: =C40-F40 -> -0.0096 | I40: =INDEX(#REF!,MATCH('Portfolio Metrics '!A40,#REF!,0)) -> #REF! | J40: =C40-I40 -> #REF! | L40: Brazil | M40: {=IFERROR(SUMPRODUCT('xUS Opp Value'!G$4:G$2041, --('xUS Opp Value'!$L$4:$L$2041>0), --( ('xUS Opp Value'!$E$4:$E$2041=$L40) + ('xUS Opp Value'!$E$4:$E$2041="") > 0 )) / SUMPRODUCT(IF( ('xUS Opp Value'!$L$4:$L$2041>0) * ( ('xUS Opp Value'!$E$4:$E$2041=$L40) + ('xUS Opp Value'!$E$4:$E$2041="") > 0 ), 'xUS Opp Value'!G$4:G$2041/'xUS Opp Value'!$L$4:$L$2041, 0)),"")} | N40: {=IFERROR(SUMPRODUCT('xUS Opp Value'!H$4:H$2041, --('xUS Opp Value'!$L$4:$L$2041>0), --( ('xUS Opp Value'!$E$4:$E$2041=$L40) + ('xUS Opp Value'!$E$4:$E$2041="") > 0 )) / SUMPRODUCT(IF( ('xUS Opp Value'!$L$4:$L$2041>0) * ( ('xUS Opp Value'!$E$4:$E$2041=$L40) + ('xUS Opp Value'!$E$4:$E$2041="") > 0 ), 'xUS Opp Value'!H$4:H$2041/'xUS Opp Value'!$L$4:$L$2041, 0)),"")} | O40: {=IFERROR(SUMPRODUCT('xUS Opp Value'!I$4:I$2041, --('xUS Opp Value'!$L$4:$L$2041>0), --( ('xUS Opp Value'!$E$4:$E$2041=$L40) + ('xUS Opp Value'!$E$4:$E$2041="") > 0 )) / SUMPRODUCT(IF( ('xUS Opp Value'!$L$4:$L$2041>0) * ( ('xUS Opp Value'!$E$4:$E$2041=$L40) + ('xUS Opp Value'!$E$4:$E$2041="") > 0 ), 'xUS Opp Value'!I$4:I$2041/'xUS Opp Value'!$L$4:$L$2041, 0)),"")} | P40: =IFERROR((1/S40)-1,"") | Q40: =IFERROR((1/T40)-1,"") | R40: =IFERROR((1/U40)-1,"") | S40: {=IFERROR(SUMPRODUCT('xUS Opp Value'!G$4:G$2041, --('xUS Opp Value'!$J$4:$J$2041>0), --( ('xUS Opp Value'!$E$4:$E$2041=$L40) + ('xUS Opp Value'!$E$4:$E$2041="") > 0 )) / SUMPRODUCT(IF( ('xUS Opp Value'!$J$4:$J$2041>0) * ( ('xUS Opp Value'!$E$4:$E$2041=$L40) + ('xUS Opp Value'!$E$4:$E$2041="") > 0 ), 'xUS Opp Value'!G$4:G$2041/'xUS Opp Value'!$J$4:$J$2041, 0)),"")} | T40: {=IFERROR(SUMPRODUCT('xUS Opp Value'!H$4:H$2041, --('xUS Opp Value'!$J$4:$J$2041>0), --( ('xUS Opp Value'!$E$4:$E$2041=$L40) + ('xUS Opp Value'!$E$4:$E$2041="") > 0 )) / SUMPRODUCT(IF( ('xUS Opp Value'!$J$4:$J$2041>0) * ( ('xUS Opp Value'!$E$4:$E$2041=$L40) + ('xUS Opp Value'!$E$4:$E$2041="") > 0 ), 'xUS Opp Value'!H$4:H$2041/'xUS Opp Value'!$J$4:$J$2041, 0)),"")} | U40: {=IFERROR(SUMPRODUCT('xUS Opp Value'!I$4:I$2041, --('xUS Opp Value'!$J$4:$J$2041>0), --( ('xUS Opp Value'!$E$4:$E$2041=$L40) + ('xUS Opp Value'!$E$4:$E$2041="") > 0 )) / SUMPRODUCT(IF( ('xUS Opp Value'!$J$4:$J$2041>0) * ( ('xUS Opp Value'!$E$4:$E$2041=$L40) + ('xUS Opp Value'!$E$4:$E$2041="") > 0 ), 'xUS Opp Value'!I$4:I$2041/'xUS Opp Value'!$J$4:$J$2041, 0)),"")}
A41: MX EQ | B41: Mexico | C41: =SUMIF('xUS Opp Value'!E:E,'Portfolio Metrics '!B41,'xUS Opp Value'!G:G)/100 -> 0.0275 | D41: =SUMIF('xUS Opp Value'!E:E,'Portfolio Metrics '!B41,'xUS Opp Value'!H:H)/100 -> 0.03238625 | E41: =SUMIF('xUS Opp Value'!E:E,'Portfolio Metrics '!B41,'xUS Opp Value'!I:I)/100 -> 0.0065 | F41: =INDEX(Algo!$D:$D,MATCH('Portfolio Metrics '!A41,Algo!A:A,0)) -> 0.0344 | G41: =C41-E41 -> 0.021 | H41: =C41-F41 -> -0.0069 | I41: =INDEX(#REF!,MATCH('Portfolio Metrics '!A41,#REF!,0)) -> #REF! | J41: =C41-I41 -> #REF! | L41: Mexico | M41: {=IFERROR(SUMPRODUCT('xUS Opp Value'!G$4:G$2041, --('xUS Opp Value'!$L$4:$L$2041>0), --( ('xUS Opp Value'!$E$4:$E$2041=$L41) + ('xUS Opp Value'!$E$4:$E$2041="") > 0 )) / SUMPRODUCT(IF( ('xUS Opp Value'!$L$4:$L$2041>0) * ( ('xUS Opp Value'!$E$4:$E$2041=$L41) + ('xUS Opp Value'!$E$4:$E$2041="") > 0 ), 'xUS Opp Value'!G$4:G$2041/'xUS Opp Value'!$L$4:$L$2041, 0)),"")} | N41: {=IFERROR(SUMPRODUCT('xUS Opp Value'!H$4:H$2041, --('xUS Opp Value'!$L$4:$L$2041>0), --( ('xUS Opp Value'!$E$4:$E$2041=$L41) + ('xUS Opp Value'!$E$4:$E$2041="") > 0 )) / SUMPRODUCT(IF( ('xUS Opp Value'!$L$4:$L$2041>0) * ( ('xUS Opp Value'!$E$4:$E$2041=$L41) + ('xUS Opp Value'!$E$4:$E$2041="") > 0 ), 'xUS Opp Value'!H$4:H$2041/'xUS Opp Value'!$L$4:$L$2041, 0)),"")} | O41: {=IFERROR(SUMPRODUCT('xUS Opp Value'!I$4:I$2041, --('xUS Opp Value'!$L$4:$L$2041>0), --( ('xUS Opp Value'!$E$4:$E$2041=$L41) + ('xUS Opp Value'!$E$4:$E$2041="") > 0 )) / SUMPRODUCT(IF( ('xUS Opp Value'!$L$4:$L$2041>0) * ( ('xUS Opp Value'!$E$4:$E$2041=$L41) + ('xUS Opp Value'!$E$4:$E$2041="") > 0 ), 'xUS Opp Value'!I$4:I$2041/'xUS Opp Value'!$L$4:$L$2041, 0)),"")} | P41: =IFERROR((1/S41)-1,"") | Q41: =IFERROR((1/T41)-1,"") | R41: =IFERROR((1/U41)-1,"") | S41: {=IFERROR(SUMPRODUCT('xUS Opp Value'!G$4:G$2041, --('xUS Opp Value'!$J$4:$J$2041>0), --( ('xUS Opp Value'!$E$4:$E$2041=$B41) + ('xUS Opp Value'!$E$4:$E$2041="") > 0 )) / SUMPRODUCT(IF( ('xUS Opp Value'!$J$4:$J$2041>0) * ( ('xUS Opp Value'!$E$4:$E$2041=$B41) + ('xUS Opp Value'!$E$4:$E$2041="") > 0 ), 'xUS Opp Value'!G$4:G$2041/'xUS Opp Value'!$J$4:$J$2041, 0)),"")} | T41: {=IFERROR(SUMPRODUCT('xUS Opp Value'!H$4:H$2041, --('xUS Opp Value'!$J$4:$J$2041>0), --( ('xUS Opp Value'!$E$4:$E$2041=$B41) + ('xUS Opp Value'!$E$4:$E$2041="") > 0 )) / SUMPRODUCT(IF( ('xUS Opp Value'!$J$4:$J$2041>0) * ( ('xUS Opp Value'!$E$4:$E$2041=$B41) + ('xUS Opp Value'!$E$4:$E$2041="") > 0 ), 'xUS Opp Value'!H$4:H$2041/'xUS Opp Value'!$J$4:$J$2041, 0)),"")} | U41: {=IFERROR(SUMPRODUCT('xUS Opp Value'!I$4:I$2041, --('xUS Opp Value'!$J$4:$J$2041>0), --( ('xUS Opp Value'!$E$4:$E$2041=$B41) + ('xUS Opp Value'!$E$4:$E$2041="") > 0 )) / SUMPRODUCT(IF( ('xUS Opp Value'!$J$4:$J$2041>0) * ( ('xUS Opp Value'!$E$4:$E$2041=$B41) + ('xUS Opp Value'!$E$4:$E$2041="") > 0 ), 'xUS Opp Value'!I$4:I$2041/'xUS Opp Value'!$J$4:$J$2041, 0)),"")}
B45: Sector | C45: Gbl xUS Opp Value (tgt) | D45: Gbl xUS Opp Value (d) | E45: BM | F45: vs. BM
B46: Communication Services | C46: =SUMIF('xUS Opp Value'!F:F,B46,'xUS Opp Value'!G:G)/100 -> 0.07 | D46: =SUMIF('xUS Opp Value'!F:F,B46,'xUS Opp Value'!H:H)/100 -> 0.064810476 | E46: =SUMIF('xUS Opp Value'!F:F,B46,'xUS Opp Value'!I:I)/100 -> 0.0488 | F46: =C46-E46 -> 0.0212
B47: Consumer Discretionary | C47: =SUMIF('xUS Opp Value'!F:F,B47,'xUS Opp Value'!G:G)/100 -> 0.1375 | D47: =SUMIF('xUS Opp Value'!F:F,B47,'xUS Opp Value'!H:H)/100 -> 0.12915218 | E47: =SUMIF('xUS Opp Value'!F:F,B47,'xUS Opp Value'!I:I)/100 -> 0.0871 | F47: =C47-E47 -> 0.0504
B48: Consumer Staples | C48: =SUMIF('xUS Opp Value'!F:F,B48,'xUS Opp Value'!G:G)/100 -> 0.1 | D48: =SUMIF('xUS Opp Value'!F:F,B48,'xUS Opp Value'!H:H)/100 -> 0.097948951 | E48: =SUMIF('xUS Opp Value'!F:F,B48,'xUS Opp Value'!I:I)/100 -> 0.0576 | F48: =C48-E48 -> 0.0424
B49: Energy | C49: =SUMIF('xUS Opp Value'!F:F,B49,'xUS Opp Value'!G:G)/100 -> 0.0525 | D49: =SUMIF('xUS Opp Value'!F:F,B49,'xUS Opp Value'!H:H)/100 -> 0.068924145 | E49: =SUMIF('xUS Opp Value'!F:F,B49,'xUS Opp Value'!I:I)/100 -> 0.0571 | F49: =C49-E49 -> -0.0046
B50: Financials | C50: =SUMIF('xUS Opp Value'!F:F,B50,'xUS Opp Value'!G:G)/100 -> 0.21 | D50: =SUMIF('xUS Opp Value'!F:F,B50,'xUS Opp Value'!H:H)/100 -> 0.21708435 | E50: =SUMIF('xUS Opp Value'!F:F,B50,'xUS Opp Value'!I:I)/100 -> 0.2433 | F50: =C50-E50 -> -0.0333
B51: Health Care | C51: =SUMIF('xUS Opp Value'!F:F,B51,'xUS Opp Value'!G:G)/100 -> 0.1 | D51: =SUMIF('xUS Opp Value'!F:F,B51,'xUS Opp Value'!H:H)/100 -> 0.091431959 | E51: =SUMIF('xUS Opp Value'!F:F,B51,'xUS Opp Value'!I:I)/100 -> 0.0678 | F51: =C51-E51 -> 0.0322
B52: Industrials | C52: =SUMIF('xUS Opp Value'!F:F,B52,'xUS Opp Value'!G:G)/100 -> 0.1175 | D52: =SUMIF('xUS Opp Value'!F:F,B52,'xUS Opp Value'!H:H)/100 -> 0.11898793 | E52: =SUMIF('xUS Opp Value'!F:F,B52,'xUS Opp Value'!I:I)/100 -> 0.1449 | F52: =C52-E52 -> -0.0274
B53: Information Technology | C53: =SUMIF('xUS Opp Value'!F:F,B53,'xUS Opp Value'!G:G)/100 -> 0.1225 | D53: =SUMIF('xUS Opp Value'!F:F,B53,'xUS Opp Value'!H:H)/100 -> 0.12919917 | E53: =SUMIF('xUS Opp Value'!F:F,B53,'xUS Opp Value'!I:I)/100 -> 0.153 | F53: =C53-E53 -> -0.0305
B54: Materials | C54: =SUMIF('xUS Opp Value'!F:F,B54,'xUS Opp Value'!G:G)/100 -> 0.0475 | D54: =SUMIF('xUS Opp Value'!F:F,B54,'xUS Opp Value'!H:H)/100 -> 0.047185844 | E54: =SUMIF('xUS Opp Value'!F:F,B54,'xUS Opp Value'!I:I)/100 -> 0.0702 | F54: =C54-E54 -> -0.0227
B55: Real Estate | C55: =SUMIF('xUS Opp Value'!F:F,B55,'xUS Opp Value'!G:G)/100 -> 0 | D55: =SUMIF('xUS Opp Value'!F:F,B55,'xUS Opp Value'!H:H)/100 -> 0 | E55: =SUMIF('xUS Opp Value'!F:F,B55,'xUS Opp Value'!I:I)/100 -> 0.014 | F55: =C55-E55 -> -0.014
B56: Utilities | C56: =SUMIF('xUS Opp Value'!F:F,B56,'xUS Opp Value'!G:G)/100 -> 0.015 | D56: =SUMIF('xUS Opp Value'!F:F,B56,'xUS Opp Value'!H:H)/100 -> 0.017919445 | E56: =SUMIF('xUS Opp Value'!F:F,B56,'xUS Opp Value'!I:I)/100 -> 0.034 | F56: =C56-E56 -> -0.019
A65: Returns | B65: 45972
B67: 1 Month | I67: Top 10 | K67: YTD
V68: Top 10
I96: Bottom 10 | V96: Bottom 10
A133: Flagged Stocks | C133: =A2 -> as of 4/13/2026
B135: P/FV > 1 | D135: PE > 30
B137: {=_xlfn._xlws.FILTER('xUS Opp Value'!A:A, ('xUS Opp Value'!G:G<>0)*('xUS Opp Value'!J:J>1), "")} -> Stock | D137: {=_xlfn._xlws.FILTER('xUS Opp Value'!A:A, ('xUS Opp Value'!G:G<>0)*('xUS Opp Value'!L:L>30), "")} -> Stock
B138: ING Groep NV | D138: CSL Ltd
B139: Singapore Technologies Engineering Ltd | D139: JD.com Inc Ordinary Shares - Class A
B140: HSBC Holdings PLC | D140: Tencent Holdings Ltd
B141: Tokyo Electron Ltd | D141: Siemens Healthineers AG Registered Shares
B142: YASKAWA Electric Corp | D142: London Stock Exchange Group PLC
B143: RWE AG Class A | D143: Bayerische Motoren Werke AG
B144: United Overseas Bank Ltd | D144: Lvmh Moet Hennessy Louis Vuitton SE
B145: MS&AD Insurance Group Holdings Inc | D145: Compagnie Financiere Richemont SA Class A
B146: Sumitomo Mitsui Financial Group Inc | D146: RWE AG Class A
B147: Hoya Corp | D147: Julius Baer Gruppe AG
B148: Veolia Environnement SA | D148: Veolia Environnement SA
B149: Glencore PLC | D149: Svenska Handelsbanken AB Class A
B150: Banco Bilbao Vizcaya Argentaria SA | D150: America Movil SAB de CV Ordinary Shares - Class B
B151: Vale SA
B152: Sumitomo Mitsui Trust Group Inc
B153: Fomento Economico Mexicano SAB de CV Units Cons. Of 1 Shs-B- And 4 Shs-D-
B154: SSE PLC
B155: ASM International NV
B156: America Movil SAB de CV Ordinary Shares - Class B
B157: OMRON Corp
B158: TotalEnergies SE
B159: Fanuc Corp
B160: Bank Bradesco SA Participating Preferred
B161: Shell PLC
B162: Bank of Montreal
... B167: Eni SpA

Sheet xUS Opp Value (Values)
H1: 98.25
A2: as of 2/18/2025
A3: Stock | B3: ISIN | C3: Ticker | D3: SECID | E3: Country | F3: Sector | G3: Opp Value Weight (tgt) | H3: Opp Value Weight (drifted) | I3: Weight In Benchmark | J3: MER P/Fair Value | K3: Upside to MER Value | L3: Forward PE | M3: P/B | N3: ROE | O3: M* MOAT Rating | P3: Base Currency
A4: 360 Security Technology Inc Class A | B4: CNE100002RZ2 | C4: 601360 | D4: 0P0000VC5A | E4: China | F4: Information Technology | G4: 0 | H4: 0 | I4: 0.00261 | J4: 0 | L4: 0 | M4: 3.021364 | N4: -0.035688 | O4: 0 | P4: Yuan Renminbi
A5: 37 Interactive Entertainment Network Technology Group Co Ltd Class A | B5: CNE1000010N2 | C5: 002555 | D5: 0P0000SMSP | E5: China | F5: Communication Services | G5: 0 | H5: 0 | I5: 0.0018 | J5: 0 | L5: 14.08125 | M5: 4.257408 | N5: 0.207766 | O5: 0 | P5: Yuan Renminbi
A6: 3i Group Ord | B6: GB00B1YW4409 | C6: III | D6: E0GBR00IH4 | E6: 0 | F6: Financials | G6: 0 | H6: 0 | I6: 0.12724 | J6: 0 | L6: 0 | M6: 0 | N6: 0 | O6: 0 | P6: Pound Sterling
A7: 99 Speed Mart Retail Holdings Bhd | B7: MYL5326OO003 | C7: 5326 | D7: 0P0001TIMB | E7: Malaysia | F7: Consumer Staples | G7: 0 | H7: 0 | I7: 0.00473 | J7: 0 | L7: 44.712644 | M7: 17.736867 | N7: 0.409302 | O7: 0 | P7: Malaysian Ringgit
A8: A P Moller Maersk AS Class A | B8: DK0010244425 | C8: MAERSK A | D8: 0P0000A5RS | E8: Denmark | F8: Industrials | G8: 0 | H8: 0 | I8: 0.01871 | J8: 0 | L8: 0 | M8: 0.65527 | N8: 0.115066 | O8: None | P8: Danish Krone
A9: A P Moller Maersk AS Class B | B9: DK0010244508 | C9: MAERSK B | D9: 0P0000A5RL | E9: Denmark | F9: Industrials | G9: 0 | H9: 0 | I9: 0.0251 | J9: 1.3190678 | K9: -0.24188885 | L9: 0 | M9: 0.66131 | N9: 0.115066 | O9: None | P9: Danish Krone
A10: A2A SpA | B10: IT0001233417 | C10: A2A | D10: 0P00009DGW | E10: Italy | F10: Utilities | G10: 0 | H10: 0 | I10: 0.01335 | J10: 0 | L10: 0 | M10: 1.391095 | N10: 0.180129 | O10: 0 | P10: Euro
A11: AAC Technologies Holdings Inc | B11: KYG2953R1149 | C11: 02018 | D11: 0P00009S8U | E11: Hong Kong | F11: Information Technology | G11: 0 | H11: 0 | I11: 0.00978 | J11: 0.82666667 | K11: 0.20967742 | L11: 11.712549 | M11: 1.680496 | N11: 0.079273 | O11: None | P11: Hong Kong Dollar
A12: AB Sagax | B12: SE0009161052 | C12: SAGA D | D12: 0P0001965I | E12: Sweden | F12: Real Estate | G12: 0 | H12: 0 | I12: 0.0012 | J12: 0 | L12: 0 | M12: 0.384285 | N12: 0.136815 | O12: 0 | P12: Swedish Krona
A13: AB Sagax Class B | B13: SE0005127818 | C13: SAGA B | D13: 0P0000YG16 | E13: Sweden | F13: Real Estate | G13: 0 | H13: 0 | I13: 0.01354 | J13: 0 | L13: 0 | M13: 2.207525 | N13: 0.136815 | O13: 0 | P13: Swedish Krona
A14: ABB India Ltd | B14: INE117A01022 | C14: 500002 | D14: 0P0000C20B | E14: India | F14: Industrials | G14: 0 | H14: 0 | I14: 0.00913 | J14: 0 | L14: 76.743416 | M14: 16.700053 | N14: 0.290465 | O14: 0 | P14: Indian Rupee
A15: ABB Ltd | B15: CH0012221716 | C15: ABBN | D15: 0P0000A5G8 | E15: Switzerland | F15: Industrials | G15: 0 | H15: 0 | I15: 0.38791 | J15: 1.26 | K15: -0.20634921 | L15: 26.211341 | M15: 9.708645 | N15: 0.317819 | O15: Wide | P15: Swiss Franc
A16: Aboitiz Power Corp | B16: PHY0005M1090 | C16: AP | D16: 0P0000D4WS | E16: Philippines | F16: Utilities | G16: 0 | H16: 0 | I16: 0.00281 | J16: 0 | L16: 10.989975 | M16: 1.50827 | N16: 0.20178 | O16: 0 | P16: Philippine Peso
A17: Absa Group Ltd | B17: ZAE000255915 | C17: ABG | D17: 0P0000DLRU | E17: South Africa | F17: Financials | G17: 0 | H17: 0 | I17: 0.0374 | J17: 0 | L17: 0 | M17: 1.301442 | N17: 0.164536 | O17: 0 | P17: Rand
A18: Abu Dhabi Commercial Bank | B18: AEA000201011 | C18: ADCB | D18: 0P0000JM1M | E18: United Arab Emirates | F18: Financials | G18: 0 | H18: 0 | I18: 0.0371 | J18: 0 | L18: 9.521849 | M18: 1.533295 | N18: 0.163433 | O18: 0 | P18: UAE Dirham
A19: Abu Dhabi Islamic Bank | B19: AEA000801018 | C19: ADIB | D19: 0P0000JM1N | E19: United Arab Emirates | F19: Financials | G19: 0 | H19: 0 | I19: 0.02737 | J19: 0 | L19: 0 | M19: 3.683558 | N19: 0.297174 | O19: 0 | P19: UAE Dirham
A20: Abu Dhabi National Oil Co For Distribution PJSC | B20: AEA006101017 | C20: ADNOCDIST | D20: 0P0001CEM7 | E20: United Arab Emirates | F20: Consumer Discretionary | G20: 0 | H20: 0 | I20: 0.00912 | J20: 0 | L20: 15 | M20: 19.953832 | N20: 0.815751 | O20: 0 | P20: UAE Dirham
A21: ACC Ltd | B21: INE012A01025 | C21: 500410 | D21: 0P0000B89U | E21: India | F21: Materials | G21: 0 | H21: 0 | I21: 0.00411 | J21: 0 | L21: 0 | M21: 1.573172 | N21: 0.139715 | O21: 0 | P21: Indian Rupee
A22: Accton Technology Corp | B22: TW0002345006 | C22: 2345 | D22: 0P0000B70L | E22: Taiwan | F22: Information Technology | G22: 0 | H22: 0 | I22: 0.05153 | J22: 0 | L22: 27.876823 | M22: 13.355329 | N22: 0.405847 | O22: 0 | P22: New Taiwan Dollar
A23: Ackermans & Van Haaren NV | B23: BE0003764785 | C23: ACKB | D23: 0P0000A5LS | E23: Belgium | F23: Industrials | G23: 0 | H23: 0 | I23: 0.01849 | J23: 0 | L23: 13.355445 | M23: 1.533978 | N23: 0.118951 | O23: 0 | P23: Euro
A24: ACM Research (Shanghai) Inc Class A | B24: CNE100004ZD8 | C24: 688082 | D24: 0P0001NTH0 | E24: China | F24: Information Technology | G24: 0 | H24: 0 | I24: 0.00148 | J24: 0 | L24: 40.066778 | M24: 6.576478 | N24: 0.165999 | O24: 0 | P24: Yuan Renminbi
A25: ACS Actividades de Construccion y Servicios SA | B25: ES0167050915 | C25: ACS | D25: 0P0000A5SO | E25: Spain | F25: Industrials | G25: 0 | H25: 0 | I25: 0.07026 | J25: 0 | L25: 24.230769 | M25: 5.369733 | N25: 0.227454 | O25: 0 | P25: Euro
A26: ACWA Power Co | B26: SA15CGS10H12 | C26: 2082 | D26: 0P0001O3H2 | E26: Saudi Arabia | F26: Utilities | G26: 0 | H26: 0 | I26: 0.01991 | J26: 0 | L26: 0 | M26: 5.104882 | N26: 0.098535 | O26: 0 | P26: Saudi Riyal
A27: Adani Energy Solutions Ltd | B27: INE931S01010 | C27: 539254 | D27: 0P00016H1G | E27: India | F27: Utilities | G27: 0 | H27: 0 | I27: 0.00911 | J27: 0 | L27: 0 | M27: 5.006751 | N27: 0.048255 | O27: 0 | P27: Indian Rupee
... A33: Ades Holding Co | B33: SA55SG6H5716 | C33: 2382 | D33: 0P0001RRFG | E33: Saudi Arabia | F33: Energy | G33: 0 | H33: 0 | I33: 0.00634 | J33: 0 | L33: 0 | M33: 3.199463 | N33: 0.133153 | O33: 0 | P33: Saudi Riyal
A34: adidas AG | B34: DE000A1EWWW0 | C34: ADS | D34: 0P00009QNK | E34: Germany | F34: Consumer Discretionary | G34: 0 | H34: 0 | I34: 0.09007 | J34: 0.81162162 | K34: 0.23210123 | L34: 15.535885 | M34: 4.704184 | N34: 0.164287 | O34: Narrow | P34: Euro
A35: Aditya Birla Capital Ltd | B35: INE674K01013 | C35: 540691 | D35: 0P0001BJU8 | E35: India | F35: Financials | G35: 0 | H35: 0 | I35: 0.00842 | J35: 0 | L35: 19.147497 | M35: 2.804469 | N35: 0.118992 | O35: 0 | P35: Indian Rupee
A36: Admiral Group PLC | B36: GB00B02J6398 | C36: ADM | D36: 0P00007NVV | E36: United Kingdom | F36: Financials | G36: 0 | H36: 0 | I36: 0.02474 | J36: 0.77333333 | K36: 0.29310345 | L36: 12.840832 | M36: 5.797291 | N36: 0.572749 | O36: Narrow | P36: Pound Sterling
A37: ADNOC Drilling Company PJSC | B37: AEA007301012 | C37: ADNOCDRILL | D37: 0P0001NGHS | E37: United Arab Emirates | F37: Energy | G37: 0 | H37: 0 | I37: 0.01089 | J37: 0 | L37: 14.763231 | M37: 5.741967 | N37: 0.380216 | O37: 0 | P37: UAE Dirham
A38: Adnoc Logistics & Services PLC | B38: AEE01268A239 | C38: ADNOCLS | D38: 0P0001R4D5 | E38: United Arab Emirates | F38: Energy | G38: 0 | H38: 0 | I38: 0.0061 | J38: 0 | L38: 11.867306 | M38: 2.247084 | N38: 0.161376 | O38: 0 | P38: UAE Dirham
A39: Advanced Info Service PCL | B39: TH0268010Z03 | C39: ADVANC | D39: 0P0000CG0H | E39: Thailand | F39: Communication Services | G39: 0 | H39: 0 | I39: 0.03798 | J39: 0 | L39: 18.514473 | M39: 11.5171 | N39: 0.385323 | O39: 0 | P39: Baht
A40: Advantech Co Ltd | B40: TW0002395001 | C40: 2395 | D40: 0P0000C217 | E40: Taiwan | F40: Information Technology | G40: 0 | H40: 0 | I40: 0.01386 | J40: 0.78378378 | K40: 0.27586207 | L40: 20.27972 | M40: 4.886005 | N40: 0.187404 | O40: Wide | P40: New Taiwan Dollar
A41: Advantest Corp | B41: JP3122400009 | C41: 6857 | D41: 0P0000AETE | E41: Japan | F41: Information Technology | G41: 0 | H41: 0 | I41: 0.32344 | J41: 1.0845833 | K41: -0.077986938 | L41: 49.774256 | M41: 31.022083 | N41: 0.342074 | O41: Wide | P41: Yen
A42: ANZ Group Holdings Ltd | B42: AU000000ANZ3 | C42: ANZ | D42: 0P00006W6R | E42: Australia | F42: Financials | G42: 0.5 | H42: 0.56 | I42: 0.21922 | J42: 1.1145455 | K42: -0.10277325 | L42: 14.669235 | M42: 1.542886 | N42: 0.083725 | O42: Wide | P42: Australian Dollar
A43: AECC Aero-Engine Controls Co Ltd Class A | B43: CNE000000RM5 | C43: 000738 | D43: 0P00007XNI | E43: China | F43: Industrials | G43: 0 | H43: 0 | I43: 0.00099 | J43: 0 | L43: 0 | M43: 2.713732 | N43: 0.062301 | O43: 0 | P43: Yuan Renminbi
A44: AECC Aviation Power Co Ltd Class A | B44: CNE000000JW1 | C44: 600893 | D44: 0P00007XKQ | E44: China | F44: Industrials | G44: 0 | H44: 0 | I44: 0.00379 | J44: 0 | L44: 0 | M44: 3.251029 | N44: 0.024774 | O44: 0 | P44: Yuan Renminbi
A45: Aena SME SA | B45: ES0105046017 | C45: AENA | D45: 0P00015CW1 | E45: Spain | F45: Industrials | G45: 0 | H45: 0 | I45: 0.0652 | J45: 0 | L45: 15.905063 | M45: 4.591428 | N45: 0.254033 | O45: Narrow | P45: Euro
A46: AEON Co Ltd | B46: JP3388200002 | C46: 8267 | D46: 0P0000AETF | E46: Japan | F46: Consumer Staples | G46: 0 | H46: 0 | I46: 0.10299 | J46: 0 | L46: 0 | M46: 5.228815 | N46: 0.06827 | O46: 0 | P46: Yen
A47: Aeroports de Paris SA | B47: FR0010340141 | C47: ADP | D47: 0P00009W9W | E47: France | F47: Industrials | G47: 0 | H47: 0 | I47: 0.0135 | J47: 0 | L47: 12.535776 | M47: 2.682144 | N47: 0.117719 | O47: Narrow | P47: Euro
A48: AGC Inc | B48: JP3112000009 | C48: 5201 | D48: 0P0000AETK | E48: Japan | F48: Industrials | G48: 0 | H48: 0 | I48: 0.02224 | J48: 0 | L48: 0 | M48: 0.886604 | N48: -0.053074 | O48: 0 | P48: Yen
A49: Ageas SA/ NV | B49: BE0974264930 | C49: AGS | D49: 0P0000A5MB | E49: Belgium | F49: Financials | G49: 0 | H49: 0 | I49: 0.03446 | J49: 0.89779412 | K49: 0.11384111 | L49: 6.383547 | M49: 1.444235 | N49: 0.172897 | O49: None | P49: Euro
A50: Agnico Eagle Mines Ltd | B50: CA0084741085 | C50: AEM | D50: 0P000067Y3 | E50: Canada | F50: Materials | G50: 0 | H50: 0 | I50: 0.27264 | J50: 2.3723636 | K50: -0.57847946 | L50: 19.733001 | M50: 4.03293 | N50: 0.095298 | O50: None | P50: Canadian Dollar
A51: Agricultural Bank of China Ltd Class A | B51: CNE100000RJ0 | C51: 601288 | D51: 0P0000P3LW | E51: China | F51: Financials | G51: 0 | H51: 0 | I51: 0.03334 | J51: 1.0918033 | K51: -0.084084084 | L51: 10.041096 | M51: 0.851154 | N51: 0.1132 | O51: Narrow | P51: Yuan Renminbi
A52: Agricultural Bank of China Ltd Class H | B52: CNE100000Q43 | C52: 01288 | D52: 0P0000P60C | E52: China | F52: Financials | G52: 0 | H52: 0 | I52: 0.05631 | J52: 0.81666667 | K52: 0.2244898 | L52: 6.861946 | M52: 0.630115 | N52: 0.1132 | O52: Narrow | P52: Hong Kong Dollar
A53: ASX Ltd | B53: AU000000ASX7 | C53: ASX | D53: 0P00006W9V | E53: Australia | F53: Financials | G53: 0.5 | H53: 0.56 | I53: 0.02208 | J53: 0.81371429 | K53: 0.22893258 | L53: 21.235709 | M53: 2.857699 | N53: 0.132751 | O53: Wide | P53: Australian Dollar
A54: Aima Technology Group Co Ltd Class A | B54: CNE1000051B1 | C54: 603529 | D54: 0P0001MOS0 | E54: China | F54: Consumer Discretionary | G54: 0 | H54: 0 | I54: 0.00061 | J54: 0 | L54: 0 | M54: 2.513777 | N54: 0.239503 | O54: 0 | P54: Yuan Renminbi
A55: Air Liquide SA | B55: FR0000120073 | C55: AI | D55: 0P00009WA4 | E55: France | F55: Materials | G55: 0 | H55: 0 | I55: 0.30694 | J55: 0.8347644 | K55: 0.1979428 | L55: 22.019178 | M55: 3.750515 | N55: 0.136007 | O55: Wide | P55: Euro
A56: Airbus SE | B56: NL0000235190 | C56: AIR | D56: 0P00009WFE | E56: Netherlands | F56: Industrials | G56: 0 | H56: 0 | I56: 0.38304 | J56: 1.0253968 | K56: -0.024767802 | L56: 26.923559 | M56: 6.48063 | N56: 0.2232 | O56: Wide | P56: Euro
A57: Airports Of Thailand PLC | B57: TH0765010Z08 | C57: AOT | D57: 0P0000CI7K | E57: Thailand | F57: Industrials | G57: 0 | H57: 0 | I57: 0.01946 | J57: 0 | L57: 33.940397 | M57: 5.647785 | N57: 0.146171 | O57: 0 | P57: Baht
A58: Airtac International Group | B58: KYG014081064 | C58: 1590 | D58: 0P0000RXT9 | E58: Taiwan | F58: Industrials | G58: 0 | H58: 0 | I58: 0.01477 | J58: 1.3055556 | K58: -0.23404255 | L58: 23.000227 | M58: 4.907372 | N58: 0.171028 | O58: Narrow | P58: New Taiwan Dollar
A59: Aisin Corp | B59: JP3102000001 | C59: 7259 | D59: 0P0000EB4H | E59: Japan | F59: Consumer Discretionary | G59: 0 | H59: 0 | I59: 0.02921 | J59: 0 | L59: 5.002362 | M59: 0.954383 | N59: 0.061849 | O59: 0 | P59: Yen
A60: Ajinomoto Co Inc | B60: JP3119600009 | C60: 2802 | D60: 0P0000AETG | E60: Japan | F60: Consumer Staples | G60: 0 | H60: 0 | I60: 0.06356 | J60: 0.935 | K60: 0.069518717 | L60: 25.721136 | M60: 4.830707 | N60: 0.103896 | O60: Wide | P60: Yen
A61: Akbank TAS | B61: TRAAKBNK91N6 | C61: AKBNK | D61: 0P0000AQU3 | E61: Turkey | F61: Financials | G61: 0 | H61: 0 | I61: 0.0187 | J61: 0 | L61: 7.954766 | M61: 1.4744 | N61: 0.215156 | O61: 0 | P61: Turkish Lira
A62: Aker BP ASA | B62: NO0010345853 | C62: AKRBP | D62: 0P0000J0N3 | E62: Norway | F62: Energy | G62: 0 | H62: 0 | I62: 0.02557 | J62: 0 | L62: 12.58983 | M62: 1.471795 | N62: 0.145682 | O62: 0 | P62: Norwegian Krone
A63: Akeso Inc Ordinary Shares | B63: KYG0146B1032 | C63: 09926 | D63: 0P0001JOG2 | E63: China | F63: Health Care | G63: 0 | H63: 0 | I63: 0.02182 | J63: 0 | L63: 3859.121 | M63: 13.024284 | N63: -0.09069 | O63: 0 | P63: Hong Kong Dollar
A64: CSL Ltd | B64: AU000000CSL8 | C64: CSL | D64: 0P00006WCJ | E64: Australia | F64: Health Care | G64: 0.5 | H64: 0.47 | I64: 0.17454 | J64: 0.60376271 | K64: 0.65627983 | L64: 24.743782 | M64: 2.913525 | N64: 0.170259 | O64: Narrow | P64: Australian Dollar
A65: Al Rajhi Bank | B65: SA0007879113 | C65: 1120 | D65: 0P0000Q2IB | E65: Saudi Arabia | F65: Financials | G65: 0 | H65: 0 | I65: 0.15926 | J65: 0 | L65: 15.329016 | M65: 3.942013 | N65: 0.210781 | O65: 0 | P65: Saudi Riyal
A66: Alchip Technologies Ltd | B66: KYG022421088 | C66: 3661 | D66: 0P0000T4AK | E66: United States | F66: Information Technology | G66: 0 | H66: 0 | I66: 0.02277 | J66: 0 | L66: 52.857143 | M66: 7.092582 | N66: 0.201312 | O66: 0 | P66: New Taiwan Dollar
A67: Ramsay Health Care Ltd | C67: RHC | E67: Australia | F67: Healthcare | G67: 0.5 | H67: 0.56 | I67: 0 | J67: 0.687593 | K67: 0.45434872 | L67: 28.54 | M67: 1.796036 | N67: 0.4838 | O67: Narrow | P67: Australian Dollar
A68: Aldar Properties PJSC | B68: AEA002001013 | C68: ALDAR | D68: 0P0000JM1D | E68: United Arab Emirates | F68: Real Estate | G68: 0 | H68: 0 | I68: 0.02825 | J68: 0 | L68: 0 | M68: 2.0046 | N68: 0.200434 | O68: 0 | P68: UAE Dirham
A69: Alfa Laval AB | B69: SE0000695876 | C69: ALFA | D69: 0P0000A6MF | E69: Sweden | F69: Industrials | G69: 0 | H69: 0 | I69: 0.04519 | J69: 1.1231111 | K69: -0.10961615 | L69: 22.766338 | M69: 5.15754 | N69: 0.197815 | O69: Wide | P69: Swedish Krona
A70: Sonic Healthcare Ltd | B70: AU000000SHL7 | C70: SKHCF | D70: 0P00006WXE | E70: Australia | F70: Health Care | G70: 0.5 | H70: 0.48 | I70: 0.02126 | J70: 0.69030303 | K70: 0.44863916 | L70: 18.986258 | M70: 1.314784 | N70: 0.066774 | O70: Narrow | P70: Australian Dollar
A71: Alibaba Health Information Technology Ltd | B71: BMG0171K1018 | C71: 00241 | D71: 0P00009RU8 | E71: China | F71: Consumer Staples | G71: 0 | H71: 0 | I71: 0.01195 | J71: 1.1648148 | K71: -0.14149444 | L71: 30.746141 | M71: 5.460409 | N71: 0.096528 | O71: Narrow | P71: Hong Kong Dollar
A72: Alimentation Couche-Tard Inc | B72: CA01626P1484 | C72: ATD | D72: 0P00005RPW | E72: Canada | F72: Consumer Staples | G72: 0 | H72: 0 | I72: 0.10574 | J72: 0 | L72: 16.074795 | M72: 3.203741 | N72: 0.184628 | O72: 0 | P72: Canadian Dollar
A73: Alinma Bank | B73: SA122050HV19 | C73: 1150 | D73: 0P0000Q2IN | E73: Saudi Arabia | F73: Financials | G73: 0 | H73: 0 | I73: 0.02628 | J73: 0 | L73: 0 | M73: 2.000539 | N73: 0.186536 | O73: 0 | P73: Saudi Riyal
A74: Alkem Laboratories Ltd | B74: INE540L01014 | C74: ALKEM | D74: 0P000177DB | E74: India | F74: Health Care | G74: 0 | H74: 0 | I74: 0.0122 | J74: 0 | L74: 22.954503 | M74: 5.1088 | N74: 0.197016 | O74: 0 | P74: Indian Rupee
A75: Allegro.EU SA Ordinary Shares | B75: LU2237380790 | C75: ALE | D75: 0P0001KVU9 | E75: Poland | F75: Consumer Discretionary | G75: 0 | H75: 0 | I75: 0.01467 | J75: 0 | L75: 25.935252 | M75: 2.850178 | N75: 0.107785 | O75: Wide | P75: Zloty
A76: Allianz SE | B76: DE0008404005 | C76: ALV | D76: 0P00009QNO | E76: Germany | F76: Financials | G76: 0 | H76: 0 | I76: 0.48558 | J76: 1.0504155 | K76: -0.047995781 | L76: 12.040334 | M76: 2.394813 | N76: 0.180611 | O76: None | P76: Euro
A77: Almarai Co | B77: SA000A0ETHT1 | C77: 2280 | D77: 0P0000Q2IQ | E77: Saudi Arabia | F77: Consumer Staples | G77: 0 | H77: 0 | I77: 0.01628 | J77: 0 | L77: 0 | M77: 2.061829 | N77: 0.124797 | O77: 0 | P77: Saudi Riyal
A78: Alpha Bank SA | B78: GRS830003000 | C78: ALPHA | D78: 0P0001WDOX | E78: Greece | F78: Financials | G78: 0 | H78: 0 | I78: 0.02866 | J78: 0 | L78: 0 | M78: 1.174031 | N78: 0.082419 | O78: 0 | P78: Euro
A79: Alpha Dhabi Holding PJSC Ordinary Shares | B79: AEA007601015 | C79: ALPHADHABI | D79: 0P0001MUV8 | E79: United Arab Emirates | F79: Industrials | G79: 0 | H79: 0 | I79: 0.01098 | J79: 0 | L79: 0 | M79: 1.557002 | N79: 0.282537 | O79: 0 | P79: UAE Dirham
A80: AlRayan Bank Shs Partly paid | B80: QA000A0M8VM3 | C80: MARK | D80: 0P0000Q2I2 | E80: Qatar | F80: Financials | G80: 0 | H80: 0 | I80: 0.01187 | J80: 0 | L80: 13.176702 | M80: 0.890152 | N80: 0.064147 | O80: 0 | P80: Qatari Rial
A81: AltaGas Ltd | B81: CA0213611001 | C81: ALA | D81: 0P000080F4 | E81: Canada | F81: Utilities | G81: 0 | H81: 0 | I81: 0.02549 | J81: 0 | L81: 17.650862 | M81: 1.498331 | N81: 0.077797 | O81: 0 | P81: Canadian Dollar
A82: Alteogen Inc | B82: KR7196170005 | C82: 196170 | D82: 0P0001528W | E82: South Korea | F82: Health Care | G82: 0 | H82: 0 | I82: 0.03285 | J82: 0 | L82: 0 | M82: 58.81437 | N82: 0.327806 | O82: 0 | P82: Won
A83: Aluminum Corp of China Ltd Class A | B83: CNE1000000T0 | C83: 601600 | D83: 0P00009G1A | E83: China | F83: Materials | G83: 0 | H83: 0 | I83: 0.00573 | J83: 0 | L83: 17.21875 | M83: 3.070912 | N83: 0.304259 | O83: None | P83: Yuan Renminbi
A84: Aluminum Corp of China Ltd Class H | B84: CNE1000001T8 | C84: 02600 | D84: 0P00009SA1 | E84: China | F84: Materials | G84: 0 | H84: 0 | I84: 0.018 | J84: 0 | L84: 10.819645 | M84: 2.809081 | N84: 0.304259 | O84: None | P84: Hong Kong Dollar
A85: Alupar Investimento SA Unit Cons of 1 Sh + 2 Pfd Shs | B85: BRALUPCDAM15 | C85: ALUP11 | D85: 0P0000YLAK | E85: Brazil | F85: Utilities | G85: 0 | H85: 0 | I85: 0.00298 | J85: 0 | L85: 0 | M85: 0 | N85: 0.237558 | O85: 0 | P85: Brazilian Real
A86: Amadeus IT Group SA | B86: ES0109067019 | C86: AMS | D86: 0P0000P5MC | E86: Spain | F86: Consumer Discretionary | G86: 0 | H86: 0 | I86: 0.08341 | J86: 0.79558824 | K86: 0.25693161 | L86: 17.69297 | M86: 4.636177 | N86: 0.267808 | O86: Narrow | P86: Euro
A87: Woodside Energy Group Ltd | B87: AU0000224040 | C87: WDS | D87: 0P00006X25 | E87: Australia | F87: Energy | G87: 0.5 | H87: 0.51 | I87: 0.09594 | J87: 0.59666667 | K87: 0.67597765 | L87: 16.423932 | M87: 0.877955 | N87: 0.104701 | O87: None | P87: Australian Dollar
A88: Ambuja Cements Ltd | B88: INE079A01024 | C88: 500425 | D88: 0P0000B269 | E88: India | F88: Materials | G88: 0 | H88: 0 | I88: 0.01258 | J88: 0 | L88: 25.093607 | M88: 2.321474 | N88: 0.108617 | O88: Narrow | P88: Indian Rupee
A89: Ambev SA | B89: BRABEVACNOR1 | C89: ABEV3 | D89: 0P0000BNIX | E89: Brazil | F89: Consumer Staples | G89: 1.25 | H89: 1.35 | I89: 0.03554 | J89: 0.85084746 | K89: 0.1752988 | L89: 13.565217 | M89: 2.551653 | N89: 0.162223 | O89: Wide | P89: Brazilian Real
A90: Amlogic (Shanghai) Co Ltd Class A | B90: CNE100003LZ3 | C90: 688099 | D90: 0P0001I7FG | E90: China | F90: Information Technology | G90: 0 | H90: 0 | I90: 0.00112 | J90: 0 | L90: 0 | M90: 4.930968 | N90: 0.138662 | O90: 0 | P90: Yuan Renminbi
A91: AMMB Holdings Bhd | B91: MYL1015OO006 | C91: 1015 | D91: 0P0000BYKR | E91: Malaysia | F91: Financials | G91: 0 | H91: 0 | I91: 0.01356 | J91: 0 | L91: 10.076923 | M91: 1.031625 | N91: 0.099953 | O91: 0 | P91: Malaysian Ringgit
A92: AmorePacific Corp | B92: KR7090430000 | C92: 090430 | D92: 0P0000B9SJ | E92: South Korea | F92: Consumer Staples | G92: 0 | H92: 0 | I92: 0.00822 | J92: 0 | L92: 20.229652 | M92: 1.792075 | N92: 0.117469 | O92: 0 | P92: Won
A93: Amundi SA | B93: FR0004125920 | C93: AMUN | D93: 0P00016YML | E93: France | F93: Financials | G93: 0 | H93: 0 | I93: 0.01577 | J93: 0.966875 | K93: 0.034259858 | L93: 10.317241 | M93: 1.314401 | N93: 0.112768 | O93: Narrow | P93: Euro
A94: ANA Holdings Inc | B94: JP3429800000 | C94: 9202 | D94: 0P0000AETH | E94: Japan | F94: Industrials | G94: 0 | H94: 0 | I94: 0.0086 | J94: 0.84335106 | K94: 0.18574582 | L94: 9.428422 | M94: 1.025584 | N94: 0.143101 | O94: None | P94: Yen
A95: Andritz AG | B95: AT0000730007 | C95: ANDR | D95: 0P0000DLCZ | E95: Austria | F95: Industrials | G95: 0 | H95: 0 | I95: 0.01602 | J95: 0 | L95: 0 | M95: 3.196434 | N95: 0.229502 | O95: 0 | P95: Euro
A96: Angel Yeast Co Ltd Class A | B96: CNE0000014G0 | C96: 600298 | D96: 0P00007X6D | E96: China | F96: Consumer Staples | G96: 0 | H96: 0 | I96: 0.00112 | J96: 0 | L96: 0 | M96: 3.244734 | N96: 0.13083 | O96: 0 | P96: Yuan Renminbi
A97: Anglo American PLC | B97: GB00BTK05J60 | C97: AAL | D97: 0P00007NXM | E97: United Kingdom | F97: Materials | G97: 0 | H97: 0 | I97: 0.14196 | J97: 1.5681818 | K97: -0.36231884 | L97: 31.723524 | M97: 2.61211 | N97: -0.119641 | O97: None | P97: Pound Sterling
A98: Anheuser-Busch InBev SA/NV | B98: BE0974293251 | C98: ABI | D98: 0P0000A63G | E98: Belgium | F98: Consumer Staples | G98: 0 | H98: 0 | I98: 0.19875 | J98: 1.0722807 | K98: -0.067408377 | L98: 16.46568 | M98: 1.734808 | N98: 0.093243 | O98: Wide | P98: Euro
A99: Anhui Conch Cement Co Ltd Class A | B99: CNE0000019V8 | C99: 600585 | D99: 0P00007XCP | E99: China | F99: Materials | G99: 0 | H99: 0 | I99: 0.00301 | J99: 0.96706349 | K99: 0.034058268 | L99: 11.989362 | M99: 0.678337 | N99: 0.04125 | O99: None | P99: Yuan Renminbi
A100: Anhui Conch Cement Co Ltd Class H | B100: CNE1000001W2 | C100: 00914 | D100: 0P00009S48 | E100: China | F100: Materials | G100: 0 | H100: 0 | I100: 0.01069 | J100: 0.87428571 | K100: 0.14379085 | L100: 11.010014 | M100: 0.623302 | N100: 0.04125 | O100: None | P100: Hong Kong Dollar
A101: Anhui Gujing Distillery Co Ltd Class A | B101: CNE000000MD5 | C101: 000596 | D101: 0P00007WVC | E101: China | F101: Consumer Staples | G101: 0 | H101: 0 | I101: 0.00166 | J101: 0.67912821 | K101: 0.47247603 | L101: 14.89268 | M101: 2.749343 | N101: 0.245189 | O101: Narrow | P101: Yuan Renminbi
A102: Anhui Gujing Distillery Co Ltd Class B | B102: CNE000000K82 | C102: 200596 | D102: 0P00007WYV | E102: China | F102: Consumer Staples | G102: 0 | H102: 0 | I102: 0.00329 | J102: 0 | L102: 8.407452 | M102: 1.576222 | N102: 0.245189 | O102: Narrow | P102: Hong Kong Dollar
A103: Anhui Jianghuai Automobile Group Co Ltd Class A | B103: CNE0000018M9 | C103: 600418 | D103: 0P00007X93 | E103: China | F103: Consumer Discretionary | G103: 0 | H103: 0 | I103: 0.00366 | J103: 0 | L103: 34.975369 | M103: 11.63792 | N103: -0.152899 | O103: 0 | P103: Yuan Renminbi
A104: Anhui Yingjia Distillery Co Ltd Class A | B104: CNE1000022H9 | C104: 603198 | D104: 0P000163U2 | E104: China | F104: Consumer Staples | G104: 0 | H104: 0 | I104: 0.00093 | J104: 0.76293578 | K104: 0.31072631 | L104: 14.108303 | M104: 3.274861 | N104: 0.284915 | O104: Narrow | P104: Yuan Renminbi
A105: Anjoy Foods Group Co Ltd Class A | B105: CNE100002YQ7 | C105: 603345 | D105: 0P00019SML | E105: China | F105: Consumer Staples | G105: 0 | H105: 0 | I105: 0.0008 | J105: 0 | L105: 16.85119 | M105: 1.92196 | N105: 0.11769 | O105: 0 | P105: Yuan Renminbi
...

Sheet xUS Opp Value
H1: =SUM(G:G) -> 99
A2: as of 4/13/2026
A3: Stock | B3: ISIN | C3: Ticker | D3: SECID | E3: Country | F3: Sector | G3: Opp Value Weight (tgt) | H3: Opp Value Weight (drifted) | I3: Weight In Benchmark | J3: MER P/Fair Value | K3: Upside to MER Value | L3: Forward PE | M3: P/B | N3: ROE | O3: M* MOAT Rating | P3: Base Currency | Q3: Fair Value Uncertainty
A4: Hitachi Ltd | B4: =INDEX('xUS TME'!B:B,MATCH('xUS Opp Value'!A4,'xUS TME'!A:A,0)) -> JP3788600009 | C4: =INDEX('xUS TME'!C:C,MATCH($B4,'xUS TME'!$B:$B,0)) -> 6501 | D4: =INDEX('xUS TME'!D:D,MATCH(B4,'xUS TME'!$B:$B,0)) -> 0P0000AEUO | E4: =INDEX('xUS TME'!F:F,MATCH(B4,'xUS TME'!$B:$B,0)) -> Japan | F4: =INDEX('xUS TME'!G:G,MATCH(B4,'xUS TME'!$B:$B,0)) -> Industrials | G4: =IFERROR(INDEX(CRIMs!G:G,MATCH(C4,CRIMs!D:D,0)),0) -> 0 | H4: =IFERROR(INDEX(CRIMs!I:I,MATCH(C4,CRIMs!D:D,0)),0) -> 0 | I4: =INDEX('xUS TME'!E:E,MATCH($B4,'xUS TME'!$B:$B,0)) -> 0.39 | J4: =INDEX('xUS TME'!H:H,MATCH(B4,'xUS TME'!$B:$B,0)) -> 0 | K4: =IFERROR((1/J4)-1,"") | L4: =INDEX('xUS TME'!J:J,MATCH('xUS Opp Value'!B4,'xUS TME'!$B:$B,0)) -> 23.03 | M4: =INDEX('xUS TME'!L:L,MATCH('xUS Opp Value'!$B4,'xUS TME'!$B:$B,0)) -> 3.41 | N4: =INDEX('xUS TME'!K:K,MATCH('xUS Opp Value'!$B4,'xUS TME'!$B:$B,0)) -> 0.12 | O4: =INDEX('xUS TME'!I:I,MATCH('xUS Opp Value'!$B4,'xUS TME'!$B:$B,0)) -> None | P4: =INDEX('xUS TME'!M:M,MATCH('xUS Opp Value'!$B4,'xUS TME'!$B:$B,0)) -> Yen | Q4: =INDEX('xUS TME'!N:N,MATCH('xUS Opp Value'!$B4,'xUS TME'!$B:$B,0)) -> Medium
A5: HDFC Bank Ltd | B5: =INDEX('xUS TME'!B:B,MATCH('xUS Opp Value'!A5,'xUS TME'!A:A,0)) -> INE040A01034 | C5: =INDEX('xUS TME'!C:C,MATCH($B5,'xUS TME'!$B:$B,0)) -> HDFCBANK | D5: =INDEX('xUS TME'!D:D,MATCH(B5,'xUS TME'!$B:$B,0)) -> 0P0000C3NZ | E5: =INDEX('xUS TME'!F:F,MATCH(B5,'xUS TME'!$B:$B,0)) -> India | F5: =INDEX('xUS TME'!G:G,MATCH(B5,'xUS TME'!$B:$B,0)) -> Financials | G5: =IFERROR(INDEX(CRIMs!G:G,MATCH(C5,CRIMs!D:D,0)),0) -> 0.75 | H5: =IFERROR(INDEX(CRIMs!I:I,MATCH(C5,CRIMs!D:D,0)),0) -> 0.79836769 | I5: =INDEX('xUS TME'!E:E,MATCH($B5,'xUS TME'!$B:$B,0)) -> 0.27 | J5: =INDEX('xUS TME'!H:H,MATCH(B5,'xUS TME'!$B:$B,0)) -> 0 | K5: =IFERROR((1/J5)-1,"") | L5: =INDEX('xUS TME'!J:J,MATCH('xUS Opp Value'!B5,'xUS TME'!$B:$B,0)) -> 16.38 | M5: =INDEX('xUS TME'!L:L,MATCH('xUS Opp Value'!$B5,'xUS TME'!$B:$B,0)) -> 1.62 | N5: =INDEX('xUS TME'!K:K,MATCH('xUS Opp Value'!$B5,'xUS TME'!$B:$B,0)) -> 0.09 | O5: =INDEX('xUS TME'!I:I,MATCH('xUS Opp Value'!$B5,'xUS TME'!$B:$B,0)) -> Narrow | P5: =INDEX('xUS TME'!M:M,MATCH('xUS Opp Value'!$B5,'xUS TME'!$B:$B,0)) -> Indian Rupee | Q5: =INDEX('xUS TME'!N:N,MATCH('xUS Opp Value'!$B5,'xUS TME'!$B:$B,0)) -> High
A6: Reliance Industries Ltd | B6: =INDEX('xUS TME'!B:B,MATCH('xUS Opp Value'!A6,'xUS TME'!A:A,0)) -> INE002A01018 | C6: =INDEX('xUS TME'!C:C,MATCH($B6,'xUS TME'!$B:$B,0)) -> RELIANCE | D6: =INDEX('xUS TME'!D:D,MATCH(B6,'xUS TME'!$B:$B,0)) -> 0P0000B1W1 | E6: =INDEX('xUS TME'!F:F,MATCH(B6,'xUS TME'!$B:$B,0)) -> India | F6: =INDEX('xUS TME'!G:G,MATCH(B6,'xUS TME'!$B:$B,0)) -> Energy | G6: =IFERROR(INDEX(CRIMs!G:G,MATCH(C6,CRIMs!D:D,0)),0) -> 0 | H6: =IFERROR(INDEX(CRIMs!I:I,MATCH(C6,CRIMs!D:D,0)),0) -> 0 | I6: =INDEX('xUS TME'!E:E,MATCH($B6,'xUS TME'!$B:$B,0)) -> 0.31 | J6: =INDEX('xUS TME'!H:H,MATCH(B6,'xUS TME'!$B:$B,0)) -> 0 | K6: =IFERROR((1/J6)-1,"") | L6: =INDEX('xUS TME'!J:J,MATCH('xUS Opp Value'!B6,'xUS TME'!$B:$B,0)) -> 18.52 | M6: =INDEX('xUS TME'!L:L,MATCH('xUS Opp Value'!$B6,'xUS TME'!$B:$B,0)) -> 2.08 | N6: =INDEX('xUS TME'!K:K,MATCH('xUS Opp Value'!$B6,'xUS TME'!$B:$B,0)) -> 0.1 | O6: =INDEX('xUS TME'!I:I,MATCH('xUS Opp Value'!$B6,'xUS TME'!$B:$B,0)) -> None | P6: =INDEX('xUS TME'!M:M,MATCH('xUS Opp Value'!$B6,'xUS TME'!$B:$B,0)) -> Indian Rupee | Q6: =INDEX('xUS TME'!N:N,MATCH('xUS Opp Value'!$B6,'xUS TME'!$B:$B,0)) -> High
A7: Mitsubishi Heavy Industries Ltd | B7: =INDEX('xUS TME'!B:B,MATCH('xUS Opp Value'!A7,'xUS TME'!A:A,0)) -> JP3900000005 | C7: =INDEX('xUS TME'!C:C,MATCH($B7,'xUS TME'!$B:$B,0)) -> 7011 | D7: =INDEX('xUS TME'!D:D,MATCH(B7,'xUS TME'!$B:$B,0)) -> 0P0000AEVY | E7: =INDEX('xUS TME'!F:F,MATCH(B7,'xUS TME'!$B:$B,0)) -> Japan | F7: =INDEX('xUS TME'!G:G,MATCH(B7,'xUS TME'!$B:$B,0)) -> Industrials | G7: =IFERROR(INDEX(CRIMs!G:G,MATCH(C7,CRIMs!D:D,0)),0) -> 0 | H7: =IFERROR(INDEX(CRIMs!I:I,MATCH(C7,CRIMs!D:D,0)),0) -> 0 | I7: =INDEX('xUS TME'!E:E,MATCH($B7,'xUS TME'!$B:$B,0)) -> 0.27 | J7: =INDEX('xUS TME'!H:H,MATCH(B7,'xUS TME'!$B:$B,0)) -> 1.79 | K7: =IFERROR((1/J7)-1,"") -> -0.44134078 | L7: =INDEX('xUS TME'!J:J,MATCH('xUS Opp Value'!B7,'xUS TME'!$B:$B,0)) -> 45.26 | M7: =INDEX('xUS TME'!L:L,MATCH('xUS Opp Value'!$B7,'xUS TME'!$B:$B,0)) -> 6.01 | N7: =INDEX('xUS TME'!K:K,MATCH('xUS Opp Value'!$B7,'xUS TME'!$B:$B,0)) -> 0.11 | O7: =INDEX('xUS TME'!I:I,MATCH('xUS Opp Value'!$B7,'xUS TME'!$B:$B,0)) -> Narrow | P7: =INDEX('xUS TME'!M:M,MATCH('xUS Opp Value'!$B7,'xUS TME'!$B:$B,0)) -> Yen | Q7: =INDEX('xUS TME'!N:N,MATCH('xUS Opp Value'!$B7,'xUS TME'!$B:$B,0)) -> High
A8: Brookfield Corp Registered Shs -A- Limited Vtg | B8: =INDEX('xUS TME'!B:B,MATCH('xUS Opp Value'!A8,'xUS TME'!A:A,0)) -> CA11271J1075 | C8: =INDEX('xUS TME'!C:C,MATCH($B8,'xUS TME'!$B:$B,0)) -> BN | D8: =INDEX('xUS TME'!D:D,MATCH(B8,'xUS TME'!$B:$B,0)) -> 0P000067ZL | E8: =INDEX('xUS TME'!F:F,MATCH(B8,'xUS TME'!$B:$B,0)) -> Canada | F8: =INDEX('xUS TME'!G:G,MATCH(B8,'xUS TME'!$B:$B,0)) -> Financials | G8: =IFERROR(INDEX(CRIMs!G:G,MATCH(C8,CRIMs!D:D,0)),0) -> 0 | H8: =IFERROR(INDEX(CRIMs!I:I,MATCH(C8,CRIMs!D:D,0)),0) -> 0 | I8: =INDEX('xUS TME'!E:E,MATCH($B8,'xUS TME'!$B:$B,0)) -> 0.23 | J8: =INDEX('xUS TME'!H:H,MATCH(B8,'xUS TME'!$B:$B,0)) -> 0 | K8: =IFERROR((1/J8)-1,"") | L8: =INDEX('xUS TME'!J:J,MATCH('xUS Opp Value'!B8,'xUS TME'!$B:$B,0)) -> 11.95 | M8: =INDEX('xUS TME'!L:L,MATCH('xUS Opp Value'!$B8,'xUS TME'!$B:$B,0)) -> 2.18 | N8: =INDEX('xUS TME'!K:K,MATCH('xUS Opp Value'!$B8,'xUS TME'!$B:$B,0)) -> 0.08 | O8: =INDEX('xUS TME'!I:I,MATCH('xUS Opp Value'!$B8,'xUS TME'!$B:$B,0)) -> Narrow | P8: =INDEX('xUS TME'!M:M,MATCH('xUS Opp Value'!$B8,'xUS TME'!$B:$B,0)) -> Canadian Dollar | Q8: =INDEX('xUS TME'!N:N,MATCH('xUS Opp Value'!$B8,'xUS TME'!$B:$B,0)) -> Very High
A9: International Holdings Co PJSC | B9: =INDEX('xUS TME'!B:B,MATCH('xUS Opp Value'!A9,'xUS TME'!A:A,0)) -> AEI000201014 | C9: =INDEX('xUS TME'!C:C,MATCH($B9,'xUS TME'!$B:$B,0)) -> IHC | D9: =INDEX('xUS TME'!D:D,MATCH(B9,'xUS TME'!$B:$B,0)) -> 0P0000RUHY | E9: =INDEX('xUS TME'!F:F,MATCH(B9,'xUS TME'!$B:$B,0)) -> United Arab Emirates | F9: =INDEX('xUS TME'!G:G,MATCH(B9,'xUS TME'!$B:$B,0)) -> Industrials | G9: =IFERROR(INDEX(CRIMs!G:G,MATCH(C9,CRIMs!D:D,0)),0) -> 0 | H9: =IFERROR(INDEX(CRIMs!I:I,MATCH(C9,CRIMs!D:D,0)),0) -> 0 | I9: =INDEX('xUS TME'!E:E,MATCH($B9,'xUS TME'!$B:$B,0)) -> 0.24 | J9: =INDEX('xUS TME'!H:H,MATCH(B9,'xUS TME'!$B:$B,0)) -> 0 | K9: =IFERROR((1/J9)-1,"") | L9: =INDEX('xUS TME'!J:J,MATCH('xUS Opp Value'!B9,'xUS TME'!$B:$B,0)) -> 0 | M9: =INDEX('xUS TME'!L:L,MATCH('xUS Opp Value'!$B9,'xUS TME'!$B:$B,0)) -> 5.57 | N9: =INDEX('xUS TME'!K:K,MATCH('xUS Opp Value'!$B9,'xUS TME'!$B:$B,0)) -> 0.23 | O9: =INDEX('xUS TME'!I:I,MATCH('xUS Opp Value'!$B9,'xUS TME'!$B:$B,0)) -> 0 | P9: =INDEX('xUS TME'!M:M,MATCH('xUS Opp Value'!$B9,'xUS TME'!$B:$B,0)) -> UAE Dirham | Q9: =INDEX('xUS TME'!N:N,MATCH('xUS Opp Value'!$B9,'xUS TME'!$B:$B,0)) -> 0
A10: ICICI Bank Ltd | B10: =INDEX('xUS TME'!B:B,MATCH('xUS Opp Value'!A10,'xUS TME'!A:A,0)) -> INE090A01021 | C10: =INDEX('xUS TME'!C:C,MATCH($B10,'xUS TME'!$B:$B,0)) -> ICICIBANK | D10: =INDEX('xUS TME'!D:D,MATCH(B10,'xUS TME'!$B:$B,0)) -> 0P0000BIOD | E10: =INDEX('xUS TME'!F:F,MATCH(B10,'xUS TME'!$B:$B,0)) -> India | F10: =INDEX('xUS TME'!G:G,MATCH(B10,'xUS TME'!$B:$B,0)) -> Financials | G10: =IFERROR(INDEX(CRIMs!G:G,MATCH(C10,CRIMs!D:D,0)),0) -> 0.5 | H10: =IFERROR(INDEX(CRIMs!I:I,MATCH(C10,CRIMs!D:D,0)),0) -> 0.53626582 | I10: =INDEX('xUS TME'!E:E,MATCH($B10,'xUS TME'!$B:$B,0)) -> 0.2 | J10: =INDEX('xUS TME'!H:H,MATCH(B10,'xUS TME'!$B:$B,0)) -> 0 | K10: =IFERROR((1/J10)-1,"") | L10: =INDEX('xUS TME'!J:J,MATCH('xUS Opp Value'!B10,'xUS TME'!$B:$B,0)) -> 16.76 | M10: =INDEX('xUS TME'!L:L,MATCH('xUS Opp Value'!$B10,'xUS TME'!$B:$B,0)) -> 2.73 | N10: =INDEX('xUS TME'!K:K,MATCH('xUS Opp Value'!$B10,'xUS TME'!$B:$B,0)) -> 0.19 | O10: =INDEX('xUS TME'!I:I,MATCH('xUS Opp Value'!$B10,'xUS TME'!$B:$B,0)) -> Narrow | P10: =INDEX('xUS TME'!M:M,MATCH('xUS Opp Value'!$B10,'xUS TME'!$B:$B,0)) -> Indian Rupee | Q10: =INDEX('xUS TME'!N:N,MATCH('xUS Opp Value'!$B10,'xUS TME'!$B:$B,0)) -> High
A11: Investor AB Class B | B11: =INDEX('xUS TME'!B:B,MATCH('xUS Opp Value'!A11,'xUS TME'!A:A,0)) -> SE0015811963 | C11: =INDEX('xUS TME'!C:C,MATCH($B11,'xUS TME'!$B:$B,0)) -> INVE B | D11: =INDEX('xUS TME'!D:D,MATCH(B11,'xUS TME'!$B:$B,0)) -> 0P0000A6GL | E11: =INDEX('xUS TME'!F:F,MATCH(B11,'xUS TME'!$B:$B,0)) -> Sweden | F11: =INDEX('xUS TME'!G:G,MATCH(B11,'xUS TME'!$B:$B,0)) -> Financials | G11: =IFERROR(INDEX(CRIMs!G:G,MATCH(C11,CRIMs!D:D,0)),0) -> 0 | H11: =IFERROR(INDEX(CRIMs!I:I,MATCH(C11,CRIMs!D:D,0)),0) -> 0 | I11: =INDEX('xUS TME'!E:E,MATCH($B11,'xUS TME'!$B:$B,0)) -> 0.21 | J11: =INDEX('xUS TME'!H:H,MATCH(B11,'xUS TME'!$B:$B,0)) -> 0 | K11: =IFERROR((1/J11)-1,"") | L11: =INDEX('xUS TME'!J:J,MATCH('xUS Opp Value'!B11,'xUS TME'!$B:$B,0)) -> 0 | M11: =INDEX('xUS TME'!L:L,MATCH('xUS Opp Value'!$B11,'xUS TME'!$B:$B,0)) -> 1.2 | N11: =INDEX('xUS TME'!K:K,MATCH('xUS Opp Value'!$B11,'xUS TME'!$B:$B,0)) -> 0.18 | O11: =INDEX('xUS TME'!I:I,MATCH('xUS Opp Value'!$B11,'xUS TME'!$B:$B,0)) -> 0 | P11: =INDEX('xUS TME'!M:M,MATCH('xUS Opp Value'!$B11,'xUS TME'!$B:$B,0)) -> Swedish Krona | Q11: =INDEX('xUS TME'!N:N,MATCH('xUS Opp Value'!$B11,'xUS TME'!$B:$B,0)) -> 0
A12: Samsung Electronics Co Ltd Participating Preferred | B12: =INDEX('xUS TME'!B:B,MATCH('xUS Opp Value'!A12,'xUS TME'!A:A,0)) -> KR7005931001 | C12: =INDEX('xUS TME'!C:C,MATCH($B12,'xUS TME'!$B:$B,0)) -> 5935 | D12: =INDEX('xUS TME'!D:D,MATCH(B12,'xUS TME'!$B:$B,0)) -> 0P0000D5B8 | E12: =INDEX('xUS TME'!F:F,MATCH(B12,'xUS TME'!$B:$B,0)) -> South Korea | F12: =INDEX('xUS TME'!G:G,MATCH(B12,'xUS TME'!$B:$B,0)) -> Information Technology | G12: =IFERROR(INDEX(CRIMs!G:G,MATCH(C12,CRIMs!D:D,0)),0) -> 0 | H12: =IFERROR(INDEX(CRIMs!I:I,MATCH(C12,CRIMs!D:D,0)),0) -> 0 | I12: =INDEX('xUS TME'!E:E,MATCH($B12,'xUS TME'!$B:$B,0)) -> 0.18 | J12: =INDEX('xUS TME'!H:H,MATCH(B12,'xUS TME'!$B:$B,0)) -> 0 | K12: =IFERROR((1/J12)-1,"") | L12: =INDEX('xUS TME'!J:J,MATCH('xUS Opp Value'!B12,'xUS TME'!$B:$B,0)) -> 5.07 | M12: =INDEX('xUS TME'!L:L,MATCH('xUS Opp Value'!$B12,'xUS TME'!$B:$B,0)) -> 2.21 | N12: =INDEX('xUS TME'!K:K,MATCH('xUS Opp Value'!$B12,'xUS TME'!$B:$B,0)) -> 0.11 | O12: =INDEX('xUS TME'!I:I,MATCH('xUS Opp Value'!$B12,'xUS TME'!$B:$B,0)) -> None | P12: =INDEX('xUS TME'!M:M,MATCH('xUS Opp Value'!$B12,'xUS TME'!$B:$B,0)) -> Won | Q12: =INDEX('xUS TME'!N:N,MATCH('xUS Opp Value'!$B12,'xUS TME'!$B:$B,0)) -> High
A13: Suncor Energy Inc | B13: =INDEX('xUS TME'!B:B,MATCH('xUS Opp Value'!A13,'xUS TME'!A:A,0)) -> CA8672241079 | C13: =INDEX('xUS TME'!C:C,MATCH($B13,'xUS TME'!$B:$B,0)) -> SU | D13: =INDEX('xUS TME'!D:D,MATCH(B13,'xUS TME'!$B:$B,0)) -> 0P0000688T | E13: =INDEX('xUS TME'!F:F,MATCH(B13,'xUS TME'!$B:$B,0)) -> Canada | F13: =INDEX('xUS TME'!G:G,MATCH(B13,'xUS TME'!$B:$B,0)) -> Energy | G13: =IFERROR(INDEX(CRIMs!G:G,MATCH(C13,CRIMs!D:D,0)),0) -> 0 | H13: =IFERROR(INDEX(CRIMs!I:I,MATCH(C13,CRIMs!D:D,0)),0) -> 0 | I13: =INDEX('xUS TME'!E:E,MATCH($B13,'xUS TME'!$B:$B,0)) -> 0.24 | J13: =INDEX('xUS TME'!H:H,MATCH(B13,'xUS TME'!$B:$B,0)) -> 0 | K13: =IFERROR((1/J13)-1,"") | L13: =INDEX('xUS TME'!J:J,MATCH('xUS Opp Value'!B13,'xUS TME'!$B:$B,0)) -> 9.02 | M13: =INDEX('xUS TME'!L:L,MATCH('xUS Opp Value'!$B13,'xUS TME'!$B:$B,0)) -> 2.36 | N13: =INDEX('xUS TME'!K:K,MATCH('xUS Opp Value'!$B13,'xUS TME'!$B:$B,0)) -> 0.13 | O13: =INDEX('xUS TME'!I:I,MATCH('xUS Opp Value'!$B13,'xUS TME'!$B:$B,0)) -> None | P13: =INDEX('xUS TME'!M:M,MATCH('xUS Opp Value'!$B13,'xUS TME'!$B:$B,0)) -> Canadian Dollar | Q13: =INDEX('xUS TME'!N:N,MATCH('xUS Opp Value'!$B13,'xUS TME'!$B:$B,0)) -> High
A14: Bharti Airtel Ltd | B14: =INDEX('xUS TME'!B:B,MATCH('xUS Opp Value'!A14,'xUS TME'!A:A,0)) -> INE397D01024 | C14: =INDEX('xUS TME'!C:C,MATCH($B14,'xUS TME'!$B:$B,0)) -> BHARTIARTL | D14: =INDEX('xUS TME'!D:D,MATCH(B14,'xUS TME'!$B:$B,0)) -> 0P0000BJR2 | E14: =INDEX('xUS TME'!F:F,MATCH(B14,'xUS TME'!$B:$B,0)) -> India | F14: =INDEX('xUS TME'!G:G,MATCH(B14,'xUS TME'!$B:$B,0)) -> Communication Services | G14: =IFERROR(INDEX(CRIMs!G:G,MATCH(C14,CRIMs!D:D,0)),0) -> 0 | H14: =IFERROR(INDEX(CRIMs!I:I,MATCH(C14,CRIMs!D:D,0)),0) -> 0 | I14: =INDEX('xUS TME'!E:E,MATCH($B14,'xUS TME'!$B:$B,0)) -> 0.19 | J14: =INDEX('xUS TME'!H:H,MATCH(B14,'xUS TME'!$B:$B,0)) -> 0 | K14: =IFERROR((1/J14)-1,"") | L14: =INDEX('xUS TME'!J:J,MATCH('xUS Opp Value'!B14,'xUS TME'!$B:$B,0)) -> 25.82 | M14: =INDEX('xUS TME'!L:L,MATCH('xUS Opp Value'!$B14,'xUS TME'!$B:$B,0)) -> 9.67 | N14: =INDEX('xUS TME'!K:K,MATCH('xUS Opp Value'!$B14,'xUS TME'!$B:$B,0)) -> 0.4 | O14: =INDEX('xUS TME'!I:I,MATCH('xUS Opp Value'!$B14,'xUS TME'!$B:$B,0)) -> Narrow | P14: =INDEX('xUS TME'!M:M,MATCH('xUS Opp Value'!$B14,'xUS TME'!$B:$B,0)) -> Indian Rupee | Q14: =INDEX('xUS TME'!N:N,MATCH('xUS Opp Value'!$B14,'xUS TME'!$B:$B,0)) -> Medium
A15: Wheaton Precious Metals Corp | B15: =INDEX('xUS TME'!B:B,MATCH('xUS Opp Value'!A15,'xUS TME'!A:A,0)) -> CA9628791027 | C15: =INDEX('xUS TME'!C:C,MATCH($B15,'xUS TME'!$B:$B,0)) -> WPM | D15: =INDEX('xUS TME'!D:D,MATCH(B15,'xUS TME'!$B:$B,0)) -> 0P00006888 | E15: =INDEX('xUS TME'!F:F,MATCH(B15,'xUS TME'!$B:$B,0)) -> Canada | F15: =INDEX('xUS TME'!G:G,MATCH(B15,'xUS TME'!$B:$B,0)) -> Materials | G15: =IFERROR(INDEX(CRIMs!G:G,MATCH(C15,CRIMs!D:D,0)),0) -> 0 | H15: =IFERROR(INDEX(CRIMs!I:I,MATCH(C15,CRIMs!D:D,0)),0) -> 0 | I15: =INDEX('xUS TME'!E:E,MATCH($B15,'xUS TME'!$B:$B,0)) -> 0.18 | J15: =INDEX('xUS TME'!H:H,MATCH(B15,'xUS TME'!$B:$B,0)) -> 0 | K15: =IFERROR((1/J15)-1,"") | L15: =INDEX('xUS TME'!J:J,MATCH('xUS Opp Value'!B15,'xUS TME'!$B:$B,0)) -> 24.58 | M15: =INDEX('xUS TME'!L:L,MATCH('xUS Opp Value'!$B15,'xUS TME'!$B:$B,0)) -> 7.67 | N15: =INDEX('xUS TME'!K:K,MATCH('xUS Opp Value'!$B15,'xUS TME'!$B:$B,0)) -> 0.19 | O15: =INDEX('xUS TME'!I:I,MATCH('xUS Opp Value'!$B15,'xUS TME'!$B:$B,0)) -> None | P15: =INDEX('xUS TME'!M:M,MATCH('xUS Opp Value'!$B15,'xUS TME'!$B:$B,0)) -> Canadian Dollar | Q15: =INDEX('xUS TME'!N:N,MATCH('xUS Opp Value'!$B15,'xUS TME'!$B:$B,0)) -> Very High
... A153: Itausa Investimentos ITAU SA Participating Preferred | B153: =INDEX('xUS TME'!B:B,MATCH('xUS Opp Value'!A153,'xUS TME'!A:A,0)) -> BRITSAACNPR7 | C153: =INDEX('xUS TME'!C:C,MATCH($B153,'xUS TME'!$B:$B,0)) -> ITSA4 | D153: =INDEX('xUS TME'!D:D,MATCH(B153,'xUS TME'!$B:$B,0)) -> 0P0000BOD7 | E153: =INDEX('xUS TME'!F:F,MATCH(B153,'xUS TME'!$B:$B,0)) -> Brazil | F153: =INDEX('xUS TME'!G:G,MATCH(B153,'xUS TME'!$B:$B,0)) -> Financials | G153: =IFERROR(INDEX(CRIMs!G:G,MATCH(C153,CRIMs!D:D,0)),0) -> 0 | H153: =IFERROR(INDEX(CRIMs!I:I,MATCH(C153,CRIMs!D:D,0)),0) -> 0 | I153: =INDEX('xUS TME'!E:E,MATCH($B153,'xUS TME'!$B:$B,0)) -> 0.05 | J153: =INDEX('xUS TME'!H:H,MATCH(B153,'xUS TME'!$B:$B,0)) -> 0 | K153: =IFERROR((1/J153)-1,"") | L153: =INDEX('xUS TME'!J:J,MATCH('xUS Opp Value'!B153,'xUS TME'!$B:$B,0)) -> 0 | M153: =INDEX('xUS TME'!L:L,MATCH('xUS Opp Value'!$B153,'xUS TME'!$B:$B,0)) -> 1.87 | N153: =INDEX('xUS TME'!K:K,MATCH('xUS Opp Value'!$B153,'xUS TME'!$B:$B,0)) -> 0.19 | O153: =INDEX('xUS TME'!I:I,MATCH('xUS Opp Value'!$B153,'xUS TME'!$B:$B,0)) -> 0 | P153: =INDEX('xUS TME'!M:M,MATCH('xUS Opp Value'!$B153,'xUS TME'!$B:$B,0)) -> Brazilian Real | Q153: =INDEX('xUS TME'!N:N,MATCH('xUS Opp Value'!$B153,'xUS TME'!$B:$B,0)) -> 0
A154: WuXi Biologics (Cayman) Inc | B154: =INDEX('xUS TME'!B:B,MATCH('xUS Opp Value'!A154,'xUS TME'!A:A,0)) -> KYG970081173 | C154: 2269h | D154: =INDEX('xUS TME'!D:D,MATCH(B154,'xUS TME'!$B:$B,0)) -> 0P0001AMNY | E154: =INDEX('xUS TME'!F:F,MATCH(B154,'xUS TME'!$B:$B,0)) -> China | F154: =INDEX('xUS TME'!G:G,MATCH(B154,'xUS TME'!$B:$B,0)) -> Health Care | G154: =IFERROR(INDEX(CRIMs!G:G,MATCH(C154,CRIMs!D:D,0)),0) -> 0 | H154: =IFERROR(INDEX(CRIMs!I:I,MATCH(C154,CRIMs!D:D,0)),0) -> 0 | I154: =INDEX('xUS TME'!E:E,MATCH($B154,'xUS TME'!$B:$B,0)) -> 0.05 | J154: =INDEX('xUS TME'!H:H,MATCH(B154,'xUS TME'!$B:$B,0)) -> 0.84 | K154: =IFERROR((1/J154)-1,"") -> 0.19047619 | L154: =INDEX('xUS TME'!J:J,MATCH('xUS Opp Value'!B154,'xUS TME'!$B:$B,0)) -> 22.07 | M154: =INDEX('xUS TME'!L:L,MATCH('xUS Opp Value'!$B154,'xUS TME'!$B:$B,0)) -> 2.82 | N154: =INDEX('xUS TME'!K:K,MATCH('xUS Opp Value'!$B154,'xUS TME'!$B:$B,0)) -> 0.1 | O154: =INDEX('xUS TME'!I:I,MATCH('xUS Opp Value'!$B154,'xUS TME'!$B:$B,0)) -> Narrow | P154: =INDEX('xUS TME'!M:M,MATCH('xUS Opp Value'!$B154,'xUS TME'!$B:$B,0)) -> Hong Kong Dollar | Q154: =INDEX('xUS TME'!N:N,MATCH('xUS Opp Value'!$B154,'xUS TME'!$B:$B,0)) -> Very High
A155: Imperial Oil Ltd | B155: =INDEX('xUS TME'!B:B,MATCH('xUS Opp Value'!A155,'xUS TME'!A:A,0)) -> CA4530384086 | C155: =INDEX('xUS TME'!C:C,MATCH($B155,'xUS TME'!$B:$B,0)) -> IMO | D155: =INDEX('xUS TME'!D:D,MATCH(B155,'xUS TME'!$B:$B,0)) -> 0P0000683H | E155: =INDEX('xUS TME'!F:F,MATCH(B155,'xUS TME'!$B:$B,0)) -> Canada | F155: =INDEX('xUS TME'!G:G,MATCH(B155,'xUS TME'!$B:$B,0)) -> Energy | G155: =IFERROR(INDEX(CRIMs!G:G,MATCH(C155,CRIMs!D:D,0)),0) -> 0 | H155: =IFERROR(INDEX(CRIMs!I:I,MATCH(C155,CRIMs!D:D,0)),0) -> 0 | I155: =INDEX('xUS TME'!E:E,MATCH($B155,'xUS TME'!$B:$B,0)) -> 0.06 | J155: =INDEX('xUS TME'!H:H,MATCH(B155,'xUS TME'!$B:$B,0)) -> 0 | K155: =IFERROR((1/J155)-1,"") | L155: =INDEX('xUS TME'!J:J,MATCH('xUS Opp Value'!B155,'xUS TME'!$B:$B,0)) -> 15.88 | M155: =INDEX('xUS TME'!L:L,MATCH('xUS Opp Value'!$B155,'xUS TME'!$B:$B,0)) -> 3.89 | N155: =INDEX('xUS TME'!K:K,MATCH('xUS Opp Value'!$B155,'xUS TME'!$B:$B,0)) -> 0.14 | O155: =INDEX('xUS TME'!I:I,MATCH('xUS Opp Value'!$B155,'xUS TME'!$B:$B,0)) -> None | P155: =INDEX('xUS TME'!M:M,MATCH('xUS Opp Value'!$B155,'xUS TME'!$B:$B,0)) -> Canadian Dollar | Q155: =INDEX('xUS TME'!N:N,MATCH('xUS Opp Value'!$B155,'xUS TME'!$B:$B,0)) -> High
A156: Kansai Electric Power Co Inc | B156: =INDEX('xUS TME'!B:B,MATCH('xUS Opp Value'!A156,'xUS TME'!A:A,0)) -> JP3228600007 | C156: =INDEX('xUS TME'!C:C,MATCH($B156,'xUS TME'!$B:$B,0)) -> 9503 | D156: =INDEX('xUS TME'!D:D,MATCH(B156,'xUS TME'!$B:$B,0)) -> 0P0000AEYS | E156: =INDEX('xUS TME'!F:F,MATCH(B156,'xUS TME'!$B:$B,0)) -> Japan | F156: =INDEX('xUS TME'!G:G,MATCH(B156,'xUS TME'!$B:$B,0)) -> Utilities | G156: =IFERROR(INDEX(CRIMs!G:G,MATCH(C156,CRIMs!D:D,0)),0) -> 0 | H156: =IFERROR(INDEX(CRIMs!I:I,MATCH(C156,CRIMs!D:D,0)),0) -> 0 | I156: =INDEX('xUS TME'!E:E,MATCH($B156,'xUS TME'!$B:$B,0)) -> 0.05 | J156: =INDEX('xUS TME'!H:H,MATCH(B156,'xUS TME'!$B:$B,0)) -> 0 | K156: =IFERROR((1/J156)-1,"") | L156: =INDEX('xUS TME'!J:J,MATCH('xUS Opp Value'!B156,'xUS TME'!$B:$B,0)) -> 0 | M156: =INDEX('xUS TME'!L:L,MATCH('xUS Opp Value'!$B156,'xUS TME'!$B:$B,0)) -> 0.86 | N156: =INDEX('xUS TME'!K:K,MATCH('xUS Opp Value'!$B156,'xUS TME'!$B:$B,0)) -> 0.17 | O156: =INDEX('xUS TME'!I:I,MATCH('xUS Opp Value'!$B156,'xUS TME'!$B:$B,0)) -> 0 | P156: =INDEX('xUS TME'!M:M,MATCH('xUS Opp Value'!$B156,'xUS TME'!$B:$B,0)) -> Yen | Q156: =INDEX('xUS TME'!N:N,MATCH('xUS Opp Value'!$B156,'xUS TME'!$B:$B,0)) -> 0
A157: E. Sun Financial Holding Co Ltd | B157: =INDEX('xUS TME'!B:B,MATCH('xUS Opp Value'!A157,'xUS TME'!A:A,0)) -> TW0002884004 | C157: =INDEX('xUS TME'!C:C,MATCH($B157,'xUS TME'!$B:$B,0)) -> 2884 | D157: =INDEX('xUS TME'!D:D,MATCH(B157,'xUS TME'!$B:$B,0)) -> 0P0000AN3L | E157: =INDEX('xUS TME'!F:F,MATCH(B157,'xUS TME'!$B:$B,0)) -> Taiwan | F157: =INDEX('xUS TME'!G:G,MATCH(B157,'xUS TME'!$B:$B,0)) -> Financials | G157: =IFERROR(INDEX(CRIMs!G:G,MATCH(C157,CRIMs!D:D,0)),0) -> 0 | H157: =IFERROR(INDEX(CRIMs!I:I,MATCH(C157,CRIMs!D:D,0)),0) -> 0 | I157: =INDEX('xUS TME'!E:E,MATCH($B157,'xUS TME'!$B:$B,0)) -> 0.05 | J157: =INDEX('xUS TME'!H:H,MATCH(B157,'xUS TME'!$B:$B,0)) -> 0 | K157: =IFERROR((1/J157)-1,"") | L157: =INDEX('xUS TME'!J:J,MATCH('xUS Opp Value'!B157,'xUS TME'!$B:$B,0)) -> 14.76 | M157: =INDEX('xUS TME'!L:L,MATCH('xUS Opp Value'!$B157,'xUS TME'!$B:$B,0)) -> 1.91 | N157: =INDEX('xUS TME'!K:K,MATCH('xUS Opp Value'!$B157,'xUS TME'!$B:$B,0)) -> 0.13 | O157: =INDEX('xUS TME'!I:I,MATCH('xUS Opp Value'!$B157,'xUS TME'!$B:$B,0)) -> 0 | P157: =INDEX('xUS TME'!M:M,MATCH('xUS Opp Value'!$B157,'xUS TME'!$B:$B,0)) -> New Taiwan Dollar | Q157: =INDEX('xUS TME'!N:N,MATCH('xUS Opp Value'!$B157,'xUS TME'!$B:$B,0)) -> 0
A158: Tenaga Nasional Bhd | B158: =INDEX('xUS TME'!B:B,MATCH('xUS Opp Value'!A158,'xUS TME'!A:A,0)) -> MYL5347OO009 | C158: =INDEX('xUS TME'!C:C,MATCH($B158,'xUS TME'!$B:$B,0)) -> 5347 | D158: =INDEX('xUS TME'!D:D,MATCH(B158,'xUS TME'!$B:$B,0)) -> 0P0000AJ2W | E158: =INDEX('xUS TME'!F:F,MATCH(B158,'xUS TME'!$B:$B,0)) -> Malaysia | F158: =INDEX('xUS TME'!G:G,MATCH(B158,'xUS TME'!$B:$B,0)) -> Utilities | G158: =IFERROR(INDEX(CRIMs!G:G,MATCH(C158,CRIMs!D:D,0)),0) -> 0 | H158: =IFERROR(INDEX(CRIMs!I:I,MATCH(C158,CRIMs!D:D,0)),0) -> 0 | I158: =INDEX('xUS TME'!E:E,MATCH($B158,'xUS TME'!$B:$B,0)) -> 0.05 | J158: =INDEX('xUS TME'!H:H,MATCH(B158,'xUS TME'!$B:$B,0)) -> 0 | K158: =IFERROR((1/J158)-1,"") | L158: =INDEX('xUS TME'!J:J,MATCH('xUS Opp Value'!B158,'xUS TME'!$B:$B,0)) -> 17.47 | M158: =INDEX('xUS TME'!L:L,MATCH('xUS Opp Value'!$B158,'xUS TME'!$B:$B,0)) -> 1.62 | N158: =INDEX('xUS TME'!K:K,MATCH('xUS Opp Value'!$B158,'xUS TME'!$B:$B,0)) -> 0.08 | O158: =INDEX('xUS TME'!I:I,MATCH('xUS Opp Value'!$B158,'xUS TME'!$B:$B,0)) -> 0 | P158: =INDEX('xUS TME'!M:M,MATCH('xUS Opp Value'!$B158,'xUS TME'!$B:$B,0)) -> Malaysian Ringgit | Q158: =INDEX('xUS TME'!N:N,MATCH('xUS Opp Value'!$B158,'xUS TME'!$B:$B,0)) -> 0
A159: FinecoBank SpA | B159: =INDEX('xUS TME'!B:B,MATCH('xUS Opp Value'!A159,'xUS TME'!A:A,0)) -> IT0000072170 | C159: =INDEX('xUS TME'!C:C,MATCH($B159,'xUS TME'!$B:$B,0)) -> FBK | D159: =INDEX('xUS TME'!D:D,MATCH(B159,'xUS TME'!$B:$B,0)) -> 0P00013KWW | E159: =INDEX('xUS TME'!F:F,MATCH(B159,'xUS TME'!$B:$B,0)) -> Italy | F159: =INDEX('xUS TME'!G:G,MATCH(B159,'xUS TME'!$B:$B,0)) -> Financials | G159: =IFERROR(INDEX(CRIMs!G:G,MATCH(C159,CRIMs!D:D,0)),0) -> 0 | H159: =IFERROR(INDEX(CRIMs!I:I,MATCH(C159,CRIMs!D:D,0)),0) -> 0 | I159: =INDEX('xUS TME'!E:E,MATCH($B159,'xUS TME'!$B:$B,0)) -> 0.04 | J159: =INDEX('xUS TME'!H:H,MATCH(B159,'xUS TME'!$B:$B,0)) -> 0 | K159: =IFERROR((1/J159)-1,"") | L159: =INDEX('xUS TME'!J:J,MATCH('xUS Opp Value'!B159,'xUS TME'!$B:$B,0)) -> 24.89 | M159: =INDEX('xUS TME'!L:L,MATCH('xUS Opp Value'!$B159,'xUS TME'!$B:$B,0)) -> 6.19 | N159: =INDEX('xUS TME'!K:K,MATCH('xUS Opp Value'!$B159,'xUS TME'!$B:$B,0)) -> 0.34 | O159: =INDEX('xUS TME'!I:I,MATCH('xUS Opp Value'!$B159,'xUS TME'!$B:$B,0)) -> 0 | P159: =INDEX('xUS TME'!M:M,MATCH('xUS Opp Value'!$B159,'xUS TME'!$B:$B,0)) -> Euro | Q159: =INDEX('xUS TME'!N:N,MATCH('xUS Opp Value'!$B159,'xUS TME'!$B:$B,0)) -> 0
A160: Unimicron Technology Corp | B160: =INDEX('xUS TME'!B:B,MATCH('xUS Opp Value'!A160,'xUS TME'!A:A,0)) -> TW0003037008 | C160: =INDEX('xUS TME'!C:C,MATCH($B160,'xUS TME'!$B:$B,0)) -> 3037 | D160: =INDEX('xUS TME'!D:D,MATCH(B160,'xUS TME'!$B:$B,0)) -> 0P0000BQ66 | E160: =INDEX('xUS TME'!F:F,MATCH(B160,'xUS TME'!$B:$B,0)) -> Taiwan | F160: =INDEX('xUS TME'!G:G,MATCH(B160,'xUS TME'!$B:$B,0)) -> Information Technology | G160: =IFERROR(INDEX(CRIMs!G:G,MATCH(C160,CRIMs!D:D,0)),0) -> 0 | H160: =IFERROR(INDEX(CRIMs!I:I,MATCH(C160,CRIMs!D:D,0)),0) -> 0 | I160: =INDEX('xUS TME'!E:E,MATCH($B160,'xUS TME'!$B:$B,0)) -> 0.06 | J160: =INDEX('xUS TME'!H:H,MATCH(B160,'xUS TME'!$B:$B,0)) -> 0 | K160: =IFERROR((1/J160)-1,"") | L160: =INDEX('xUS TME'!J:J,MATCH('xUS Opp Value'!B160,'xUS TME'!$B:$B,0)) -> 12.28 | M160: =INDEX('xUS TME'!L:L,MATCH('xUS Opp Value'!$B160,'xUS TME'!$B:$B,0)) -> 9.7 | N160: =INDEX('xUS TME'!K:K,MATCH('xUS Opp Value'!$B160,'xUS TME'!$B:$B,0)) -> 0.08 | O160: =INDEX('xUS TME'!I:I,MATCH('xUS Opp Value'!$B160,'xUS TME'!$B:$B,0)) -> 0 | P160: =INDEX('xUS TME'!M:M,MATCH('xUS Opp Value'!$B160,'xUS TME'!$B:$B,0)) -> New Taiwan Dollar | Q160: =INDEX('xUS TME'!N:N,MATCH('xUS Opp Value'!$B160,'xUS TME'!$B:$B,0)) -> 0
A161: Chunghwa Telecom Co Ltd | B161: =INDEX('xUS TME'!B:B,MATCH('xUS Opp Value'!A161,'xUS TME'!A:A,0)) -> TW0002412004 | C161: =INDEX('xUS TME'!C:C,MATCH($B161,'xUS TME'!$B:$B,0)) -> 2412 | D161: =INDEX('xUS TME'!D:D,MATCH(B161,'xUS TME'!$B:$B,0)) -> 0P0000BO2I | E161: =INDEX('xUS TME'!F:F,MATCH(B161,'xUS TME'!$B:$B,0)) -> Taiwan | F161: =INDEX('xUS TME'!G:G,MATCH(B161,'xUS TME'!$B:$B,0)) -> Communication Services | G161: =IFERROR(INDEX(CRIMs!G:G,MATCH(C161,CRIMs!D:D,0)),0) -> 0 | H161: =IFERROR(INDEX(CRIMs!I:I,MATCH(C161,CRIMs!D:D,0)),0) -> 0 | I161: =INDEX('xUS TME'!E:E,MATCH($B161,'xUS TME'!$B:$B,0)) -> 0.05 | J161: =INDEX('xUS TME'!H:H,MATCH(B161,'xUS TME'!$B:$B,0)) -> 0 | K161: =IFERROR((1/J161)-1,"") | L161: =INDEX('xUS TME'!J:J,MATCH('xUS Opp Value'!B161,'xUS TME'!$B:$B,0)) -> 26.27 | M161: =INDEX('xUS TME'!L:L,MATCH('xUS Opp Value'!$B161,'xUS TME'!$B:$B,0)) -> 2.72 | N161: =INDEX('xUS TME'!K:K,MATCH('xUS Opp Value'!$B161,'xUS TME'!$B:$B,0)) -> 0.11 | O161: =INDEX('xUS TME'!I:I,MATCH('xUS Opp Value'!$B161,'xUS TME'!$B:$B,0)) -> Narrow | P161: =INDEX('xUS TME'!M:M,MATCH('xUS Opp Value'!$B161,'xUS TME'!$B:$B,0)) -> New Taiwan Dollar | Q161: =INDEX('xUS TME'!N:N,MATCH('xUS Opp Value'!$B161,'xUS TME'!$B:$B,0)) -> Medium
A162: B3 SA - Brasil Bolsa Balcao | B162: =INDEX('xUS TME'!B:B,MATCH('xUS Opp Value'!A162,'xUS TME'!A:A,0)) -> BRB3SAACNOR6 | C162: =INDEX('xUS TME'!C:C,MATCH($B162,'xUS TME'!$B:$B,0)) -> B3SA3 | D162: =INDEX('xUS TME'!D:D,MATCH(B162,'xUS TME'!$B:$B,0)) -> 0P0000I29S | E162: =INDEX('xUS TME'!F:F,MATCH(B162,'xUS TME'!$B:$B,0)) -> Brazil | F162: =INDEX('xUS TME'!G:G,MATCH(B162,'xUS TME'!$B:$B,0)) -> Financials | G162: =IFERROR(INDEX(CRIMs!G:G,MATCH(C162,CRIMs!D:D,0)),0) -> 0.75 | H162: =IFERROR(INDEX(CRIMs!I:I,MATCH(C162,CRIMs!D:D,0)),0) -> 1.0363536 | I162: =INDEX('xUS TME'!E:E,MATCH($B162,'xUS TME'!$B:$B,0)) -> 0.05 | J162: =INDEX('xUS TME'!H:H,MATCH(B162,'xUS TME'!$B:$B,0)) -> 0 | K162: =IFERROR((1/J162)-1,"") | L162: =INDEX('xUS TME'!J:J,MATCH('xUS Opp Value'!B162,'xUS TME'!$B:$B,0)) -> 16.89 | M162: =INDEX('xUS TME'!L:L,MATCH('xUS Opp Value'!$B162,'xUS TME'!$B:$B,0)) -> 5.63 | N162: =INDEX('xUS TME'!K:K,MATCH('xUS Opp Value'!$B162,'xUS TME'!$B:$B,0)) -> 0.24 | O162: =INDEX('xUS TME'!I:I,MATCH('xUS Opp Value'!$B162,'xUS TME'!$B:$B,0)) -> 0 | P162: =INDEX('xUS TME'!M:M,MATCH('xUS Opp Value'!$B162,'xUS TME'!$B:$B,0)) -> Brazilian Real | Q162: =INDEX('xUS TME'!N:N,MATCH('xUS Opp Value'!$B162,'xUS TME'!$B:$B,0)) -> 0
A163: Sumitomo Metal Mining Co Ltd | B163: =INDEX('xUS TME'!B:B,MATCH('xUS Opp Value'!A163,'xUS TME'!A:A,0)) -> JP3402600005 | C163: =INDEX('xUS TME'!C:C,MATCH($B163,'xUS TME'!$B:$B,0)) -> 5713 | D163: =INDEX('xUS TME'!D:D,MATCH(B163,'xUS TME'!$B:$B,0)) -> 0P0000AEY8 | E163: =INDEX('xUS TME'!F:F,MATCH(B163,'xUS TME'!$B:$B,0)) -> Japan | F163: =INDEX('xUS TME'!G:G,MATCH(B163,'xUS TME'!$B:$B,0)) -> Materials | G163: =IFERROR(INDEX(CRIMs!G:G,MATCH(C163,CRIMs!D:D,0)),0) -> 0 | H163: =IFERROR(INDEX(CRIMs!I:I,MATCH(C163,CRIMs!D:D,0)),0) -> 0 | I163: =INDEX('xUS TME'!E:E,MATCH($B163,'xUS TME'!$B:$B,0)) -> 0.04 | J163: =INDEX('xUS TME'!H:H,MATCH(B163,'xUS TME'!$B:$B,0)) -> 0 | K163: =IFERROR((1/J163)-1,"") | L163: =INDEX('xUS TME'!J:J,MATCH('xUS Opp Value'!B163,'xUS TME'!$B:$B,0)) -> 0 | M163: =INDEX('xUS TME'!L:L,MATCH('xUS Opp Value'!$B163,'xUS TME'!$B:$B,0)) -> 1.42 | N163: =INDEX('xUS TME'!K:K,MATCH('xUS Opp Value'!$B163,'xUS TME'!$B:$B,0)) -> 0.01 | O163: =INDEX('xUS TME'!I:I,MATCH('xUS Opp Value'!$B163,'xUS TME'!$B:$B,0)) -> 0 | P163: =INDEX('xUS TME'!M:M,MATCH('xUS Opp Value'!$B163,'xUS TME'!$B:$B,0)) -> Yen | Q163: =INDEX('xUS TME'!N:N,MATCH('xUS Opp Value'!$B163,'xUS TME'!$B:$B,0)) -> 0
A164: Wal - Mart de Mexico SAB de CV | B164: =INDEX('xUS TME'!B:B,MATCH('xUS Opp Value'!A164,'xUS TME'!A:A,0)) -> MX01WA000038 | C164: =INDEX('xUS TME'!C:C,MATCH($B164,'xUS TME'!$B:$B,0)) -> WALMEX | D164: =INDEX('xUS TME'!D:D,MATCH(B164,'xUS TME'!$B:$B,0)) -> 0P0000BXAY | E164: =INDEX('xUS TME'!F:F,MATCH(B164,'xUS TME'!$B:$B,0)) -> Mexico | F164: =INDEX('xUS TME'!G:G,MATCH(B164,'xUS TME'!$B:$B,0)) -> Consumer Staples | G164: 0.5 | H164: 0.52 | I164: =INDEX('xUS TME'!E:E,MATCH($B164,'xUS TME'!$B:$B,0)) -> 0.05 | J164: =INDEX('xUS TME'!H:H,MATCH(B164,'xUS TME'!$B:$B,0)) -> 0 | K164: =IFERROR((1/J164)-1,"") | L164: =INDEX('xUS TME'!J:J,MATCH('xUS Opp Value'!B164,'xUS TME'!$B:$B,0)) -> 18.35 | M164: =INDEX('xUS TME'!L:L,MATCH('xUS Opp Value'!$B164,'xUS TME'!$B:$B,0)) -> 4.07 | N164: =INDEX('xUS TME'!K:K,MATCH('xUS Opp Value'!$B164,'xUS TME'!$B:$B,0)) -> 0.21 | O164: =INDEX('xUS TME'!I:I,MATCH('xUS Opp Value'!$B164,'xUS TME'!$B:$B,0)) -> 0 | P164: =INDEX('xUS TME'!M:M,MATCH('xUS Opp Value'!$B164,'xUS TME'!$B:$B,0)) -> Mexican Peso | Q164: =INDEX('xUS TME'!N:N,MATCH('xUS Opp Value'!$B164,'xUS TME'!$B:$B,0)) -> 0
A165: Obayashi Corp | B165: =INDEX('xUS TME'!B:B,MATCH('xUS Opp Value'!A165,'xUS TME'!A:A,0)) -> JP3190000004 | C165: =INDEX('xUS TME'!C:C,MATCH($B165,'xUS TME'!$B:$B,0)) -> 1802 | D165: =INDEX('xUS TME'!D:D,MATCH(B165,'xUS TME'!$B:$B,0)) -> 0P0000AEX9 | E165: =INDEX('xUS TME'!F:F,MATCH(B165,'xUS TME'!$B:$B,0)) -> Japan | F165: =INDEX('xUS TME'!G:G,MATCH(B165,'xUS TME'!$B:$B,0)) -> Industrials | G165: =IFERROR(INDEX(CRIMs!G:G,MATCH(C165,CRIMs!D:D,0)),0) -> 0 | H165: =IFERROR(INDEX(CRIMs!I:I,MATCH(C165,CRIMs!D:D,0)),0) -> 0 | I165: =INDEX('xUS TME'!E:E,MATCH($B165,'xUS TME'!$B:$B,0)) -> 0.05 | J165: =INDEX('xUS TME'!H:H,MATCH(B165,'xUS TME'!$B:$B,0)) -> 0 | K165: =IFERROR((1/J165)-1,"") | L165: =INDEX('xUS TME'!J:J,MATCH('xUS Opp Value'!B165,'xUS TME'!$B:$B,0)) -> 0 | M165: =INDEX('xUS TME'!L:L,MATCH('xUS Opp Value'!$B165,'xUS TME'!$B:$B,0)) -> 2.18 | N165: =INDEX('xUS TME'!K:K,MATCH('xUS Opp Value'!$B165,'xUS TME'!$B:$B,0)) -> 0.13 | O165: =INDEX('xUS TME'!I:I,MATCH('xUS Opp Value'!$B165,'xUS TME'!$B:$B,0)) -> 0 | P165: =INDEX('xUS TME'!M:M,MATCH('xUS Opp Value'!$B165,'xUS TME'!$B:$B,0)) -> Yen | Q165: =INDEX('xUS TME'!N:N,MATCH('xUS Opp Value'!$B165,'xUS TME'!$B:$B,0)) -> 0
A166: Taisei Corp | B166: =INDEX('xUS TME'!B:B,MATCH('xUS Opp Value'!A166,'xUS TME'!A:A,0)) -> JP3443600006 | C166: =INDEX('xUS TME'!C:C,MATCH($B166,'xUS TME'!$B:$B,0)) -> 1801 | D166: =INDEX('xUS TME'!D:D,MATCH(B166,'xUS TME'!$B:$B,0)) -> 0P0000AEYH | E166: =INDEX('xUS TME'!F:F,MATCH(B166,'xUS TME'!$B:$B,0)) -> Japan | F166: =INDEX('xUS TME'!G:G,MATCH(B166,'xUS TME'!$B:$B,0)) -> Industrials | G166: =IFERROR(INDEX(CRIMs!G:G,MATCH(C166,CRIMs!D:D,0)),0) -> 0 | H166: =IFERROR(INDEX(CRIMs!I:I,MATCH(C166,CRIMs!D:D,0)),0) -> 0 | I166: =INDEX('xUS TME'!E:E,MATCH($B166,'xUS TME'!$B:$B,0)) -> 0.05 | J166: =INDEX('xUS TME'!H:H,MATCH(B166,'xUS TME'!$B:$B,0)) -> 0 | K166: =IFERROR((1/J166)-1,"") | L166: =INDEX('xUS TME'!J:J,MATCH('xUS Opp Value'!B166,'xUS TME'!$B:$B,0)) -> 0 | M166: =INDEX('xUS TME'!L:L,MATCH('xUS Opp Value'!$B166,'xUS TME'!$B:$B,0)) -> 3.1 | N166: =INDEX('xUS TME'!K:K,MATCH('xUS Opp Value'!$B166,'xUS TME'!$B:$B,0)) -> 0.14 | O166: =INDEX('xUS TME'!I:I,MATCH('xUS Opp Value'!$B166,'xUS TME'!$B:$B,0)) -> 0 | P166: =INDEX('xUS TME'!M:M,MATCH('xUS Opp Value'!$B166,'xUS TME'!$B:$B,0)) -> Yen | Q166: =INDEX('xUS TME'!N:N,MATCH('xUS Opp Value'!$B166,'xUS TME'!$B:$B,0)) -> 0
A167: Schindler Holding AG Non Voting | B167: =INDEX('xUS TME'!B:B,MATCH('xUS Opp Value'!A167,'xUS TME'!A:A,0)) -> CH0024638196 | C167: =INDEX('xUS TME'!C:C,MATCH($B167,'xUS TME'!$B:$B,0)) -> SCHP | D167: =INDEX('xUS TME'!D:D,MATCH(B167,'xUS TME'!$B:$B,0)) -> 0P0000B4Y4 | E167: =INDEX('xUS TME'!F:F,MATCH(B167,'xUS TME'!$B:$B,0)) -> Switzerland | F167: =INDEX('xUS TME'!G:G,MATCH(B167,'xUS TME'!$B:$B,0)) -> Industrials | G167: =IFERROR(INDEX(CRIMs!G:G,MATCH(C167,CRIMs!D:D,0)),0) -> 0 | H167: =IFERROR(INDEX(CRIMs!I:I,MATCH(C167,CRIMs!D:D,0)),0) -> 0 | I167: =INDEX('xUS TME'!E:E,MATCH($B167,'xUS TME'!$B:$B,0)) -> 0.04 | J167: =INDEX('xUS TME'!H:H,MATCH(B167,'xUS TME'!$B:$B,0)) -> 0 | K167: =IFERROR((1/J167)-1,"") | L167: =INDEX('xUS TME'!J:J,MATCH('xUS Opp Value'!B167,'xUS TME'!$B:$B,0)) -> 25.74 | M167: =INDEX('xUS TME'!L:L,MATCH('xUS Opp Value'!$B167,'xUS TME'!$B:$B,0)) -> 5.73 | N167: =INDEX('xUS TME'!K:K,MATCH('xUS Opp Value'!$B167,'xUS TME'!$B:$B,0)) -> 0.22 | O167: =INDEX('xUS TME'!I:I,MATCH('xUS Opp Value'!$B167,'xUS TME'!$B:$B,0)) -> Wide | P167: =INDEX('xUS TME'!M:M,MATCH('xUS Opp Value'!$B167,'xUS TME'!$B:$B,0)) -> Swiss Franc | Q167: =INDEX('xUS TME'!N:N,MATCH('xUS Opp Value'!$B167,'xUS TME'!$B:$B,0)) -> Low
A168: Weg SA | B168: =INDEX('xUS TME'!B:B,MATCH('xUS Opp Value'!A168,'xUS TME'!A:A,0)) -> BRWEGEACNOR0 | C168: =INDEX('xUS TME'!C:C,MATCH($B168,'xUS TME'!$B:$B,0)) -> WEGE3 | D168: =INDEX('xUS TME'!D:D,MATCH(B168,'xUS TME'!$B:$B,0)) -> 0P0000CJQ0 | E168: =INDEX('xUS TME'!F:F,MATCH(B168,'xUS TME'!$B:$B,0)) -> Brazil | F168: =INDEX('xUS TME'!G:G,MATCH(B168,'xUS TME'!$B:$B,0)) -> Industrials | G168: =IFERROR(INDEX(CRIMs!G:G,MATCH(C168,CRIMs!D:D,0)),0) -> 0 | H168: =IFERROR(INDEX(CRIMs!I:I,MATCH(C168,CRIMs!D:D,0)),0) -> 0 | I168: =INDEX('xUS TME'!E:E,MATCH($B168,'xUS TME'!$B:$B,0)) -> 0.05 | J168: =INDEX('xUS TME'!H:H,MATCH(B168,'xUS TME'!$B:$B,0)) -> 0 | K168: =IFERROR((1/J168)-1,"") | L168: =INDEX('xUS TME'!J:J,MATCH('xUS Opp Value'!B168,'xUS TME'!$B:$B,0)) -> 27.5 | M168: =INDEX('xUS TME'!L:L,MATCH('xUS Opp Value'!$B168,'xUS TME'!$B:$B,0)) -> 12.75 | N168: =INDEX('xUS TME'!K:K,MATCH('xUS Opp Value'!$B168,'xUS TME'!$B:$B,0)) -> 0.32 | O168: =INDEX('xUS TME'!I:I,MATCH('xUS Opp Value'!$B168,'xUS TME'!$B:$B,0)) -> 0 | P168: =INDEX('xUS TME'!M:M,MATCH('xUS Opp Value'!$B168,'xUS TME'!$B:$B,0)) -> Brazilian Real | Q168: =INDEX('xUS TME'!N:N,MATCH('xUS Opp Value'!$B168,'xUS TME'!$B:$B,0)) -> 0
A169: Asia Vital Components Co Ltd | B169: =INDEX('xUS TME'!B:B,MATCH('xUS Opp Value'!A169,'xUS TME'!A:A,0)) -> TW0003017000 | C169: =INDEX('xUS TME'!C:C,MATCH($B169,'xUS TME'!$B:$B,0)) -> 3017 | D169: =INDEX('xUS TME'!D:D,MATCH(B169,'xUS TME'!$B:$B,0)) -> 0P0000AJTZ | E169: =INDEX('xUS TME'!F:F,MATCH(B169,'xUS TME'!$B:$B,0)) -> Taiwan | F169: =INDEX('xUS TME'!G:G,MATCH(B169,'xUS TME'!$B:$B,0)) -> Information Technology | G169: =IFERROR(INDEX(CRIMs!G:G,MATCH(C169,CRIMs!D:D,0)),0) -> 0 | H169: =IFERROR(INDEX(CRIMs!I:I,MATCH(C169,CRIMs!D:D,0)),0) -> 0 | I169: =INDEX('xUS TME'!E:E,MATCH($B169,'xUS TME'!$B:$B,0)) -> 0.06 | J169: =INDEX('xUS TME'!H:H,MATCH(B169,'xUS TME'!$B:$B,0)) -> 0 | K169: =IFERROR((1/J169)-1,"") | L169: =INDEX('xUS TME'!J:J,MATCH('xUS Opp Value'!B169,'xUS TME'!$B:$B,0)) -> 0 | M169: =INDEX('xUS TME'!L:L,MATCH('xUS Opp Value'!$B169,'xUS TME'!$B:$B,0)) -> 19.84 | N169: =INDEX('xUS TME'!K:K,MATCH('xUS Opp Value'!$B169,'xUS TME'!$B:$B,0)) -> 0.62 | O169: =INDEX('xUS TME'!I:I,MATCH('xUS Opp Value'!$B169,'xUS TME'!$B:$B,0)) -> 0 | P169: =INDEX('xUS TME'!M:M,MATCH('xUS Opp Value'!$B169,'xUS TME'!$B:$B,0)) -> New Taiwan Dollar | Q169: =INDEX('xUS TME'!N:N,MATCH('xUS Opp Value'!$B169,'xUS TME'!$B:$B,0)) -> 0
A170: Tokyo Gas Co Ltd | B170: =INDEX('xUS TME'!B:B,MATCH('xUS Opp Value'!A170,'xUS TME'!A:A,0)) -> JP3573000001 | C170: =INDEX('xUS TME'!C:C,MATCH($B170,'xUS TME'!$B:$B,0)) -> 9531 | D170: =INDEX('xUS TME'!D:D,MATCH(B170,'xUS TME'!$B:$B,0)) -> 0P0000AEZ4 | E170: =INDEX('xUS TME'!F:F,MATCH(B170,'xUS TME'!$B:$B,0)) -> Japan | F170: =INDEX('xUS TME'!G:G,MATCH(B170,'xUS TME'!$B:$B,0)) -> Utilities | G170: =IFERROR(INDEX(CRIMs!G:G,MATCH(C170,CRIMs!D:D,0)),0) -> 0 | H170: =IFERROR(INDEX(CRIMs!I:I,MATCH(C170,CRIMs!D:D,0)),0) -> 0 | I170: =INDEX('xUS TME'!E:E,MATCH($B170,'xUS TME'!$B:$B,0)) -> 0.05 | J170: =INDEX('xUS TME'!H:H,MATCH(B170,'xUS TME'!$B:$B,0)) -> 0 | K170: =IFERROR((1/J170)-1,"") | L170: =INDEX('xUS TME'!J:J,MATCH('xUS Opp Value'!B170,'xUS TME'!$B:$B,0)) -> 0 | M170: =INDEX('xUS TME'!L:L,MATCH('xUS Opp Value'!$B170,'xUS TME'!$B:$B,0)) -> 1.54 | N170: =INDEX('xUS TME'!K:K,MATCH('xUS Opp Value'!$B170,'xUS TME'!$B:$B,0)) -> 0.04 | O170: =INDEX('xUS TME'!I:I,MATCH('xUS Opp Value'!$B170,'xUS TME'!$B:$B,0)) -> 0 | P170: =INDEX('xUS TME'!M:M,MATCH('xUS Opp Value'!$B170,'xUS TME'!$B:$B,0)) -> Yen | Q170: =INDEX('xUS TME'!N:N,MATCH('xUS Opp Value'!$B170,'xUS TME'!$B:$B,0)) -> 0
A171: Terna SpA | B171: =INDEX('xUS TME'!B:B,MATCH('xUS Opp Value'!A171,'xUS TME'!A:A,0)) -> IT0003242622 | C171: =INDEX('xUS TME'!C:C,MATCH($B171,'xUS TME'!$B:$B,0)) -> TRN | D171: =INDEX('xUS TME'!D:D,MATCH(B171,'xUS TME'!$B:$B,0)) -> 0P00009DOD | E171: =INDEX('xUS TME'!F:F,MATCH(B171,'xUS TME'!$B:$B,0)) -> Italy | F171: =INDEX('xUS TME'!G:G,MATCH(B171,'xUS TME'!$B:$B,0)) -> Utilities | G171: =IFERROR(INDEX(CRIMs!G:G,MATCH(C171,CRIMs!D:D,0)),0) -> 0 | H171: =IFERROR(INDEX(CRIMs!I:I,MATCH(C171,CRIMs!D:D,0)),0) -> 0 | I171: =INDEX('xUS TME'!E:E,MATCH($B171,'xUS TME'!$B:$B,0)) -> 0.05 | J171: =INDEX('xUS TME'!H:H,MATCH(B171,'xUS TME'!$B:$B,0)) -> 0 | K171: =IFERROR((1/J171)-1,"") | L171: =INDEX('xUS TME'!J:J,MATCH('xUS Opp Value'!B171,'xUS TME'!$B:$B,0)) -> 20.46 | M171: =INDEX('xUS TME'!L:L,MATCH('xUS Opp Value'!$B171,'xUS TME'!$B:$B,0)) -> 2.66 | N171: =INDEX('xUS TME'!K:K,MATCH('xUS Opp Value'!$B171,'xUS TME'!$B:$B,0)) -> 0.15 | O171: =INDEX('xUS TME'!I:I,MATCH('xUS Opp Value'!$B171,'xUS TME'!$B:$B,0)) -> 0 | P171: =INDEX('xUS TME'!M:M,MATCH('xUS Opp Value'!$B171,'xUS TME'!$B:$B,0)) -> Euro | Q171: =INDEX('xUS TME'!N:N,MATCH('xUS Opp Value'!$B171,'xUS TME'!$B:$B,0)) -> 0
A172: SECOM Co Ltd | B172: =INDEX('xUS TME'!B:B,MATCH('xUS Opp Value'!A172,'xUS TME'!A:A,0)) -> JP3421800008 | C172: =INDEX('xUS TME'!C:C,MATCH($B172,'xUS TME'!$B:$B,0)) -> 9735 | D172: =INDEX('xUS TME'!D:D,MATCH(B172,'xUS TME'!$B:$B,0)) -> 0P0000AEXN | E172: =INDEX('xUS TME'!F:F,MATCH(B172,'xUS TME'!$B:$B,0)) -> Japan | F172: =INDEX('xUS TME'!G:G,MATCH(B172,'xUS TME'!$B:$B,0)) -> Industrials | G172: =IFERROR(INDEX(CRIMs!G:G,MATCH(C172,CRIMs!D:D,0)),0) -> 0 | H172: =IFERROR(INDEX(CRIMs!I:I,MATCH(C172,CRIMs!D:D,0)),0) -> 0 | I172: =INDEX('xUS TME'!E:E,MATCH($B172,'xUS TME'!$B:$B,0)) -> 0.05 | J172: =INDEX('xUS TME'!H:H,MATCH(B172,'xUS TME'!$B:$B,0)) -> 0 | K172: =IFERROR((1/J172)-1,"") | L172: =INDEX('xUS TME'!J:J,MATCH('xUS Opp Value'!B172,'xUS TME'!$B:$B,0)) -> 0 | M172: =INDEX('xUS TME'!L:L,MATCH('xUS Opp Value'!$B172,'xUS TME'!$B:$B,0)) -> 1.94 | N172: =INDEX('xUS TME'!K:K,MATCH('xUS Opp Value'!$B172,'xUS TME'!$B:$B,0)) -> 0.1 | O172: =INDEX('xUS TME'!I:I,MATCH('xUS Opp Value'!$B172,'xUS TME'!$B:$B,0)) -> 0 | P172: =INDEX('xUS TME'!M:M,MATCH('xUS Opp Value'!$B172,'xUS TME'!$B:$B,0)) -> Yen | Q172: =INDEX('xUS TME'!N:N,MATCH('xUS Opp Value'!$B172,'xUS TME'!$B:$B,0)) -> 0
A173: Hindalco Industries Ltd | B173: =INDEX('xUS TME'!B:B,MATCH('xUS Opp Value'!A173,'xUS TME'!A:A,0)) -> INE038A01020 | C173: =INDEX('xUS TME'!C:C,MATCH($B173,'xUS TME'!$B:$B,0)) -> HINDALCO | D173: =INDEX('xUS TME'!D:D,MATCH(B173,'xUS TME'!$B:$B,0)) -> 0P0000CLH9 | E173: =INDEX('xUS TME'!F:F,MATCH(B173,'xUS TME'!$B:$B,0)) -> India | F173: =INDEX('xUS TME'!G:G,MATCH(B173,'xUS TME'!$B:$B,0)) -> Materials | G173: =IFERROR(INDEX(CRIMs!G:G,MATCH(C173,CRIMs!D:D,0)),0) -> 0 | H173: =IFERROR(INDEX(CRIMs!I:I,MATCH(C173,CRIMs!D:D,0)),0) -> 0 | I173: =INDEX('xUS TME'!E:E,MATCH($B173,'xUS TME'!$B:$B,0)) -> 0.04 | J173: =INDEX('xUS TME'!H:H,MATCH(B173,'xUS TME'!$B:$B,0)) -> 0 | K173: =IFERROR((1/J173)-1,"") | L173: =INDEX('xUS TME'!J:J,MATCH('xUS Opp Value'!B173,'xUS TME'!$B:$B,0)) -> 6.76 | M173: =INDEX('xUS TME'!L:L,MATCH('xUS Opp Value'!$B173,'xUS TME'!$B:$B,0)) -> 1.64 | N173: =INDEX('xUS TME'!K:K,MATCH('xUS Opp Value'!$B173,'xUS TME'!$B:$B,0)) -> 0.14 | O173: =INDEX('xUS TME'!I:I,MATCH('xUS Opp Value'!$B173,'xUS TME'!$B:$B,0)) -> 0 | P173: =INDEX('xUS TME'!M:M,MATCH('xUS Opp Value'!$B173,'xUS TME'!$B:$B,0)) -> Indian Rupee | Q173: =INDEX('xUS TME'!N:N,MATCH('xUS Opp Value'!$B173,'xUS TME'!$B:$B,0)) -> 0
A174: Osaka Gas Co Ltd | B174: =INDEX('xUS TME'!B:B,MATCH('xUS Opp Value'!A174,'xUS TME'!A:A,0)) -> JP3180400008 | C174: =INDEX('xUS TME'!C:C,MATCH($B174,'xUS TME'!$B:$B,0)) -> 9532 | D174: =INDEX('xUS TME'!D:D,MATCH(B174,'xUS TME'!$B:$B,0)) -> 0P0000AEXF | E174: =INDEX('xUS TME'!F:F,MATCH(B174,'xUS TME'!$B:$B,0)) -> Japan | F174: =INDEX('xUS TME'!G:G,MATCH(B174,'xUS TME'!$B:$B,0)) -> Utilities | G174: =IFERROR(INDEX(CRIMs!G:G,MATCH(C174,CRIMs!D:D,0)),0) -> 0 | H174: =IFERROR(INDEX(CRIMs!I:I,MATCH(C174,CRIMs!D:D,0)),0) -> 0 | I174: =INDEX('xUS TME'!E:E,MATCH($B174,'xUS TME'!$B:$B,0)) -> 0.05 | J174: =INDEX('xUS TME'!H:H,MATCH(B174,'xUS TME'!$B:$B,0)) -> 0 | K174: =IFERROR((1/J174)-1,"") | L174: =INDEX('xUS TME'!J:J,MATCH('xUS Opp Value'!B174,'xUS TME'!$B:$B,0)) -> 0 | M174: =INDEX('xUS TME'!L:L,MATCH('xUS Opp Value'!$B174,'xUS TME'!$B:$B,0)) -> 1.44 | N174: =INDEX('xUS TME'!K:K,MATCH('xUS Opp Value'!$B174,'xUS TME'!$B:$B,0)) -> 0.08 | O174: =INDEX('xUS TME'!I:I,MATCH('xUS Opp Value'!$B174,'xUS TME'!$B:$B,0)) -> 0 | P174: =INDEX('xUS TME'!M:M,MATCH('xUS Opp Value'!$B174,'xUS TME'!$B:$B,0)) -> Yen | Q174: =INDEX('xUS TME'!N:N,MATCH('xUS Opp Value'!$B174,'xUS TME'!$B:$B,0)) -> 0
A175: Mega Financial Holding Co Ltd | B175: =INDEX('xUS TME'!B:B,MATCH('xUS Opp Value'!A175,'xUS TME'!A:A,0)) -> TW0002886009 | C175: =INDEX('xUS TME'!C:C,MATCH($B175,'xUS TME'!$B:$B,0)) -> 2886 | D175: =INDEX('xUS TME'!D:D,MATCH(B175,'xUS TME'!$B:$B,0)) -> 0P0000B8XH | E175: =INDEX('xUS TME'!F:F,MATCH(B175,'xUS TME'!$B:$B,0)) -> Taiwan | F175: =INDEX('xUS TME'!G:G,MATCH(B175,'xUS TME'!$B:$B,0)) -> Financials | G175: =IFERROR(INDEX(CRIMs!G:G,MATCH(C175,CRIMs!D:D,0)),0) -> 0 | H175: =IFERROR(INDEX(CRIMs!I:I,MATCH(C175,CRIMs!D:D,0)),0) -> 0 | I175: =INDEX('xUS TME'!E:E,MATCH($B175,'xUS TME'!$B:$B,0)) -> 0.04 | J175: =INDEX('xUS TME'!H:H,MATCH(B175,'xUS TME'!$B:$B,0)) -> 0 | K175: =IFERROR((1/J175)-1,"") | L175: =INDEX('xUS TME'!J:J,MATCH('xUS Opp Value'!B175,'xUS TME'!$B:$B,0)) -> 13.13 | M175: =INDEX('xUS TME'!L:L,MATCH('xUS Opp Value'!$B175,'xUS TME'!$B:$B,0)) -> 1.51 | N175: =INDEX('xUS TME'!K:K,MATCH('xUS Opp Value'!$B175,'xUS TME'!$B:$B,0)) -> 0.09 | O175: =INDEX('xUS TME'!I:I,MATCH('xUS Opp Value'!$B175,'xUS TME'!$B:$B,0)) -> 0 | P175: =INDEX('xUS TME'!M:M,MATCH('xUS Opp Value'!$B175,'xUS TME'!$B:$B,0)) -> New Taiwan Dollar | Q175: =INDEX('xUS TME'!N:N,MATCH('xUS Opp Value'!$B175,'xUS TME'!$B:$B,0)) -> 0
A176: National Bank of Greece SA | B176: =INDEX('xUS TME'!B:B,MATCH('xUS Opp Value'!A176,'xUS TME'!A:A,0)) -> GRS003003035 | C176: =INDEX('xUS TME'!C:C,MATCH($B176,'xUS TME'!$B:$B,0)) -> ETE | D176: =INDEX('xUS TME'!D:D,MATCH(B176,'xUS TME'!$B:$B,0)) -> 0P0000BKXS | E176: =INDEX('xUS TME'!F:F,MATCH(B176,'xUS TME'!$B:$B,0)) -> Greece | F176: =INDEX('xUS TME'!G:G,MATCH(B176,'xUS TME'!$B:$B,0)) -> Financials | G176: =IFERROR(INDEX(CRIMs!G:G,MATCH(C176,CRIMs!D:D,0)),0) -> 0 | H176: =IFERROR(INDEX(CRIMs!I:I,MATCH(C176,CRIMs!D:D,0)),0) -> 0 | I176: =INDEX('xUS TME'!E:E,MATCH($B176,'xUS TME'!$B:$B,0)) -> 0.04 | J176: =INDEX('xUS TME'!H:H,MATCH(B176,'xUS TME'!$B:$B,0)) -> 0 | K176: =IFERROR((1/J176)-1,"") | L176: =INDEX('xUS TME'!J:J,MATCH('xUS Opp Value'!B176,'xUS TME'!$B:$B,0)) -> 9.65 | M176: =INDEX('xUS TME'!L:L,MATCH('xUS Opp Value'!$B176,'xUS TME'!$B:$B,0)) -> 1.42 | N176: =INDEX('xUS TME'!K:K,MATCH('xUS Opp Value'!$B176,'xUS TME'!$B:$B,0)) -> 0.13 | O176: =INDEX('xUS TME'!I:I,MATCH('xUS Opp Value'!$B176,'xUS TME'!$B:$B,0)) -> None | P176: =INDEX('xUS TME'!M:M,MATCH('xUS Opp Value'!$B176,'xUS TME'!$B:$B,0)) -> Euro | Q176: =INDEX('xUS TME'!N:N,MATCH('xUS Opp Value'!$B176,'xUS TME'!$B:$B,0)) -> Extreme
... A196: Woori Financial Group Inc | B196: =INDEX('xUS TME'!B:B,MATCH('xUS Opp Value'!A196,'xUS TME'!A:A,0)) -> KR7316140003 | C196: =INDEX('xUS TME'!C:C,MATCH($B196,'xUS TME'!$B:$B,0)) -> 316140 | D196: =INDEX('xUS TME'!D:D,MATCH(B196,'xUS TME'!$B:$B,0)) -> 0P0001FU10 | E196: =INDEX('xUS TME'!F:F,MATCH(B196,'xUS TME'!$B:$B,0)) -> South Korea | F196: =INDEX('xUS TME'!G:G,MATCH(B196,'xUS TME'!$B:$B,0)) -> Financials | G196: =IFERROR(INDEX(CRIMs!G:G,MATCH(C196,CRIMs!D:D,0)),0) -> 0.5 | H196: =IFERROR(INDEX(CRIMs!I:I,MATCH(C196,CRIMs!D:D,0)),0) -> 0.59926243 | I196: =INDEX('xUS TME'!E:E,MATCH($B196,'xUS TME'!$B:$B,0)) -> 0.04 | J196: =INDEX('xUS TME'!H:H,MATCH(B196,'xUS TME'!$B:$B,0)) -> 0 | K196: =IFERROR((1/J196)-1,"") | L196: =INDEX('xUS TME'!J:J,MATCH('xUS Opp Value'!B196,'xUS TME'!$B:$B,0)) -> 3.37 | M196: =INDEX('xUS TME'!L:L,MATCH('xUS Opp Value'!$B196,'xUS TME'!$B:$B,0)) -> 0.77 | N196: =INDEX('xUS TME'!K:K,MATCH('xUS Opp Value'!$B196,'xUS TME'!$B:$B,0)) -> 0 | O196: =INDEX('xUS TME'!I:I,MATCH('xUS Opp Value'!$B196,'xUS TME'!$B:$B,0)) -> None | P196: =INDEX('xUS TME'!M:M,MATCH('xUS Opp Value'!$B196,'xUS TME'!$B:$B,0)) -> Won | Q196: =INDEX('xUS TME'!N:N,MATCH('xUS Opp Value'!$B196,'xUS TME'!$B:$B,0)) -> Medium
A197: Olympus Corp | B197: =INDEX('xUS TME'!B:B,MATCH('xUS Opp Value'!A197,'xUS TME'!A:A,0)) -> JP3201200007 | C197: 7733 | D197: =INDEX('xUS TME'!D:D,MATCH(B197,'xUS TME'!$B:$B,0)) -> 0P0000AEXE | E197: =INDEX('xUS TME'!F:F,MATCH(B197,'xUS TME'!$B:$B,0)) -> Japan | F197: =INDEX('xUS TME'!G:G,MATCH(B197,'xUS TME'!$B:$B,0)) -> Health Care | G197: =IFERROR(INDEX(CRIMs!G:G,MATCH(C197,CRIMs!D:D,0)),0) -> 0.5 | H197: =IFERROR(INDEX(CRIMs!I:I,MATCH(C197,CRIMs!D:D,0)),0) -> 0.38256494 | I197: =INDEX('xUS TME'!E:E,MATCH($B197,'xUS TME'!$B:$B,0)) -> 0.03 | J197: =INDEX('xUS TME'!H:H,MATCH(B197,'xUS TME'!$B:$B,0)) -> 0 | K197: =IFERROR((1/J197)-1,"") | L197: =INDEX('xUS TME'!J:J,MATCH('xUS Opp Value'!B197,'xUS TME'!$B:$B,0)) -> 20.99 | M197: =INDEX('xUS TME'!L:L,MATCH('xUS Opp Value'!$B197,'xUS TME'!$B:$B,0)) -> 2.23 | N197: =INDEX('xUS TME'!K:K,MATCH('xUS Opp Value'!$B197,'xUS TME'!$B:$B,0)) -> 0.16 | O197: =INDEX('xUS TME'!I:I,MATCH('xUS Opp Value'!$B197,'xUS TME'!$B:$B,0)) -> Narrow | P197: =INDEX('xUS TME'!M:M,MATCH('xUS Opp Value'!$B197,'xUS TME'!$B:$B,0)) -> Yen | Q197: =INDEX('xUS TME'!N:N,MATCH('xUS Opp Value'!$B197,'xUS TME'!$B:$B,0)) -> High
A198: Roche Holding AG Bearer Shares | B198: =INDEX('xUS TME'!B:B,MATCH('xUS Opp Value'!A198,'xUS TME'!A:A,0)) -> CH0012032113 | C198: =INDEX('xUS TME'!C:C,MATCH($B198,'xUS TME'!$B:$B,0)) -> RO | D198: =INDEX('xUS TME'!D:D,MATCH(B198,'xUS TME'!$B:$B,0)) -> 0P0000A6PP | E198: =INDEX('xUS TME'!F:F,MATCH(B198,'xUS TME'!$B:$B,0)) -> Switzerland | F198: =INDEX('xUS TME'!G:G,MATCH(B198,'xUS TME'!$B:$B,0)) -> Health Care | G198: =IFERROR(INDEX(CRIMs!G:G,MATCH(C198,CRIMs!D:D,0)),0) -> 0 | H198: =IFERROR(INDEX(CRIMs!I:I,MATCH(C198,CRIMs!D:D,0)),0) -> 0 | I198: =INDEX('xUS TME'!E:E,MATCH($B198,'xUS TME'!$B:$B,0)) -> 0.04 | J198: =INDEX('xUS TME'!H:H,MATCH(B198,'xUS TME'!$B:$B,0)) -> 0 | K198: =IFERROR((1/J198)-1,"") | L198: =INDEX('xUS TME'!J:J,MATCH('xUS Opp Value'!B198,'xUS TME'!$B:$B,0)) -> 15.99 | M198: =INDEX('xUS TME'!L:L,MATCH('xUS Opp Value'!$B198,'xUS TME'!$B:$B,0)) -> 7.74 | N198: =INDEX('xUS TME'!K:K,MATCH('xUS Opp Value'!$B198,'xUS TME'!$B:$B,0)) -> 0.44 | O198: =INDEX('xUS TME'!I:I,MATCH('xUS Opp Value'!$B198,'xUS TME'!$B:$B,0)) -> Wide | P198: =INDEX('xUS TME'!M:M,MATCH('xUS Opp Value'!$B198,'xUS TME'!$B:$B,0)) -> Swiss Franc | Q198: =INDEX('xUS TME'!N:N,MATCH('xUS Opp Value'!$B198,'xUS TME'!$B:$B,0)) -> Low
A199: Advanced Info Service PCL | B199: =INDEX('xUS TME'!B:B,MATCH('xUS Opp Value'!A199,'xUS TME'!A:A,0)) -> TH0268010Z03 | C199: =INDEX('xUS TME'!C:C,MATCH($B199,'xUS TME'!$B:$B,0)) -> ADVANC | D199: =INDEX('xUS TME'!D:D,MATCH(B199,'xUS TME'!$B:$B,0)) -> 0P0000CG0H | E199: =INDEX('xUS TME'!F:F,MATCH(B199,'xUS TME'!$B:$B,0)) -> Thailand | F199: =INDEX('xUS TME'!G:G,MATCH(B199,'xUS TME'!$B:$B,0)) -> Communication Services | G199: =IFERROR(INDEX(CRIMs!G:G,MATCH(C199,CRIMs!D:D,0)),0) -> 0 | H199: =IFERROR(INDEX(CRIMs!I:I,MATCH(C199,CRIMs!D:D,0)),0) -> 0 | I199: =INDEX('xUS TME'!E:E,MATCH($B199,'xUS TME'!$B:$B,0)) -> 0.04 | J199: =INDEX('xUS TME'!H:H,MATCH(B199,'xUS TME'!$B:$B,0)) -> 0 | K199: =IFERROR((1/J199)-1,"") | L199: =INDEX('xUS TME'!J:J,MATCH('xUS Opp Value'!B199,'xUS TME'!$B:$B,0)) -> 20.96 | M199: =INDEX('xUS TME'!L:L,MATCH('xUS Opp Value'!$B199,'xUS TME'!$B:$B,0)) -> 10.07 | N199: =INDEX('xUS TME'!K:K,MATCH('xUS Opp Value'!$B199,'xUS TME'!$B:$B,0)) -> 0.49 | O199: =INDEX('xUS TME'!I:I,MATCH('xUS Opp Value'!$B199,'xUS TME'!$B:$B,0)) -> 0 | P199: =INDEX('xUS TME'!M:M,MATCH('xUS Opp Value'!$B199,'xUS TME'!$B:$B,0)) -> Baht | Q199: =INDEX('xUS TME'!N:N,MATCH('xUS Opp Value'!$B199,'xUS TME'!$B:$B,0)) -> 0
A200: Eternal Ltd | B200: =INDEX('xUS TME'!B:B,MATCH('xUS Opp Value'!A200,'xUS TME'!A:A,0)) -> INE758T01015 | C200: =INDEX('xUS TME'!C:C,MATCH($B200,'xUS TME'!$B:$B,0)) -> 543320 | D200: =INDEX('xUS TME'!D:D,MATCH(B200,'xUS TME'!$B:$B,0)) -> 0P0001MZRH | E200: =INDEX('xUS TME'!F:F,MATCH(B200,'xUS TME'!$B:$B,0)) -> India | F200: =INDEX('xUS TME'!G:G,MATCH(B200,'xUS TME'!$B:$B,0)) -> Consumer Discretionary | G200: =IFERROR(INDEX(CRIMs!G:G,MATCH(C200,CRIMs!D:D,0)),0) -> 0 | H200: =IFERROR(INDEX(CRIMs!I:I,MATCH(C200,CRIMs!D:D,0)),0) -> 0 | I200: =INDEX('xUS TME'!E:E,MATCH($B200,'xUS TME'!$B:$B,0)) -> 0.03 | J200: =INDEX('xUS TME'!H:H,MATCH(B200,'xUS TME'!$B:$B,0)) -> 0 | K200: =IFERROR((1/J200)-1,"") | L200: =INDEX('xUS TME'!J:J,MATCH('xUS Opp Value'!B200,'xUS TME'!$B:$B,0)) -> 0 | M200: =INDEX('xUS TME'!L:L,MATCH('xUS Opp Value'!$B200,'xUS TME'!$B:$B,0)) -> 7.09 | N200: =INDEX('xUS TME'!K:K,MATCH('xUS Opp Value'!$B200,'xUS TME'!$B:$B,0)) -> 0.02 | O200: =INDEX('xUS TME'!I:I,MATCH('xUS Opp Value'!$B200,'xUS TME'!$B:$B,0)) -> 0 | P200: =INDEX('xUS TME'!M:M,MATCH('xUS Opp Value'!$B200,'xUS TME'!$B:$B,0)) -> Indian Rupee | Q200: =INDEX('xUS TME'!N:N,MATCH('xUS Opp Value'!$B200,'xUS TME'!$B:$B,0)) -> 0
A201: Nan Ya Plastics Corp | B201: =INDEX('xUS TME'!B:B,MATCH('xUS Opp Value'!A201,'xUS TME'!A:A,0)) -> TW0001303006 | C201: =INDEX('xUS TME'!C:C,MATCH($B201,'xUS TME'!$B:$B,0)) -> 1303 | D201: =INDEX('xUS TME'!D:D,MATCH(B201,'xUS TME'!$B:$B,0)) -> 0P0000BQ45 | E201: =INDEX('xUS TME'!F:F,MATCH(B201,'xUS TME'!$B:$B,0)) -> Taiwan | F201: =INDEX('xUS TME'!G:G,MATCH(B201,'xUS TME'!$B:$B,0)) -> Materials | G201: =IFERROR(INDEX(CRIMs!G:G,MATCH(C201,CRIMs!D:D,0)),0) -> 0 | H201: =IFERROR(INDEX(CRIMs!I:I,MATCH(C201,CRIMs!D:D,0)),0) -> 0 | I201: =INDEX('xUS TME'!E:E,MATCH($B201,'xUS TME'!$B:$B,0)) -> 0.04 | J201: =INDEX('xUS TME'!H:H,MATCH(B201,'xUS TME'!$B:$B,0)) -> 0 | K201: =IFERROR((1/J201)-1,"") | L201: =INDEX('xUS TME'!J:J,MATCH('xUS Opp Value'!B201,'xUS TME'!$B:$B,0)) -> 0 | M201: =INDEX('xUS TME'!L:L,MATCH('xUS Opp Value'!$B201,'xUS TME'!$B:$B,0)) -> 1.82 | N201: =INDEX('xUS TME'!K:K,MATCH('xUS Opp Value'!$B201,'xUS TME'!$B:$B,0)) -> 0.01 | O201: =INDEX('xUS TME'!I:I,MATCH('xUS Opp Value'!$B201,'xUS TME'!$B:$B,0)) -> 0 | P201: =INDEX('xUS TME'!M:M,MATCH('xUS Opp Value'!$B201,'xUS TME'!$B:$B,0)) -> New Taiwan Dollar | Q201: =INDEX('xUS TME'!N:N,MATCH('xUS Opp Value'!$B201,'xUS TME'!$B:$B,0)) -> 0
A202: Asahi Kasei Corp | B202: =INDEX('xUS TME'!B:B,MATCH('xUS Opp Value'!A202,'xUS TME'!A:A,0)) -> JP3111200006 | C202: =INDEX('xUS TME'!C:C,MATCH($B202,'xUS TME'!$B:$B,0)) -> 3407 | D202: =INDEX('xUS TME'!D:D,MATCH(B202,'xUS TME'!$B:$B,0)) -> 0P0000AETL | E202: =INDEX('xUS TME'!F:F,MATCH(B202,'xUS TME'!$B:$B,0)) -> Japan | F202: =INDEX('xUS TME'!G:G,MATCH(B202,'xUS TME'!$B:$B,0)) -> Materials | G202: =IFERROR(INDEX(CRIMs!G:G,MATCH(C202,CRIMs!D:D,0)),0) -> 0 | H202: =IFERROR(INDEX(CRIMs!I:I,MATCH(C202,CRIMs!D:D,0)),0) -> 0 | I202: =INDEX('xUS TME'!E:E,MATCH($B202,'xUS TME'!$B:$B,0)) -> 0.04 | J202: =INDEX('xUS TME'!H:H,MATCH(B202,'xUS TME'!$B:$B,0)) -> 0 | K202: =IFERROR((1/J202)-1,"") | L202: =INDEX('xUS TME'!J:J,MATCH('xUS Opp Value'!B202,'xUS TME'!$B:$B,0)) -> 0 | M202: =INDEX('xUS TME'!L:L,MATCH('xUS Opp Value'!$B202,'xUS TME'!$B:$B,0)) -> 1.11 | N202: =INDEX('xUS TME'!K:K,MATCH('xUS Opp Value'!$B202,'xUS TME'!$B:$B,0)) -> 0.08 | O202: =INDEX('xUS TME'!I:I,MATCH('xUS Opp Value'!$B202,'xUS TME'!$B:$B,0)) -> 0 | P202: =INDEX('xUS TME'!M:M,MATCH('xUS Opp Value'!$B202,'xUS TME'!$B:$B,0)) -> Yen | Q202: =INDEX('xUS TME'!N:N,MATCH('xUS Opp Value'!$B202,'xUS TME'!$B:$B,0)) -> 0
A203: HD Korea Shipbuilding & Offshore Engineering | B203: =INDEX('xUS TME'!B:B,MATCH('xUS Opp Value'!A203,'xUS TME'!A:A,0)) -> KR7009540006 | C203: =INDEX('xUS TME'!C:C,MATCH($B203,'xUS TME'!$B:$B,0)) -> 009540 | D203: =INDEX('xUS TME'!D:D,MATCH(B203,'xUS TME'!$B:$B,0)) -> 0P0000APQT | E203: =INDEX('xUS TME'!F:F,MATCH(B203,'xUS TME'!$B:$B,0)) -> South Korea | F203: =INDEX('xUS TME'!G:G,MATCH(B203,'xUS TME'!$B:$B,0)) -> Industrials | G203: =IFERROR(INDEX(CRIMs!G:G,MATCH(C203,CRIMs!D:D,0)),0) -> 0 | H203: =IFERROR(INDEX(CRIMs!I:I,MATCH(C203,CRIMs!D:D,0)),0) -> 0 | I203: =INDEX('xUS TME'!E:E,MATCH($B203,'xUS TME'!$B:$B,0)) -> 0.03 | J203: =INDEX('xUS TME'!H:H,MATCH(B203,'xUS TME'!$B:$B,0)) -> 0 | K203: =IFERROR((1/J203)-1,"") | L203: =INDEX('xUS TME'!J:J,MATCH('xUS Opp Value'!B203,'xUS TME'!$B:$B,0)) -> 11.31 | M203: =INDEX('xUS TME'!L:L,MATCH('xUS Opp Value'!$B203,'xUS TME'!$B:$B,0)) -> 2.1 | N203: =INDEX('xUS TME'!K:K,MATCH('xUS Opp Value'!$B203,'xUS TME'!$B:$B,0)) -> 0.24 | O203: =INDEX('xUS TME'!I:I,MATCH('xUS Opp Value'!$B203,'xUS TME'!$B:$B,0)) -> 0 | P203: =INDEX('xUS TME'!M:M,MATCH('xUS Opp Value'!$B203,'xUS TME'!$B:$B,0)) -> Won | Q203: =INDEX('xUS TME'!N:N,MATCH('xUS Opp Value'!$B203,'xUS TME'!$B:$B,0)) -> 0
A204: Absa Group Ltd | B204: =INDEX('xUS TME'!B:B,MATCH('xUS Opp Value'!A204,'xUS TME'!A:A,0)) -> ZAE000255915 | C204: =INDEX('xUS TME'!C:C,MATCH($B204,'xUS TME'!$B:$B,0)) -> ABG | D204: =INDEX('xUS TME'!D:D,MATCH(B204,'xUS TME'!$B:$B,0)) -> 0P0000DLRU | E204: =INDEX('xUS TME'!F:F,MATCH(B204,'xUS TME'!$B:$B,0)) -> South Africa | F204: =INDEX('xUS TME'!G:G,MATCH(B204,'xUS TME'!$B:$B,0)) -> Financials | G204: =IFERROR(INDEX(CRIMs!G:G,MATCH(C204,CRIMs!D:D,0)),0) -> 0 | H204: =IFERROR(INDEX(CRIMs!I:I,MATCH(C204,CRIMs!D:D,0)),0) -> 0 | I204: =INDEX('xUS TME'!E:E,MATCH($B204,'xUS TME'!$B:$B,0)) -> 0.04 | J204: =INDEX('xUS TME'!H:H,MATCH(B204,'xUS TME'!$B:$B,0)) -> 0 | K204: =IFERROR((1/J204)-1,"") | L204: =INDEX('xUS TME'!J:J,MATCH('xUS Opp Value'!B204,'xUS TME'!$B:$B,0)) -> 0 | M204: =INDEX('xUS TME'!L:L,MATCH('xUS Opp Value'!$B204,'xUS TME'!$B:$B,0)) -> 1.2 | N204: =INDEX('xUS TME'!K:K,MATCH('xUS Opp Value'!$B204,'xUS TME'!$B:$B,0)) -> 0.15 | O204: =INDEX('xUS TME'!I:I,MATCH('xUS Opp Value'!$B204,'xUS TME'!$B:$B,0)) -> 0 | P204: =INDEX('xUS TME'!M:M,MATCH('xUS Opp Value'!$B204,'xUS TME'!$B:$B,0)) -> Rand | Q204: =INDEX('xUS TME'!N:N,MATCH('xUS Opp Value'!$B204,'xUS TME'!$B:$B,0)) -> 0
A205: Wiwynn Corp Ordinary Shares | B205: =INDEX('xUS TME'!B:B,MATCH('xUS Opp Value'!A205,'xUS TME'!A:A,0)) -> TW0006669005 | C205: =INDEX('xUS TME'!C:C,MATCH($B205,'xUS TME'!$B:$B,0)) -> 6669 | D205: =INDEX('xUS TME'!D:D,MATCH(B205,'xUS TME'!$B:$B,0)) -> 0P0001C5O1 | E205: =INDEX('xUS TME'!F:F,MATCH(B205,'xUS TME'!$B:$B,0)) -> Taiwan | F205: =INDEX('xUS TME'!G:G,MATCH(B205,'xUS TME'!$B:$B,0)) -> Information Technology | G205: =IFERROR(INDEX(CRIMs!G:G,MATCH(C205,CRIMs!D:D,0)),0) -> 0 | H205: =IFERROR(INDEX(CRIMs!I:I,MATCH(C205,CRIMs!D:D,0)),0) -> 0 | I205: =INDEX('xUS TME'!E:E,MATCH($B205,'xUS TME'!$B:$B,0)) -> 0.04 | J205: =INDEX('xUS TME'!H:H,MATCH(B205,'xUS TME'!$B:$B,0)) -> 0 | K205: =IFERROR((1/J205)-1,"") | L205: =INDEX('xUS TME'!J:J,MATCH('xUS Opp Value'!B205,'xUS TME'!$B:$B,0)) -> 20.69 | M205: =INDEX('xUS TME'!L:L,MATCH('xUS Opp Value'!$B205,'xUS TME'!$B:$B,0)) -> 5.41 | N205: =INDEX('xUS TME'!K:K,MATCH('xUS Opp Value'!$B205,'xUS TME'!$B:$B,0)) -> 0.5 | O205: =INDEX('xUS TME'!I:I,MATCH('xUS Opp Value'!$B205,'xUS TME'!$B:$B,0)) -> 0 | P205: =INDEX('xUS TME'!M:M,MATCH('xUS Opp Value'!$B205,'xUS TME'!$B:$B,0)) -> New Taiwan Dollar | Q205: =INDEX('xUS TME'!N:N,MATCH('xUS Opp Value'!$B205,'xUS TME'!$B:$B,0)) -> 0
A206: Kakao Corp | B206: =INDEX('xUS TME'!B:B,MATCH('xUS Opp Value'!A206,'xUS TME'!A:A,0)) -> KR7035720002 | C206: =INDEX('xUS TME'!C:C,MATCH($B206,'xUS TME'!$B:$B,0)) -> 035720 | D206: =INDEX('xUS TME'!D:D,MATCH(B206,'xUS TME'!$B:$B,0)) -> 0P0000AN5S | E206: =INDEX('xUS TME'!F:F,MATCH(B206,'xUS TME'!$B:$B,0)) -> South Korea | F206: =INDEX('xUS TME'!G:G,MATCH(B206,'xUS TME'!$B:$B,0)) -> Communication Services | G206: =IFERROR(INDEX(CRIMs!G:G,MATCH(C206,CRIMs!D:D,0)),0) -> 0 | H206: =IFERROR(INDEX(CRIMs!I:I,MATCH(C206,CRIMs!D:D,0)),0) -> 0 | I206: =INDEX('xUS TME'!E:E,MATCH($B206,'xUS TME'!$B:$B,0)) -> 0.03 | J206: =INDEX('xUS TME'!H:H,MATCH(B206,'xUS TME'!$B:$B,0)) -> 0 | K206: =IFERROR((1/J206)-1,"") | L206: =INDEX('xUS TME'!J:J,MATCH('xUS Opp Value'!B206,'xUS TME'!$B:$B,0)) -> 36.44 | M206: =INDEX('xUS TME'!L:L,MATCH('xUS Opp Value'!$B206,'xUS TME'!$B:$B,0)) -> 1.89 | N206: =INDEX('xUS TME'!K:K,MATCH('xUS Opp Value'!$B206,'xUS TME'!$B:$B,0)) -> 0.05 | O206: =INDEX('xUS TME'!I:I,MATCH('xUS Opp Value'!$B206,'xUS TME'!$B:$B,0)) -> None | P206: =INDEX('xUS TME'!M:M,MATCH('xUS Opp Value'!$B206,'xUS TME'!$B:$B,0)) -> Won | Q206: =INDEX('xUS TME'!N:N,MATCH('xUS Opp Value'!$B206,'xUS TME'!$B:$B,0)) -> Very High
A207: Abu Dhabi Commercial Bank | B207: =INDEX('xUS TME'!B:B,MATCH('xUS Opp Value'!A207,'xUS TME'!A:A,0)) -> AEA000201011 | C207: =INDEX('xUS TME'!C:C,MATCH($B207,'xUS TME'!$B:$B,0)) -> ADCB | D207: =INDEX('xUS TME'!D:D,MATCH(B207,'xUS TME'!$B:$B,0)) -> 0P0000JM1M | E207: =INDEX('xUS TME'!F:F,MATCH(B207,'xUS TME'!$B:$B,0)) -> United Arab Emirates | F207: =INDEX('xUS TME'!G:G,MATCH(B207,'xUS TME'!$B:$B,0)) -> Financials | G207: =IFERROR(INDEX(CRIMs!G:G,MATCH(C207,CRIMs!D:D,0)),0) -> 0 | H207: =IFERROR(INDEX(CRIMs!I:I,MATCH(C207,CRIMs!D:D,0)),0) -> 0 | I207: =INDEX('xUS TME'!E:E,MATCH($B207,'xUS TME'!$B:$B,0)) -> 0.03 | J207: =INDEX('xUS TME'!H:H,MATCH(B207,'xUS TME'!$B:$B,0)) -> 0 | K207: =IFERROR((1/J207)-1,"") | L207: =INDEX('xUS TME'!J:J,MATCH('xUS Opp Value'!B207,'xUS TME'!$B:$B,0)) -> 9.52 | M207: =INDEX('xUS TME'!L:L,MATCH('xUS Opp Value'!$B207,'xUS TME'!$B:$B,0)) -> 1.32 | N207: =INDEX('xUS TME'!K:K,MATCH('xUS Opp Value'!$B207,'xUS TME'!$B:$B,0)) -> 0.16 | O207: =INDEX('xUS TME'!I:I,MATCH('xUS Opp Value'!$B207,'xUS TME'!$B:$B,0)) -> 0 | P207: =INDEX('xUS TME'!M:M,MATCH('xUS Opp Value'!$B207,'xUS TME'!$B:$B,0)) -> UAE Dirham | Q207: =INDEX('xUS TME'!N:N,MATCH('xUS Opp Value'!$B207,'xUS TME'!$B:$B,0)) -> 0
A208: Sibanye Stillwater Ltd Ordinary Shares | B208: =INDEX('xUS TME'!B:B,MATCH('xUS Opp Value'!A208,'xUS TME'!A:A,0)) -> ZAE000259701 | C208: =INDEX('xUS TME'!C:C,MATCH($B208,'xUS TME'!$B:$B,0)) -> SSW | D208: =INDEX('xUS TME'!D:D,MATCH(B208,'xUS TME'!$B:$B,0)) -> 0P0001JB2M | E208: =INDEX('xUS TME'!F:F,MATCH(B208,'xUS TME'!$B:$B,0)) -> South Africa | F208: =INDEX('xUS TME'!G:G,MATCH(B208,'xUS TME'!$B:$B,0)) -> Materials | G208: =IFERROR(INDEX(CRIMs!G:G,MATCH(C208,CRIMs!D:D,0)),0) -> 0 | H208: =IFERROR(INDEX(CRIMs!I:I,MATCH(C208,CRIMs!D:D,0)),0) -> 0 | I208: =INDEX('xUS TME'!E:E,MATCH($B208,'xUS TME'!$B:$B,0)) -> 0.03 | J208: =INDEX('xUS TME'!H:H,MATCH(B208,'xUS TME'!$B:$B,0)) -> 0 | K208: =IFERROR((1/J208)-1,"") | L208: =INDEX('xUS TME'!J:J,MATCH('xUS Opp Value'!B208,'xUS TME'!$B:$B,0)) -> 4.49 | M208: =INDEX('xUS TME'!L:L,MATCH('xUS Opp Value'!$B208,'xUS TME'!$B:$B,0)) -> 3.81 | N208: =INDEX('xUS TME'!K:K,MATCH('xUS Opp Value'!$B208,'xUS TME'!$B:$B,0)) -> 0 | O208: =INDEX('xUS TME'!I:I,MATCH('xUS Opp Value'!$B208,'xUS TME'!$B:$B,0)) -> 0 | P208: =INDEX('xUS TME'!M:M,MATCH('xUS Opp Value'!$B208,'xUS TME'!$B:$B,0)) -> Rand | Q208: =INDEX('xUS TME'!N:N,MATCH('xUS Opp Value'!$B208,'xUS TME'!$B:$B,0)) -> 0
A209: Samsung Life Insurance Co Ltd | B209: =INDEX('xUS TME'!B:B,MATCH('xUS Opp Value'!A209,'xUS TME'!A:A,0)) -> KR7032830002 | C209: =INDEX('xUS TME'!C:C,MATCH($B209,'xUS TME'!$B:$B,0)) -> 32830 | D209: =INDEX('xUS TME'!D:D,MATCH(B209,'xUS TME'!$B:$B,0)) -> 0P0000O50Q | E209: =INDEX('xUS TME'!F:F,MATCH(B209,'xUS TME'!$B:$B,0)) -> South Korea | F209: =INDEX('xUS TME'!G:G,MATCH(B209,'xUS TME'!$B:$B,0)) -> Financials | G209: =IFERROR(INDEX(CRIMs!G:G,MATCH(C209,CRIMs!D:D,0)),0) -> 0 | H209: =IFERROR(INDEX(CRIMs!I:I,MATCH(C209,CRIMs!D:D,0)),0) -> 0 | I209: =INDEX('xUS TME'!E:E,MATCH($B209,'xUS TME'!$B:$B,0)) -> 0.04 | J209: =INDEX('xUS TME'!H:H,MATCH(B209,'xUS TME'!$B:$B,0)) -> 0 | K209: =IFERROR((1/J209)-1,"") | L209: =INDEX('xUS TME'!J:J,MATCH('xUS Opp Value'!B209,'xUS TME'!$B:$B,0)) -> 9.53 | M209: =INDEX('xUS TME'!L:L,MATCH('xUS Opp Value'!$B209,'xUS TME'!$B:$B,0)) -> 0.67 | N209: =INDEX('xUS TME'!K:K,MATCH('xUS Opp Value'!$B209,'xUS TME'!$B:$B,0)) -> 0.06 | O209: =INDEX('xUS TME'!I:I,MATCH('xUS Opp Value'!$B209,'xUS TME'!$B:$B,0)) -> None | P209: =INDEX('xUS TME'!M:M,MATCH('xUS Opp Value'!$B209,'xUS TME'!$B:$B,0)) -> Won | Q209: =INDEX('xUS TME'!N:N,MATCH('xUS Opp Value'!$B209,'xUS TME'!$B:$B,0)) -> Medium
... A532: Krafton Inc | B532: =INDEX('xUS TME'!B:B,MATCH('xUS Opp Value'!A532,'xUS TME'!A:A,0)) -> KR7259960003 | C532: =INDEX('xUS TME'!C:C,MATCH($B532,'xUS TME'!$B:$B,0)) -> 259960 | D532: =INDEX('xUS TME'!D:D,MATCH(B532,'xUS TME'!$B:$B,0)) -> 0P0001N2HR | E532: =INDEX('xUS TME'!F:F,MATCH(B532,'xUS TME'!$B:$B,0)) -> South Korea | F532: =INDEX('xUS TME'!G:G,MATCH(B532,'xUS TME'!$B:$B,0)) -> Communication Services | G532: =IFERROR(INDEX(CRIMs!G:G,MATCH(C532,CRIMs!D:D,0)),0) -> 0 | H532: =IFERROR(INDEX(CRIMs!I:I,MATCH(C532,CRIMs!D:D,0)),0) -> 0 | I532: =INDEX('xUS TME'!E:E,MATCH($B532,'xUS TME'!$B:$B,0)) -> 0.02 | J532: =INDEX('xUS TME'!H:H,MATCH(B532,'xUS TME'!$B:$B,0)) -> 0 | K532: =IFERROR((1/J532)-1,"") | L532: =INDEX('xUS TME'!J:J,MATCH('xUS Opp Value'!B532,'xUS TME'!$B:$B,0)) -> 10.99 | M532: =INDEX('xUS TME'!L:L,MATCH('xUS Opp Value'!$B532,'xUS TME'!$B:$B,0)) -> 1.54 | N532: =INDEX('xUS TME'!K:K,MATCH('xUS Opp Value'!$B532,'xUS TME'!$B:$B,0)) -> 0.11 | O532: =INDEX('xUS TME'!I:I,MATCH('xUS Opp Value'!$B532,'xUS TME'!$B:$B,0)) -> 0 | P532: =INDEX('xUS TME'!M:M,MATCH('xUS Opp Value'!$B532,'xUS TME'!$B:$B,0)) -> Won | Q532: =INDEX('xUS TME'!N:N,MATCH('xUS Opp Value'!$B532,'xUS TME'!$B:$B,0)) -> 0
A533: ELM Co | B533: =INDEX('xUS TME'!B:B,MATCH('xUS Opp Value'!A533,'xUS TME'!A:A,0)) -> SA15GG53GHH3 | C533: 7203H | D533: =INDEX('xUS TME'!D:D,MATCH(B533,'xUS TME'!$B:$B,0)) -> 0P0001OJV0 | E533: =INDEX('xUS TME'!F:F,MATCH(B533,'xUS TME'!$B:$B,0)) -> Saudi Arabia | F533: =INDEX('xUS TME'!G:G,MATCH(B533,'xUS TME'!$B:$B,0)) -> Information Technology | G533: =IFERROR(INDEX(CRIMs!G:G,MATCH(C533,CRIMs!D:D,0)),0) -> 0 | H533: =IFERROR(INDEX(CRIMs!I:I,MATCH(C533,CRIMs!D:D,0)),0) -> 0 | I533: =INDEX('xUS TME'!E:E,MATCH($B533,'xUS TME'!$B:$B,0)) -> 0.01 | J533: =INDEX('xUS TME'!H:H,MATCH(B533,'xUS TME'!$B:$B,0)) -> 0 | K533: =IFERROR((1/J533)-1,"") | L533: =INDEX('xUS TME'!J:J,MATCH('xUS Opp Value'!B533,'xUS TME'!$B:$B,0)) -> 0 | M533: =INDEX('xUS TME'!L:L,MATCH('xUS Opp Value'!$B533,'xUS TME'!$B:$B,0)) -> 11.6 | N533: =INDEX('xUS TME'!K:K,MATCH('xUS Opp Value'!$B533,'xUS TME'!$B:$B,0)) -> 0.49 | O533: =INDEX('xUS TME'!I:I,MATCH('xUS Opp Value'!$B533,'xUS TME'!$B:$B,0)) -> 0 | P533: =INDEX('xUS TME'!M:M,MATCH('xUS Opp Value'!$B533,'xUS TME'!$B:$B,0)) -> Saudi Riyal | Q533: =INDEX('xUS TME'!N:N,MATCH('xUS Opp Value'!$B533,'xUS TME'!$B:$B,0)) -> 0
A534: Fastighets AB Balder Class B | B534: =INDEX('xUS TME'!B:B,MATCH('xUS Opp Value'!A534,'xUS TME'!A:A,0)) -> SE0017832488 | C534: =INDEX('xUS TME'!C:C,MATCH($B534,'xUS TME'!$B:$B,0)) -> BALD B | D534: =INDEX('xUS TME'!D:D,MATCH(B534,'xUS TME'!$B:$B,0)) -> 0P0000A6JC | E534: =INDEX('xUS TME'!F:F,MATCH(B534,'xUS TME'!$B:$B,0)) -> Sweden | F534: =INDEX('xUS TME'!G:G,MATCH(B534,'xUS TME'!$B:$B,0)) -> Real Estate | G534: =IFERROR(INDEX(CRIMs!G:G,MATCH(C534,CRIMs!D:D,0)),0) -> 0 | H534: =IFERROR(INDEX(CRIMs!I:I,MATCH(C534,CRIMs!D:D,0)),0) -> 0 | I534: =INDEX('xUS TME'!E:E,MATCH($B534,'xUS TME'!$B:$B,0)) -> 0.01 | J534: =INDEX('xUS TME'!H:H,MATCH(B534,'xUS TME'!$B:$B,0)) -> 0 | K534: =IFERROR((1/J534)-1,"") | L534: =INDEX('xUS TME'!J:J,MATCH('xUS Opp Value'!B534,'xUS TME'!$B:$B,0)) -> 0 | M534: =INDEX('xUS TME'!L:L,MATCH('xUS Opp Value'!$B534,'xUS TME'!$B:$B,0)) -> 0.74 | N534: =INDEX('xUS TME'!K:K,MATCH('xUS Opp Value'!$B534,'xUS TME'!$B:$B,0)) -> 0.09 | O534: =INDEX('xUS TME'!I:I,MATCH('xUS Opp Value'!$B534,'xUS TME'!$B:$B,0)) -> 0 | P534: =INDEX('xUS TME'!M:M,MATCH('xUS Opp Value'!$B534,'xUS TME'!$B:$B,0)) -> Swedish Krona | Q534: =INDEX('xUS TME'!N:N,MATCH('xUS Opp Value'!$B534,'xUS TME'!$B:$B,0)) -> 0
A535: Zensho Holdings Co Ltd | B535: =INDEX('xUS TME'!B:B,MATCH('xUS Opp Value'!A535,'xUS TME'!A:A,0)) -> JP3429300001 | C535: =INDEX('xUS TME'!C:C,MATCH($B535,'xUS TME'!$B:$B,0)) -> 7550 | D535: =INDEX('xUS TME'!D:D,MATCH(B535,'xUS TME'!$B:$B,0)) -> 0P0000EAH8 | E535: =INDEX('xUS TME'!F:F,MATCH(B535,'xUS TME'!$B:$B,0)) -> Japan | F535: =INDEX('xUS TME'!G:G,MATCH(B535,'xUS TME'!$B:$B,0)) -> Consumer Discretionary | G535: =IFERROR(INDEX(CRIMs!G:G,MATCH(C535,CRIMs!D:D,0)),0) -> 0 | H535: =IFERROR(INDEX(CRIMs!I:I,MATCH(C535,CRIMs!D:D,0)),0) -> 0 | I535: =INDEX('xUS TME'!E:E,MATCH($B535,'xUS TME'!$B:$B,0)) -> 0.02 | J535: =INDEX('xUS TME'!H:H,MATCH(B535,'xUS TME'!$B:$B,0)) -> 0 | K535: =IFERROR((1/J535)-1,"") | L535: =INDEX('xUS TME'!J:J,MATCH('xUS Opp Value'!B535,'xUS TME'!$B:$B,0)) -> 0 | M535: =INDEX('xUS TME'!L:L,MATCH('xUS Opp Value'!$B535,'xUS TME'!$B:$B,0)) -> 4.24 | N535: =INDEX('xUS TME'!K:K,MATCH('xUS Opp Value'!$B535,'xUS TME'!$B:$B,0)) -> 0.18 | O535: =INDEX('xUS TME'!I:I,MATCH('xUS Opp Value'!$B535,'xUS TME'!$B:$B,0)) -> 0 | P535: =INDEX('xUS TME'!M:M,MATCH('xUS Opp Value'!$B535,'xUS TME'!$B:$B,0)) -> Yen | Q535: =INDEX('xUS TME'!N:N,MATCH('xUS Opp Value'!$B535,'xUS TME'!$B:$B,0)) -> 0
A536: Guotai Haitong Securities Co Ltd Registered Shs -H- Unitary 144A/Reg S | B536: =INDEX('xUS TME'!B:B,MATCH('xUS Opp Value'!A536,'xUS TME'!A:A,0)) -> CNE100002FK9 | C536: =INDEX('xUS TME'!C:C,MATCH($B536,'xUS TME'!$B:$B,0)) -> 02611 | D536: =INDEX('xUS TME'!D:D,MATCH(B536,'xUS TME'!$B:$B,0)) -> 0P0001A5I9 | E536: =INDEX('xUS TME'!F:F,MATCH(B536,'xUS TME'!$B:$B,0)) -> China | F536: =INDEX('xUS TME'!G:G,MATCH(B536,'xUS TME'!$B:$B,0)) -> Financials | G536: =IFERROR(INDEX(CRIMs!G:G,MATCH(C536,CRIMs!D:D,0)),0) -> 0 | H536: =IFERROR(INDEX(CRIMs!I:I,MATCH(C536,CRIMs!D:D,0)),0) -> 0 | I536: =INDEX('xUS TME'!E:E,MATCH($B536,'xUS TME'!$B:$B,0)) -> 0.01 | J536: =INDEX('xUS TME'!H:H,MATCH(B536,'xUS TME'!$B:$B,0)) -> 0 | K536: =IFERROR((1/J536)-1,"") | L536: =INDEX('xUS TME'!J:J,MATCH('xUS Opp Value'!B536,'xUS TME'!$B:$B,0)) -> 4.64 | M536: =INDEX('xUS TME'!L:L,MATCH('xUS Opp Value'!$B536,'xUS TME'!$B:$B,0)) -> 0.71 | N536: =INDEX('xUS TME'!K:K,MATCH('xUS Opp Value'!$B536,'xUS TME'!$B:$B,0)) -> 0.1 | O536: =INDEX('xUS TME'!I:I,MATCH('xUS Opp Value'!$B536,'xUS TME'!$B:$B,0)) -> 0 | P536: =INDEX('xUS TME'!M:M,MATCH('xUS Opp Value'!$B536,'xUS TME'!$B:$B,0)) -> Hong Kong Dollar | Q536: =INDEX('xUS TME'!N:N,MATCH('xUS Opp Value'!$B536,'xUS TME'!$B:$B,0)) -> 0
A537: Rightmove PLC | B537: =INDEX('xUS TME'!B:B,MATCH('xUS Opp Value'!A537,'xUS TME'!A:A,0)) -> GB00BGDT3G23 | C537: =INDEX('xUS TME'!C:C,MATCH($B537,'xUS TME'!$B:$B,0)) -> RMV | D537: =INDEX('xUS TME'!D:D,MATCH(B537,'xUS TME'!$B:$B,0)) -> 0P00007Z2B | E537: =INDEX('xUS TME'!F:F,MATCH(B537,'xUS TME'!$B:$B,0)) -> United Kingdom | F537: =INDEX('xUS TME'!G:G,MATCH(B537,'xUS TME'!$B:$B,0)) -> Communication Services | G537: =IFERROR(INDEX(CRIMs!G:G,MATCH(C537,CRIMs!D:D,0)),0) -> 0 | H537: =IFERROR(INDEX(CRIMs!I:I,MATCH(C537,CRIMs!D:D,0)),0) -> 0 | I537: =INDEX('xUS TME'!E:E,MATCH($B537,'xUS TME'!$B:$B,0)) -> 0.01 | J537: =INDEX('xUS TME'!H:H,MATCH(B537,'xUS TME'!$B:$B,0)) -> 0 | K537: =IFERROR((1/J537)-1,"") | L537: =INDEX('xUS TME'!J:J,MATCH('xUS Opp Value'!B537,'xUS TME'!$B:$B,0)) -> 13.94 | M537: =INDEX('xUS TME'!L:L,MATCH('xUS Opp Value'!$B537,'xUS TME'!$B:$B,0)) -> 33.58 | N537: =INDEX('xUS TME'!K:K,MATCH('xUS Opp Value'!$B537,'xUS TME'!$B:$B,0)) -> 2.24 | O537: =INDEX('xUS TME'!I:I,MATCH('xUS Opp Value'!$B537,'xUS TME'!$B:$B,0)) -> 0 | P537: =INDEX('xUS TME'!M:M,MATCH('xUS Opp Value'!$B537,'xUS TME'!$B:$B,0)) -> Pound Sterling | Q537: =INDEX('xUS TME'!N:N,MATCH('xUS Opp Value'!$B537,'xUS TME'!$B:$B,0)) -> 0
A538: SK Telecom Co Ltd | B538: =INDEX('xUS TME'!B:B,MATCH('xUS Opp Value'!A538,'xUS TME'!A:A,0)) -> KR7017670001 | C538: =INDEX('xUS TME'!C:C,MATCH($B538,'xUS TME'!$B:$B,0)) -> 17670 | D538: =INDEX('xUS TME'!D:D,MATCH(B538,'xUS TME'!$B:$B,0)) -> 0P0000BAGH | E538: =INDEX('xUS TME'!F:F,MATCH(B538,'xUS TME'!$B:$B,0)) -> South Korea | F538: =INDEX('xUS TME'!G:G,MATCH(B538,'xUS TME'!$B:$B,0)) -> Communication Services | G538: =IFERROR(INDEX(CRIMs!G:G,MATCH(C538,CRIMs!D:D,0)),0) -> 0 | H538: =IFERROR(INDEX(CRIMs!I:I,MATCH(C538,CRIMs!D:D,0)),0) -> 0 | I538: =INDEX('xUS TME'!E:E,MATCH($B538,'xUS TME'!$B:$B,0)) -> 0.02 | J538: =INDEX('xUS TME'!H:H,MATCH(B538,'xUS TME'!$B:$B,0)) -> 0 | K538: =IFERROR((1/J538)-1,"") | L538: =INDEX('xUS TME'!J:J,MATCH('xUS Opp Value'!B538,'xUS TME'!$B:$B,0)) -> 20.18 | M538: =INDEX('xUS TME'!L:L,MATCH('xUS Opp Value'!$B538,'xUS TME'!$B:$B,0)) -> 1.59 | N538: =INDEX('xUS TME'!K:K,MATCH('xUS Opp Value'!$B538,'xUS TME'!$B:$B,0)) -> 0 | O538: =INDEX('xUS TME'!I:I,MATCH('xUS Opp Value'!$B538,'xUS TME'!$B:$B,0)) -> None | P538: =INDEX('xUS TME'!M:M,MATCH('xUS Opp Value'!$B538,'xUS TME'!$B:$B,0)) -> Won | Q538: =INDEX('xUS TME'!N:N,MATCH('xUS Opp Value'!$B538,'xUS TME'!$B:$B,0)) -> Medium
A539: Sysmex Corp | B539: =INDEX('xUS TME'!B:B,MATCH('xUS Opp Value'!A539,'xUS TME'!A:A,0)) -> JP3351100007 | C539: =INDEX('xUS TME'!C:C,MATCH($B539,'xUS TME'!$B:$B,0)) -> 6869 | D539: =INDEX('xUS TME'!D:D,MATCH(B539,'xUS TME'!$B:$B,0)) -> 0P0000EEFH | E539: =INDEX('xUS TME'!F:F,MATCH(B539,'xUS TME'!$B:$B,0)) -> Japan | F539: =INDEX('xUS TME'!G:G,MATCH(B539,'xUS TME'!$B:$B,0)) -> Health Care | G539: =IFERROR(INDEX(CRIMs!G:G,MATCH(C539,CRIMs!D:D,0)),0) -> 0 | H539: =IFERROR(INDEX(CRIMs!I:I,MATCH(C539,CRIMs!D:D,0)),0) -> 0 | I539: =INDEX('xUS TME'!E:E,MATCH($B539,'xUS TME'!$B:$B,0)) -> 0.01 | J539: =INDEX('xUS TME'!H:H,MATCH(B539,'xUS TME'!$B:$B,0)) -> 0 | K539: =IFERROR((1/J539)-1,"") | L539: =INDEX('xUS TME'!J:J,MATCH('xUS Opp Value'!B539,'xUS TME'!$B:$B,0)) -> 27.93 | M539: =INDEX('xUS TME'!L:L,MATCH('xUS Opp Value'!$B539,'xUS TME'!$B:$B,0)) -> 1.73 | N539: =INDEX('xUS TME'!K:K,MATCH('xUS Opp Value'!$B539,'xUS TME'!$B:$B,0)) -> 0.12 | O539: =INDEX('xUS TME'!I:I,MATCH('xUS Opp Value'!$B539,'xUS TME'!$B:$B,0)) -> 0 | P539: =INDEX('xUS TME'!M:M,MATCH('xUS Opp Value'!$B539,'xUS TME'!$B:$B,0)) -> Yen | Q539: =INDEX('xUS TME'!N:N,MATCH('xUS Opp Value'!$B539,'xUS TME'!$B:$B,0)) -> 0
A540: Vodacom Group Ltd | B540: =INDEX('xUS TME'!B:B,MATCH('xUS Opp Value'!A540,'xUS TME'!A:A,0)) -> ZAE000132577 | C540: =INDEX('xUS TME'!C:C,MATCH($B540,'xUS TME'!$B:$B,0)) -> VOD | D540: =INDEX('xUS TME'!D:D,MATCH(B540,'xUS TME'!$B:$B,0)) -> 0P0000MPIU | E540: =INDEX('xUS TME'!F:F,MATCH(B540,'xUS TME'!$B:$B,0)) -> South Africa | F540: =INDEX('xUS TME'!G:G,MATCH(B540,'xUS TME'!$B:$B,0)) -> Communication Services | G540: =IFERROR(INDEX(CRIMs!G:G,MATCH(C540,CRIMs!D:D,0)),0) -> 0 | H540: =IFERROR(INDEX(CRIMs!I:I,MATCH(C540,CRIMs!D:D,0)),0) -> 0 | I540: =INDEX('xUS TME'!E:E,MATCH($B540,'xUS TME'!$B:$B,0)) -> 0.01 | J540: =INDEX('xUS TME'!H:H,MATCH(B540,'xUS TME'!$B:$B,0)) -> 0 | K540: =IFERROR((1/J540)-1,"") | L540: =INDEX('xUS TME'!J:J,MATCH('xUS Opp Value'!B540,'xUS TME'!$B:$B,0)) -> 0 | M540: =INDEX('xUS TME'!L:L,MATCH('xUS Opp Value'!$B540,'xUS TME'!$B:$B,0)) -> 3.16 | N540: =INDEX('xUS TME'!K:K,MATCH('xUS Opp Value'!$B540,'xUS TME'!$B:$B,0)) -> 0.22 | O540: =INDEX('xUS TME'!I:I,MATCH('xUS Opp Value'!$B540,'xUS TME'!$B:$B,0)) -> 0 | P540: =INDEX('xUS TME'!M:M,MATCH('xUS Opp Value'!$B540,'xUS TME'!$B:$B,0)) -> Rand | Q540: =INDEX('xUS TME'!N:N,MATCH('xUS Opp Value'!$B540,'xUS TME'!$B:$B,0)) -> 0
A541: 3SBio Inc Shs Unitary 144A/Reg S | B541: =INDEX('xUS TME'!B:B,MATCH('xUS Opp Value'!A541,'xUS TME'!A:A,0)) -> KYG8875G1029 | C541: =INDEX('xUS TME'!C:C,MATCH($B541,'xUS TME'!$B:$B,0)) -> 01530 | D541: =INDEX('xUS TME'!D:D,MATCH(B541,'xUS TME'!$B:$B,0)) -> 0P0001675Y | E541: =INDEX('xUS TME'!F:F,MATCH(B541,'xUS TME'!$B:$B,0)) -> China | F541: =INDEX('xUS TME'!G:G,MATCH(B541,'xUS TME'!$B:$B,0)) -> Health Care | G541: =IFERROR(INDEX(CRIMs!G:G,MATCH(C541,CRIMs!D:D,0)),0) -> 0 | H541: =IFERROR(INDEX(CRIMs!I:I,MATCH(C541,CRIMs!D:D,0)),0) -> 0 | I541: =INDEX('xUS TME'!E:E,MATCH($B541,'xUS TME'!$B:$B,0)) -> 0.02 | J541: =INDEX('xUS TME'!H:H,MATCH(B541,'xUS TME'!$B:$B,0)) -> 0 | K541: =IFERROR((1/J541)-1,"") | L541: =INDEX('xUS TME'!J:J,MATCH('xUS Opp Value'!B541,'xUS TME'!$B:$B,0)) -> 26.92 | M541: =INDEX('xUS TME'!L:L,MATCH('xUS Opp Value'!$B541,'xUS TME'!$B:$B,0)) -> 3.03 | N541: =INDEX('xUS TME'!K:K,MATCH('xUS Opp Value'!$B541,'xUS TME'!$B:$B,0)) -> 0.15 | O541: =INDEX('xUS TME'!I:I,MATCH('xUS Opp Value'!$B541,'xUS TME'!$B:$B,0)) -> Narrow | P541: =INDEX('xUS TME'!M:M,MATCH('xUS Opp Value'!$B541,'xUS TME'!$B:$B,0)) -> Hong Kong Dollar | Q541: =INDEX('xUS TME'!N:N,MATCH('xUS Opp Value'!$B541,'xUS TME'!$B:$B,0)) -> Very High
A542: Gerdau SA Participating Preferred | B542: =INDEX('xUS TME'!B:B,MATCH('xUS Opp Value'!A542,'xUS TME'!A:A,0)) -> BRGGBRACNPR8 | C542: =INDEX('xUS TME'!C:C,MATCH($B542,'xUS TME'!$B:$B,0)) -> GGBR4 | D542: =INDEX('xUS TME'!D:D,MATCH(B542,'xUS TME'!$B:$B,0)) -> 0P0000AWM4 | E542: =INDEX('xUS TME'!F:F,MATCH(B542,'xUS TME'!$B:$B,0)) -> Brazil | F542: =INDEX('xUS TME'!G:G,MATCH(B542,'xUS TME'!$B:$B,0)) -> Materials | G542: =IFERROR(INDEX(CRIMs!G:G,MATCH(C542,CRIMs!D:D,0)),0) -> 0 | H542: =IFERROR(INDEX(CRIMs!I:I,MATCH(C542,CRIMs!D:D,0)),0) -> 0 | I542: =INDEX('xUS TME'!E:E,MATCH($B542,'xUS TME'!$B:$B,0)) -> 0.01 | J542: =INDEX('xUS TME'!H:H,MATCH(B542,'xUS TME'!$B:$B,0)) -> 0 | K542: =IFERROR((1/J542)-1,"") | L542: =INDEX('xUS TME'!J:J,MATCH('xUS Opp Value'!B542,'xUS TME'!$B:$B,0)) -> 6.86 | M542: =INDEX('xUS TME'!L:L,MATCH('xUS Opp Value'!$B542,'xUS TME'!$B:$B,0)) -> 0.78 | N542: =INDEX('xUS TME'!K:K,MATCH('xUS Opp Value'!$B542,'xUS TME'!$B:$B,0)) -> 0.03 | O542: =INDEX('xUS TME'!I:I,MATCH('xUS Opp Value'!$B542,'xUS TME'!$B:$B,0)) -> None | P542: =INDEX('xUS TME'!M:M,MATCH('xUS Opp Value'!$B542,'xUS TME'!$B:$B,0)) -> Brazilian Real | Q542: =INDEX('xUS TME'!N:N,MATCH('xUS Opp Value'!$B542,'xUS TME'!$B:$B,0)) -> Extreme
A543: Bank Albilad | B543: =INDEX('xUS TME'!B:B,MATCH('xUS Opp Value'!A543,'xUS TME'!A:A,0)) -> SA000A0D9HK3 | C543: =INDEX('xUS TME'!C:C,MATCH($B543,'xUS TME'!$B:$B,0)) -> 1140 | D543: =INDEX('xUS TME'!D:D,MATCH(B543,'xUS TME'!$B:$B,0)) -> 0P0000Q2J3 | E543: =INDEX('xUS TME'!F:F,MATCH(B543,'xUS TME'!$B:$B,0)) -> Saudi Arabia | F543: =INDEX('xUS TME'!G:G,MATCH(B543,'xUS TME'!$B:$B,0)) -> Financials | G543: =IFERROR(INDEX(CRIMs!G:G,MATCH(C543,CRIMs!D:D,0)),0) -> 0 | H543: =IFERROR(INDEX(CRIMs!I:I,MATCH(C543,CRIMs!D:D,0)),0) -> 0 | I543: =INDEX('xUS TME'!E:E,MATCH($B543,'xUS TME'!$B:$B,0)) -> 0.02 | J543: =INDEX('xUS TME'!H:H,MATCH(B543,'xUS TME'!$B:$B,0)) -> 0 | K543: =IFERROR((1/J543)-1,"") | L543: =INDEX('xUS TME'!J:J,MATCH('xUS Opp Value'!B543,'xUS TME'!$B:$B,0)) -> 0 | M543: =INDEX('xUS TME'!L:L,MATCH('xUS Opp Value'!$B543,'xUS TME'!$B:$B,0)) -> 2.13 | N543: =INDEX('xUS TME'!K:K,MATCH('xUS Opp Value'!$B543,'xUS TME'!$B:$B,0)) -> 0.17 | O543: =INDEX('xUS TME'!I:I,MATCH('xUS Opp Value'!$B543,'xUS TME'!$B:$B,0)) -> 0 | P543: =INDEX('xUS TME'!M:M,MATCH('xUS Opp Value'!$B543,'xUS TME'!$B:$B,0)) -> Saudi Riyal | Q543: =INDEX('xUS TME'!N:N,MATCH('xUS Opp Value'!$B543,'xUS TME'!$B:$B,0)) -> 0
A544: GAIL (India) Ltd | B544: =INDEX('xUS TME'!B:B,MATCH('xUS Opp Value'!A544,'xUS TME'!A:A,0)) -> INE129A01019 | C544: =INDEX('xUS TME'!C:C,MATCH($B544,'xUS TME'!$B:$B,0)) -> 532155 | D544: =INDEX('xUS TME'!D:D,MATCH(B544,'xUS TME'!$B:$B,0)) -> 0P0000BQWX | E544: =INDEX('xUS TME'!F:F,MATCH(B544,'xUS TME'!$B:$B,0)) -> India | F544: =INDEX('xUS TME'!G:G,MATCH(B544,'xUS TME'!$B:$B,0)) -> Utilities | G544: =IFERROR(INDEX(CRIMs!G:G,MATCH(C544,CRIMs!D:D,0)),0) -> 0 | H544: =IFERROR(INDEX(CRIMs!I:I,MATCH(C544,CRIMs!D:D,0)),0) -> 0 | I544: =INDEX('xUS TME'!E:E,MATCH($B544,'xUS TME'!$B:$B,0)) -> 0.01 | J544: =INDEX('xUS TME'!H:H,MATCH(B544,'xUS TME'!$B:$B,0)) -> 0 | K544: =IFERROR((1/J544)-1,"") | L544: =INDEX('xUS TME'!J:J,MATCH('xUS Opp Value'!B544,'xUS TME'!$B:$B,0)) -> 14.06 | M544: =INDEX('xUS TME'!L:L,MATCH('xUS Opp Value'!$B544,'xUS TME'!$B:$B,0)) -> 1.15 | N544: =INDEX('xUS TME'!K:K,MATCH('xUS Opp Value'!$B544,'xUS TME'!$B:$B,0)) -> 0.15 | O544: =INDEX('xUS TME'!I:I,MATCH('xUS Opp Value'!$B544,'xUS TME'!$B:$B,0)) -> 0 | P544: =INDEX('xUS TME'!M:M,MATCH('xUS Opp Value'!$B544,'xUS TME'!$B:$B,0)) -> Indian Rupee | Q544: =INDEX('xUS TME'!N:N,MATCH('xUS Opp Value'!$B544,'xUS TME'!$B:$B,0)) -> 0
A545: Nordnet AB (publ) Ordinary Shares | B545: =INDEX('xUS TME'!B:B,MATCH('xUS Opp Value'!A545,'xUS TME'!A:A,0)) -> SE0015192067 | C545: =INDEX('xUS TME'!C:C,MATCH($B545,'xUS TME'!$B:$B,0)) -> SAVE | D545: =INDEX('xUS TME'!D:D,MATCH(B545,'xUS TME'!$B:$B,0)) -> 0P0001L6NG | E545: =INDEX('xUS TME'!F:F,MATCH(B545,'xUS TME'!$B:$B,0)) -> Sweden | F545: =INDEX('xUS TME'!G:G,MATCH(B545,'xUS TME'!$B:$B,0)) -> Financials | G545: =IFERROR(INDEX(CRIMs!G:G,MATCH(C545,CRIMs!D:D,0)),0) -> 0 | H545: =IFERROR(INDEX(CRIMs!I:I,MATCH(C545,CRIMs!D:D,0)),0) -> 0 | I545: =INDEX('xUS TME'!E:E,MATCH($B545,'xUS TME'!$B:$B,0)) -> 0.02 | J545: =INDEX('xUS TME'!H:H,MATCH(B545,'xUS TME'!$B:$B,0)) -> 0 | K545: =IFERROR((1/J545)-1,"") | L545: =INDEX('xUS TME'!J:J,MATCH('xUS Opp Value'!B545,'xUS TME'!$B:$B,0)) -> 23.17 | M545: =INDEX('xUS TME'!L:L,MATCH('xUS Opp Value'!$B545,'xUS TME'!$B:$B,0)) -> 10.94 | N545: =INDEX('xUS TME'!K:K,MATCH('xUS Opp Value'!$B545,'xUS TME'!$B:$B,0)) -> 0.42 | O545: =INDEX('xUS TME'!I:I,MATCH('xUS Opp Value'!$B545,'xUS TME'!$B:$B,0)) -> 0 | P545: =INDEX('xUS TME'!M:M,MATCH('xUS Opp Value'!$B545,'xUS TME'!$B:$B,0)) -> Swedish Krona | Q545: =INDEX('xUS TME'!N:N,MATCH('xUS Opp Value'!$B545,'xUS TME'!$B:$B,0)) -> 0
... A1537: WiseTech Global Ltd | B1537: =INDEX('xUS TME'!B:B,MATCH('xUS Opp Value'!A1537,'xUS TME'!A:A,0)) -> AU000000WTC3 | C1537: =INDEX('xUS TME'!C:C,MATCH($B1537,'xUS TME'!$B:$B,0)) -> WTC | D1537: =INDEX('xUS TME'!D:D,MATCH(B1537,'xUS TME'!$B:$B,0)) -> 0P00017S3Y | E1537: =INDEX('xUS TME'!F:F,MATCH(B1537,'xUS TME'!$B:$B,0)) -> Australia | F1537: =INDEX('xUS TME'!G:G,MATCH(B1537,'xUS TME'!$B:$B,0)) -> Information Technology | G1537: =IFERROR(INDEX(CRIMs!G:G,MATCH(C1537,CRIMs!D:D,0)),0) -> 0 | H1537: =IFERROR(INDEX(CRIMs!I:I,MATCH(C1537,CRIMs!D:D,0)),0) -> 0 | I1537: =INDEX('xUS TME'!E:E,MATCH($B1537,'xUS TME'!$B:$B,0)) -> 0.01 | J1537: =INDEX('xUS TME'!H:H,MATCH(B1537,'xUS TME'!$B:$B,0)) -> 0.27 | K1537: =IFERROR((1/J1537)-1,"") -> 2.7037037 | L1537: =INDEX('xUS TME'!J:J,MATCH('xUS Opp Value'!B1537,'xUS TME'!$B:$B,0)) -> 29.58 | M1537: =INDEX('xUS TME'!L:L,MATCH('xUS Opp Value'!$B1537,'xUS TME'!$B:$B,0)) -> 4.65 | N1537: =INDEX('xUS TME'!K:K,MATCH('xUS Opp Value'!$B1537,'xUS TME'!$B:$B,0)) -> 0.13 | O1537: =INDEX('xUS TME'!I:I,MATCH('xUS Opp Value'!$B1537,'xUS TME'!$B:$B,0)) -> Wide | P1537: =INDEX('xUS TME'!M:M,MATCH('xUS Opp Value'!$B1537,'xUS TME'!$B:$B,0)) -> Australian Dollar | Q1537: =INDEX('xUS TME'!N:N,MATCH('xUS Opp Value'!$B1537,'xUS TME'!$B:$B,0)) -> High
A1538: Nexi SpA | B1538: =_xll.MSDP(C1538,"ISIN") -> US65344D2080 | C1538: NEXI | D1538: 0P0001HARK | E1538: Italy | F1538: Financials | G1538: =IFERROR(INDEX(CRIMs!G:G,MATCH(C1538,CRIMs!D:D,0)),0) -> 0.75 | H1538: =IFERROR(INDEX(CRIMs!I:I,MATCH(C1538,CRIMs!D:D,0)),0) -> 0.52206849 | I1538: 0 | K1538: =IFERROR((1/J1538)-1,"") | Q1538: =INDEX('xUS TME'!N:N,MATCH('xUS Opp Value'!$B1538,'xUS TME'!$B:$B,0)) -> #N/A
A1539: NetEase Cloud Music Inc | B1539: =INDEX('xUS TME'!B:B,MATCH('xUS Opp Value'!A1539,'xUS TME'!A:A,0)) -> KYG2215N1097 | C1539: =INDEX('xUS TME'!C:C,MATCH($B1539,'xUS TME'!$B:$B,0)) -> 9899 | D1539: =INDEX('xUS TME'!D:D,MATCH(B1539,'xUS TME'!$B:$B,0)) -> 0P0001NX39 | E1539: =INDEX('xUS TME'!F:F,MATCH(B1539,'xUS TME'!$B:$B,0)) -> China | F1539: =INDEX('xUS TME'!G:G,MATCH(B1539,'xUS TME'!$B:$B,0)) -> Communication Services | G1539: =IFERROR(INDEX(CRIMs!G:G,MATCH(C1539,CRIMs!D:D,0)),0) -> 0 | H1539: =IFERROR(INDEX(CRIMs!I:I,MATCH(C1539,CRIMs!D:D,0)),0) -> 0 | I1539: =INDEX('xUS TME'!E:E,MATCH($B1539,'xUS TME'!$B:$B,0)) -> 0 | J1539: =INDEX('xUS TME'!H:H,MATCH(B1539,'xUS TME'!$B:$B,0)) -> 0.36 | K1539: =IFERROR((1/J1539)-1,"") -> 1.7777778 | L1539: =INDEX('xUS TME'!J:J,MATCH('xUS Opp Value'!B1598,'xUS TME'!$B:$B,0)) -> 8.33 | M1539: =INDEX('xUS TME'!L:L,MATCH('xUS Opp Value'!$B1598,'xUS TME'!$B:$B,0)) -> 1.44 | N1539: =INDEX('xUS TME'!K:K,MATCH('xUS Opp Value'!$B1598,'xUS TME'!$B:$B,0)) -> 0.17 | O1539: =INDEX('xUS TME'!I:I,MATCH('xUS Opp Value'!$B1598,'xUS TME'!$B:$B,0)) -> Narrow | P1539: =INDEX('xUS TME'!M:M,MATCH('xUS Opp Value'!$B1598,'xUS TME'!$B:$B,0)) -> Hong Kong Dollar | Q1539: =INDEX('xUS TME'!N:N,MATCH('xUS Opp Value'!$B1539,'xUS TME'!$B:$B,0)) -> High
A1540: Wolters Kluwer NV | B1540: =INDEX('xUS TME'!B:B,MATCH('xUS Opp Value'!A1540,'xUS TME'!A:A,0)) -> NL0000395903 | C1540: =INDEX('xUS TME'!C:C,MATCH($B1540,'xUS TME'!$B:$B,0)) -> WKL | D1540: =INDEX('xUS TME'!D:D,MATCH(B1540,'xUS TME'!$B:$B,0)) -> 0P0000A646 | E1540: =INDEX('xUS TME'!F:F,MATCH(B1540,'xUS TME'!$B:$B,0)) -> Netherlands | F1540: =INDEX('xUS TME'!G:G,MATCH(B1540,'xUS TME'!$B:$B,0)) -> Industrials | G1540: =IFERROR(INDEX(CRIMs!G:G,MATCH(C1540,CRIMs!D:D,0)),0) -> 0.5 | H1540: =IFERROR(INDEX(CRIMs!I:I,MATCH(C1540,CRIMs!D:D,0)),0) -> 0.36805934 | I1540: =INDEX('xUS TME'!E:E,MATCH($B1540,'xUS TME'!$B:$B,0)) -> 0.05 | J1540: =INDEX('xUS TME'!H:H,MATCH(B1540,'xUS TME'!$B:$B,0)) -> 0.52 | K1540: =IFERROR((1/J1540)-1,"") -> 0.92307692 | L1540: =INDEX('xUS TME'!J:J,MATCH('xUS Opp Value'!B378,'xUS TME'!$B:$B,0)) -> 0 | M1540: =INDEX('xUS TME'!L:L,MATCH('xUS Opp Value'!$B378,'xUS TME'!$B:$B,0)) -> 0.85 | N1540: =INDEX('xUS TME'!K:K,MATCH('xUS Opp Value'!$B378,'xUS TME'!$B:$B,0)) -> -0.04 | O1540: =INDEX('xUS TME'!I:I,MATCH('xUS Opp Value'!$B378,'xUS TME'!$B:$B,0)) -> None | P1540: =INDEX('xUS TME'!M:M,MATCH('xUS Opp Value'!$B378,'xUS TME'!$B:$B,0)) -> Euro | Q1540: =INDEX('xUS TME'!N:N,MATCH('xUS Opp Value'!$B1540,'xUS TME'!$B:$B,0)) -> Medium
A1541: Tencent Music | B1541: US88034P1093 | C1541: TME | E1541: China | F1541: Communication Services | G1541: =IFERROR(INDEX(CRIMs!G:G,MATCH(C1541,CRIMs!D:D,0)),0) -> 0.75 | H1541: =IFERROR(INDEX(CRIMs!I:I,MATCH(C1541,CRIMs!D:D,0)),0) -> 0.50259544 | J1541: =9.73/28 -> 0.3475 | K1541: =IFERROR((1/J1541)-1,"") -> 1.8776978 | Q1541: =INDEX('xUS TME'!N:N,MATCH('xUS Opp Value'!$B1541,'xUS TME'!$B:$B,0)) -> #N/A
A1542: Tencent Music Entertainment Group Class A | B1542: =INDEX('xUS TME'!B:B,MATCH('xUS Opp Value'!A1542,'xUS TME'!A:A,0)) -> KYG875771134 | C1542: =INDEX('xUS TME'!C:C,MATCH($B1542,'xUS TME'!$B:$B,0)) -> 1698 | D1542: =INDEX('xUS TME'!D:D,MATCH(B1542,'xUS TME'!$B:$B,0)) -> 0P0001PQUK | E1542: =INDEX('xUS TME'!F:F,MATCH(B1542,'xUS TME'!$B:$B,0)) -> China | F1542: =INDEX('xUS TME'!G:G,MATCH(B1542,'xUS TME'!$B:$B,0)) -> Communication Services | G1542: =IFERROR(INDEX(CRIMs!G:G,MATCH(C1542,CRIMs!D:D,0)),0) -> 0 | H1542: =IFERROR(INDEX(CRIMs!I:I,MATCH(C1542,CRIMs!D:D,0)),0) -> 0 | I1542: =INDEX('xUS TME'!E:E,MATCH($B1542,'xUS TME'!$B:$B,0)) -> 0.02 | J1542: =INDEX('xUS TME'!H:H,MATCH(B1542,'xUS TME'!$B:$B,0)) -> 0.34 | K1542: =IFERROR((1/J1542)-1,"") -> 1.9411765 | L1542: =INDEX('xUS TME'!J:J,MATCH('xUS Opp Value'!B715,'xUS TME'!$B:$B,0)) -> 14.82 | M1542: =INDEX('xUS TME'!L:L,MATCH('xUS Opp Value'!$B715,'xUS TME'!$B:$B,0)) -> 17.08 | N1542: =INDEX('xUS TME'!K:K,MATCH('xUS Opp Value'!$B715,'xUS TME'!$B:$B,0)) -> 1.41 | O1542: =INDEX('xUS TME'!I:I,MATCH('xUS Opp Value'!$B715,'xUS TME'!$B:$B,0)) -> 0 | P1542: =INDEX('xUS TME'!M:M,MATCH('xUS Opp Value'!$B715,'xUS TME'!$B:$B,0)) -> Mexican Peso | Q1542: =INDEX('xUS TME'!N:N,MATCH('xUS Opp Value'!$B1542,'xUS TME'!$B:$B,0)) -> High
A1543: Stellantis NV | B1543: =INDEX('xUS TME'!B:B,MATCH('xUS Opp Value'!A1543,'xUS TME'!A:A,0)) -> NL00150001Q9 | C1543: =INDEX('xUS TME'!C:C,MATCH($B1543,'xUS TME'!$B:$B,0)) -> STLAM | D1543: =INDEX('xUS TME'!D:D,MATCH(B1543,'xUS TME'!$B:$B,0)) -> 0P00009DK4 | E1543: =INDEX('xUS TME'!F:F,MATCH(B1543,'xUS TME'!$B:$B,0)) -> Netherlands | F1543: =INDEX('xUS TME'!G:G,MATCH(B1543,'xUS TME'!$B:$B,0)) -> Consumer Discretionary | G1543: =IFERROR(INDEX(CRIMs!G:G,MATCH(C1543,CRIMs!D:D,0)),0) -> 0 | H1543: =IFERROR(INDEX(CRIMs!I:I,MATCH(C1543,CRIMs!D:D,0)),0) -> 0 | I1543: =INDEX('xUS TME'!E:E,MATCH($B1543,'xUS TME'!$B:$B,0)) -> 0.04 | J1543: =INDEX('xUS TME'!H:H,MATCH(B1543,'xUS TME'!$B:$B,0)) -> 0.56 | K1543: =IFERROR((1/J1543)-1,"") -> 0.78571429 | L1543: =INDEX('xUS TME'!J:J,MATCH('xUS Opp Value'!B409,'xUS TME'!$B:$B,0)) -> 0 | M1543: =INDEX('xUS TME'!L:L,MATCH('xUS Opp Value'!$B409,'xUS TME'!$B:$B,0)) -> 7.76 | N1543: =INDEX('xUS TME'!K:K,MATCH('xUS Opp Value'!$B409,'xUS TME'!$B:$B,0)) -> 0.28 | O1543: =INDEX('xUS TME'!I:I,MATCH('xUS Opp Value'!$B409,'xUS TME'!$B:$B,0)) -> 0 | P1543: =INDEX('xUS TME'!M:M,MATCH('xUS Opp Value'!$B409,'xUS TME'!$B:$B,0)) -> Zloty | Q1543: =INDEX('xUS TME'!N:N,MATCH('xUS Opp Value'!$B1543,'xUS TME'!$B:$B,0)) -> Very High
A1544: Pandora AS | B1544: =INDEX('xUS TME'!B:B,MATCH('xUS Opp Value'!A1544,'xUS TME'!A:A,0)) -> DK0060252690 | C1544: =INDEX('xUS TME'!C:C,MATCH($B1544,'xUS TME'!$B:$B,0)) -> PNDORA | D1544: =INDEX('xUS TME'!D:D,MATCH(B1544,'xUS TME'!$B:$B,0)) -> 0P0000Q1VF | E1544: =INDEX('xUS TME'!F:F,MATCH(B1544,'xUS TME'!$B:$B,0)) -> Denmark | F1544: =INDEX('xUS TME'!G:G,MATCH(B1544,'xUS TME'!$B:$B,0)) -> Consumer Discretionary | G1544: =IFERROR(INDEX(CRIMs!G:G,MATCH(C1544,CRIMs!D:D,0)),0) -> 0.5 | H1544: =IFERROR(INDEX(CRIMs!I:I,MATCH(C1544,CRIMs!D:D,0)),0) -> 0.37541952 | I1544: =INDEX('xUS TME'!E:E,MATCH($B1544,'xUS TME'!$B:$B,0)) -> 0.02 | J1544: =INDEX('xUS TME'!H:H,MATCH(B1544,'xUS TME'!$B:$B,0)) -> 0.51 | K1544: =IFERROR((1/J1544)-1,"") -> 0.96078431 | L1544: =INDEX('xUS TME'!J:J,MATCH('xUS Opp Value'!B950,'xUS TME'!$B:$B,0)) -> 6.56 | M1544: =INDEX('xUS TME'!L:L,MATCH('xUS Opp Value'!$B950,'xUS TME'!$B:$B,0)) -> 0.68 | N1544: =INDEX('xUS TME'!K:K,MATCH('xUS Opp Value'!$B950,'xUS TME'!$B:$B,0)) -> 0.04 | O1544: =INDEX('xUS TME'!I:I,MATCH('xUS Opp Value'!$B950,'xUS TME'!$B:$B,0)) -> None | P1544: =INDEX('xUS TME'!M:M,MATCH('xUS Opp Value'!$B950,'xUS TME'!$B:$B,0)) -> Yuan Renminbi | Q1544: =INDEX('xUS TME'!N:N,MATCH('xUS Opp Value'!$B1544,'xUS TME'!$B:$B,0)) -> High
A1545: Prosus NV Ordinary Shares - Class N | B1545: =INDEX('xUS TME'!B:B,MATCH('xUS Opp Value'!A1545,'xUS TME'!A:A,0)) -> NL0013654783 | C1545: =INDEX('xUS TME'!C:C,MATCH($B1545,'xUS TME'!$B:$B,0)) -> PRX | D1545: =INDEX('xUS TME'!D:D,MATCH(B1545,'xUS TME'!$B:$B,0)) -> 0P0001ICBL | E1545: =INDEX('xUS TME'!F:F,MATCH(B1545,'xUS TME'!$B:$B,0)) -> Netherlands | F1545: =INDEX('xUS TME'!G:G,MATCH(B1545,'xUS TME'!$B:$B,0)) -> Consumer Discretionary | G1545: =IFERROR(INDEX(CRIMs!G:G,MATCH(C1545,CRIMs!D:D,0)),0) -> 0 | H1545: =IFERROR(INDEX(CRIMs!I:I,MATCH(C1545,CRIMs!D:D,0)),0) -> 0 | I1545: =INDEX('xUS TME'!E:E,MATCH($B1545,'xUS TME'!$B:$B,0)) -> 0.15 | J1545: =INDEX('xUS TME'!H:H,MATCH(B1545,'xUS TME'!$B:$B,0)) -> 0.58 | K1545: =IFERROR((1/J1545)-1,"") -> 0.72413793 | L1545: =INDEX('xUS TME'!J:J,MATCH('xUS Opp Value'!B96,'xUS TME'!$B:$B,0)) -> 12.41 | M1545: =INDEX('xUS TME'!L:L,MATCH('xUS Opp Value'!$B96,'xUS TME'!$B:$B,0)) -> 1.44 | N1545: =INDEX('xUS TME'!K:K,MATCH('xUS Opp Value'!$B96,'xUS TME'!$B:$B,0)) -> 0.12 | O1545: =INDEX('xUS TME'!I:I,MATCH('xUS Opp Value'!$B96,'xUS TME'!$B:$B,0)) -> 0 | P1545: =INDEX('xUS TME'!M:M,MATCH('xUS Opp Value'!$B96,'xUS TME'!$B:$B,0)) -> Malaysian Ringgit | Q1545: =INDEX('xUS TME'!N:N,MATCH('xUS Opp Value'!$B1545,'xUS TME'!$B:$B,0)) -> High
A1546: CSL Ltd | B1546: =INDEX('xUS TME'!B:B,MATCH('xUS Opp Value'!A1546,'xUS TME'!A:A,0)) -> AU000000CSL8 | C1546: =INDEX('xUS TME'!C:C,MATCH($B1546,'xUS TME'!$B:$B,0)) -> CSL | D1546: =INDEX('xUS TME'!D:D,MATCH(B1546,'xUS TME'!$B:$B,0)) -> 0P00006WCJ | E1546: =INDEX('xUS TME'!F:F,MATCH(B1546,'xUS TME'!$B:$B,0)) -> Australia | F1546: =INDEX('xUS TME'!G:G,MATCH(B1546,'xUS TME'!$B:$B,0)) -> Health Care | G1546: =IFERROR(INDEX(CRIMs!G:G,MATCH(C1546,CRIMs!D:D,0)),0) -> 0.5 | H1546: =IFERROR(INDEX(CRIMs!I:I,MATCH(C1546,CRIMs!D:D,0)),0) -> 0.40628184 | I1546: =INDEX('xUS TME'!E:E,MATCH($B1546,'xUS TME'!$B:$B,0)) -> 0.14 | J1546: =INDEX('xUS TME'!H:H,MATCH(B1546,'xUS TME'!$B:$B,0)) -> 0.65 | K1546: =IFERROR((1/J1546)-1,"") -> 0.53846154 | L1546: =INDEX('xUS TME'!J:J,MATCH('xUS Opp Value'!B123,'xUS TME'!$B:$B,0)) -> 32.08 | M1546: =INDEX('xUS TME'!L:L,MATCH('xUS Opp Value'!$B123,'xUS TME'!$B:$B,0)) -> 16.52 | N1546: =INDEX('xUS TME'!K:K,MATCH('xUS Opp Value'!$B123,'xUS TME'!$B:$B,0)) -> 0.47 | O1546: =INDEX('xUS TME'!I:I,MATCH('xUS Opp Value'!$B123,'xUS TME'!$B:$B,0)) -> 0 | P1546: =INDEX('xUS TME'!M:M,MATCH('xUS Opp Value'!$B123,'xUS TME'!$B:$B,0)) -> Yen | Q1546: =INDEX('xUS TME'!N:N,MATCH('xUS Opp Value'!$B1546,'xUS TME'!$B:$B,0)) -> Medium
A1547: Daiichi Sankyo Co Ltd | B1547: =INDEX('xUS TME'!B:B,MATCH('xUS Opp Value'!A1547,'xUS TME'!A:A,0)) -> JP3475350009 | C1547: =INDEX('xUS TME'!C:C,MATCH($B1547,'xUS TME'!$B:$B,0)) -> 4568 | D1547: =INDEX('xUS TME'!D:D,MATCH(B1547,'xUS TME'!$B:$B,0)) -> 0P0000AEU1 | E1547: =INDEX('xUS TME'!F:F,MATCH(B1547,'xUS TME'!$B:$B,0)) -> Japan | F1547: =INDEX('xUS TME'!G:G,MATCH(B1547,'xUS TME'!$B:$B,0)) -> Health Care | G1547: 1 | H1547: 0.94 | I1547: =INDEX('xUS TME'!E:E,MATCH($B1547,'xUS TME'!$B:$B,0)) -> 0.1 | J1547: =INDEX('xUS TME'!H:H,MATCH(B1547,'xUS TME'!$B:$B,0)) -> 0.52 | K1547: =IFERROR((1/J1547)-1,"") -> 0.92307692 | L1547: =INDEX('xUS TME'!J:J,MATCH('xUS Opp Value'!B227,'xUS TME'!$B:$B,0)) -> 0 | M1547: =INDEX('xUS TME'!L:L,MATCH('xUS Opp Value'!$B227,'xUS TME'!$B:$B,0)) -> 2.02 | N1547: =INDEX('xUS TME'!K:K,MATCH('xUS Opp Value'!$B227,'xUS TME'!$B:$B,0)) -> 0.18 | O1547: =INDEX('xUS TME'!I:I,MATCH('xUS Opp Value'!$B227,'xUS TME'!$B:$B,0)) -> 0 | P1547: =INDEX('xUS TME'!M:M,MATCH('xUS Opp Value'!$B227,'xUS TME'!$B:$B,0)) -> Euro | Q1547: =INDEX('xUS TME'!N:N,MATCH('xUS Opp Value'!$B1547,'xUS TME'!$B:$B,0)) -> High
A1548: Alibaba Group Holding Ltd Ordinary Shares | B1548: =INDEX('xUS TME'!B:B,MATCH('xUS Opp Value'!A1548,'xUS TME'!A:A,0)) -> KYG017191142 | C1548: 9988 | D1548: =INDEX('xUS TME'!D:D,MATCH(B1548,'xUS TME'!$B:$B,0)) -> 0P0001ITIV | E1548: =INDEX('xUS TME'!F:F,MATCH(B1548,'xUS TME'!$B:$B,0)) -> China | F1548: =INDEX('xUS TME'!G:G,MATCH(B1548,'xUS TME'!$B:$B,0)) -> Consumer Discretionary | G1548: =IFERROR(INDEX(CRIMs!G:G,MATCH(C1548,CRIMs!D:D,0)),0) -> 2 | H1548: =IFERROR(INDEX(CRIMs!I:I,MATCH(C1548,CRIMs!D:D,0)),0) -> 2.0253896 | I1548: =INDEX('xUS TME'!E:E,MATCH($B1548,'xUS TME'!$B:$B,0)) -> 0.84 | J1548: =INDEX('xUS TME'!H:H,MATCH(B1548,'xUS TME'!$B:$B,0)) -> 0.49 | K1548: =IFERROR((1/J1548)-1,"") -> 1.0408163 | L1548: =INDEX('xUS TME'!J:J,MATCH('xUS Opp Value'!B8,'xUS TME'!$B:$B,0)) -> 11.95 | M1548: =INDEX('xUS TME'!L:L,MATCH('xUS Opp Value'!$B8,'xUS TME'!$B:$B,0)) -> 2.18 | N1548: =INDEX('xUS TME'!K:K,MATCH('xUS Opp Value'!$B8,'xUS TME'!$B:$B,0)) -> 0.08 | O1548: =INDEX('xUS TME'!I:I,MATCH('xUS Opp Value'!$B8,'xUS TME'!$B:$B,0)) -> Narrow | P1548: =INDEX('xUS TME'!M:M,MATCH('xUS Opp Value'!$B8,'xUS TME'!$B:$B,0)) -> Canadian Dollar | Q1548: =INDEX('xUS TME'!N:N,MATCH('xUS Opp Value'!$B1548,'xUS TME'!$B:$B,0)) -> High
A1549: Shenzhou International Group Holdings Ltd | B1549: =INDEX('xUS TME'!B:B,MATCH('xUS Opp Value'!A1549,'xUS TME'!A:A,0)) -> KYG8087W1015 | C1549: =INDEX('xUS TME'!C:C,MATCH($B1549,'xUS TME'!$B:$B,0)) -> 02313 | D1549: =INDEX('xUS TME'!D:D,MATCH(B1549,'xUS TME'!$B:$B,0)) -> 0P00009S94 | E1549: =INDEX('xUS TME'!F:F,MATCH(B1549,'xUS TME'!$B:$B,0)) -> Hong Kong | F1549: =INDEX('xUS TME'!G:G,MATCH(B1549,'xUS TME'!$B:$B,0)) -> Consumer Discretionary | G1549: =IFERROR(INDEX(CRIMs!G:G,MATCH(C1549,CRIMs!D:D,0)),0) -> 0 | H1549: =IFERROR(INDEX(CRIMs!I:I,MATCH(C1549,CRIMs!D:D,0)),0) -> 0 | I1549: =INDEX('xUS TME'!E:E,MATCH($B1549,'xUS TME'!$B:$B,0)) -> 0.01 | J1549: =INDEX('xUS TME'!H:H,MATCH(B1549,'xUS TME'!$B:$B,0)) -> 0.51 | K1549: =IFERROR((1/J1549)-1,"") -> 0.96078431 | L1549: =INDEX('xUS TME'!J:J,MATCH('xUS Opp Value'!B952,'xUS TME'!$B:$B,0)) -> 17.53 | M1549: =INDEX('xUS TME'!L:L,MATCH('xUS Opp Value'!$B952,'xUS TME'!$B:$B,0)) -> 2.52 | N1549: =INDEX('xUS TME'!K:K,MATCH('xUS Opp Value'!$B952,'xUS TME'!$B:$B,0)) -> 0.15 | O1549: =INDEX('xUS TME'!I:I,MATCH('xUS Opp Value'!$B952,'xUS TME'!$B:$B,0)) -> 0 | P1549: =INDEX('xUS TME'!M:M,MATCH('xUS Opp Value'!$B952,'xUS TME'!$B:$B,0)) -> Yuan Renminbi | Q1549: =INDEX('xUS TME'!N:N,MATCH('xUS Opp Value'!$B1549,'xUS TME'!$B:$B,0)) -> High
A1550: Jiangsu Yanghe Distillery Co Ltd Class A | B1550: =INDEX('xUS TME'!B:B,MATCH('xUS Opp Value'!A1550,'xUS TME'!A:A,0)) -> CNE100000HB8 | C1550: =INDEX('xUS TME'!C:C,MATCH($B1550,'xUS TME'!$B:$B,0)) -> 2304 | D1550: =INDEX('xUS TME'!D:D,MATCH(B1550,'xUS TME'!$B:$B,0)) -> 0P0000N44I | E1550: =INDEX('xUS TME'!F:F,MATCH(B1550,'xUS TME'!$B:$B,0)) -> China | F1550: =INDEX('xUS TME'!G:G,MATCH(B1550,'xUS TME'!$B:$B,0)) -> Consumer Staples | G1550: =IFERROR(INDEX(CRIMs!G:G,MATCH(C1550,CRIMs!D:D,0)),0) -> 0 | H1550: =IFERROR(INDEX(CRIMs!I:I,MATCH(C1550,CRIMs!D:D,0)),0) -> 0 | I1550: =INDEX('xUS TME'!E:E,MATCH($B1550,'xUS TME'!$B:$B,0)) -> 0 | J1550: =INDEX('xUS TME'!H:H,MATCH(B1550,'xUS TME'!$B:$B,0)) -> 0.53 | K1550: =IFERROR((1/J1550)-1,"") -> 0.88679245 | L1550: =INDEX('xUS TME'!J:J,MATCH('xUS Opp Value'!B1735,'xUS TME'!$B:$B,0)) -> 13.65 | M1550: =INDEX('xUS TME'!L:L,MATCH('xUS Opp Value'!$B1735,'xUS TME'!$B:$B,0)) -> 2.41 | N1550: =INDEX('xUS TME'!K:K,MATCH('xUS Opp Value'!$B1735,'xUS TME'!$B:$B,0)) -> 0.24 | O1550: =INDEX('xUS TME'!I:I,MATCH('xUS Opp Value'!$B1735,'xUS TME'!$B:$B,0)) -> Narrow | P1550: =INDEX('xUS TME'!M:M,MATCH('xUS Opp Value'!$B1735,'xUS TME'!$B:$B,0)) -> Euro | Q1550: =INDEX('xUS TME'!N:N,MATCH('xUS Opp Value'!$B1550,'xUS TME'!$B:$B,0)) -> Medium
A1551: Croda International PLC | B1551: =_xll.MSDP(C1551,"ISIN") -> GB00BJFFLV09 | C1551: CRDA | D1551: 0P000090MV | E1551: United Kingdom | F1551: Materials | G1551: =IFERROR(INDEX(CRIMs!G:G,MATCH(C1551,CRIMs!D:D,0)),0) -> 0.75 | H1551: =IFERROR(INDEX(CRIMs!I:I,MATCH(C1551,CRIMs!D:D,0)),0) -> 0.83488834 | I1551: 0 | J1551: =_xll.MSDP(B1551,"PRICE_TO_FAIR_VALUE") -> 0.58673077 | K1551: =IFERROR((1/J1551)-1,"") -> 0.70435923 | Q1551: =INDEX('xUS TME'!N:N,MATCH('xUS Opp Value'!$B1551,'xUS TME'!$B:$B,0)) -> #N/A
A1552: DSM-Firmenich AG | B1552: =INDEX('xUS TME'!B:B,MATCH('xUS Opp Value'!A1552,'xUS TME'!A:A,0)) -> CH1216478797 | C1552: =INDEX('xUS TME'!C:C,MATCH($B1552,'xUS TME'!$B:$B,0)) -> DSFIR | D1552: =INDEX('xUS TME'!D:D,MATCH(B1552,'xUS TME'!$B:$B,0)) -> 0P0001QU3R | E1552: =INDEX('xUS TME'!F:F,MATCH(B1552,'xUS TME'!$B:$B,0)) -> Switzerland | F1552: =INDEX('xUS TME'!G:G,MATCH(B1552,'xUS TME'!$B:$B,0)) -> Materials | G1552: =IFERROR(INDEX(CRIMs!G:G,MATCH(C1552,CRIMs!D:D,0)),0) -> 0.5 | H1552: =IFERROR(INDEX(CRIMs!I:I,MATCH(C1552,CRIMs!D:D,0)),0) -> 0.46438414 | I1552: =INDEX('xUS TME'!E:E,MATCH($B1552,'xUS TME'!$B:$B,0)) -> 0.05 | J1552: =INDEX('xUS TME'!H:H,MATCH(B1552,'xUS TME'!$B:$B,0)) -> 0.61 | K1552: =IFERROR((1/J1552)-1,"") -> 0.63934426 | L1552: =INDEX('xUS TME'!J:J,MATCH('xUS Opp Value'!B418,'xUS TME'!$B:$B,0)) -> 15.78 | M1552: =INDEX('xUS TME'!L:L,MATCH('xUS Opp Value'!$B418,'xUS TME'!$B:$B,0)) -> 3.72 | N1552: =INDEX('xUS TME'!K:K,MATCH('xUS Opp Value'!$B418,'xUS TME'!$B:$B,0)) -> 0.19 | O1552: =INDEX('xUS TME'!I:I,MATCH('xUS Opp Value'!$B418,'xUS TME'!$B:$B,0)) -> Narrow | P1552: =INDEX('xUS TME'!M:M,MATCH('xUS Opp Value'!$B418,'xUS TME'!$B:$B,0)) -> Swedish Krona | Q1552: =INDEX('xUS TME'!N:N,MATCH('xUS Opp Value'!$B1552,'xUS TME'!$B:$B,0)) -> Medium
A1553: NetEase Inc Ordinary Shares | B1553: =INDEX('xUS TME'!B:B,MATCH('xUS Opp Value'!A1553,'xUS TME'!A:A,0)) -> KYG6427A1022 | C1553: 9999 | D1553: =INDEX('xUS TME'!D:D,MATCH(B1553,'xUS TME'!$B:$B,0)) -> 0P0001K417 | E1553: =INDEX('xUS TME'!F:F,MATCH(B1553,'xUS TME'!$B:$B,0)) -> China | F1553: =INDEX('xUS TME'!G:G,MATCH(B1553,'xUS TME'!$B:$B,0)) -> Communication Services | G1553: =IFERROR(INDEX(CRIMs!G:G,MATCH(C1553,CRIMs!D:D,0)),0) -> 1.5 | H1553: =IFERROR(INDEX(CRIMs!I:I,MATCH(C1553,CRIMs!D:D,0)),0) -> 1.4986872 | I1553: =INDEX('xUS TME'!E:E,MATCH($B1553,'xUS TME'!$B:$B,0)) -> 0.12 | J1553: =INDEX('xUS TME'!H:H,MATCH(B1553,'xUS TME'!$B:$B,0)) -> 0.57 | K1553: =IFERROR((1/J1553)-1,"") -> 0.75438596 | L1553: =INDEX('xUS TME'!J:J,MATCH('xUS Opp Value'!B171,'xUS TME'!$B:$B,0)) -> 20.46 | M1553: =INDEX('xUS TME'!L:L,MATCH('xUS Opp Value'!$B171,'xUS TME'!$B:$B,0)) -> 2.66 | N1553: =INDEX('xUS TME'!K:K,MATCH('xUS Opp Value'!$B171,'xUS TME'!$B:$B,0)) -> 0.15 | O1553: =INDEX('xUS TME'!I:I,MATCH('xUS Opp Value'!$B171,'xUS TME'!$B:$B,0)) -> 0 | P1553: =INDEX('xUS TME'!M:M,MATCH('xUS Opp Value'!$B171,'xUS TME'!$B:$B,0)) -> Euro | Q1553: =INDEX('xUS TME'!N:N,MATCH('xUS Opp Value'!$B1553,'xUS TME'!$B:$B,0)) -> High
A1554: JD.com Inc Ordinary Shares - Class A | B1554: =INDEX('xUS TME'!B:B,MATCH('xUS Opp Value'!A1554,'xUS TME'!A:A,0)) -> KYG8208B1014 | C1554: 9618 | D1554: =INDEX('xUS TME'!D:D,MATCH(B1554,'xUS TME'!$B:$B,0)) -> 0P0001K5SZ | E1554: =INDEX('xUS TME'!F:F,MATCH(B1554,'xUS TME'!$B:$B,0)) -> China | F1554: =INDEX('xUS TME'!G:G,MATCH(B1554,'xUS TME'!$B:$B,0)) -> Consumer Discretionary | G1554: =IFERROR(INDEX(CRIMs!G:G,MATCH(C1554,CRIMs!D:D,0)),0) -> 1 | H1554: =IFERROR(INDEX(CRIMs!I:I,MATCH(C1554,CRIMs!D:D,0)),0) -> 0.8960731 | I1554: =INDEX('xUS TME'!E:E,MATCH($B1554,'xUS TME'!$B:$B,0)) -> 0.11 | J1554: =INDEX('xUS TME'!H:H,MATCH(B1554,'xUS TME'!$B:$B,0)) -> 0.65 | K1554: =IFERROR((1/J1554)-1,"") -> 0.53846154 | L1554: =INDEX('xUS TME'!J:J,MATCH('xUS Opp Value'!B206,'xUS TME'!$B:$B,0)) -> 36.44 | M1554: =INDEX('xUS TME'!L:L,MATCH('xUS Opp Value'!$B206,'xUS TME'!$B:$B,0)) -> 1.89 | N1554: =INDEX('xUS TME'!K:K,MATCH('xUS Opp Value'!$B206,'xUS TME'!$B:$B,0)) -> 0.05 | O1554: =INDEX('xUS TME'!I:I,MATCH('xUS Opp Value'!$B206,'xUS TME'!$B:$B,0)) -> None | P1554: =INDEX('xUS TME'!M:M,MATCH('xUS Opp Value'!$B206,'xUS TME'!$B:$B,0)) -> Won | Q1554: =INDEX('xUS TME'!N:N,MATCH('xUS Opp Value'!$B1554,'xUS TME'!$B:$B,0)) -> High
A1555: Meituan Class B | B1555: =INDEX('xUS TME'!B:B,MATCH('xUS Opp Value'!A1555,'xUS TME'!A:A,0)) -> KYG596691041 | C1555: =INDEX('xUS TME'!C:C,MATCH($B1555,'xUS TME'!$B:$B,0)) -> 03690 | D1555: =INDEX('xUS TME'!D:D,MATCH(B1555,'xUS TME'!$B:$B,0)) -> 0P0001EHWO | E1555: =INDEX('xUS TME'!F:F,MATCH(B1555,'xUS TME'!$B:$B,0)) -> China | F1555: =INDEX('xUS TME'!G:G,MATCH(B1555,'xUS TME'!$B:$B,0)) -> Consumer Discretionary | G1555: =IFERROR(INDEX(CRIMs!G:G,MATCH(C1555,CRIMs!D:D,0)),0) -> 0 | H1555: =IFERROR(INDEX(CRIMs!I:I,MATCH(C1555,CRIMs!D:D,0)),0) -> 0 | I1555: =INDEX('xUS TME'!E:E,MATCH($B1555,'xUS TME'!$B:$B,0)) -> 0.17 | J1555: =INDEX('xUS TME'!H:H,MATCH(B1555,'xUS TME'!$B:$B,0)) -> 0.79 | K1555: =IFERROR((1/J1555)-1,"") -> 0.26582278 | L1555: =INDEX('xUS TME'!J:J,MATCH('xUS Opp Value'!B110,'xUS TME'!$B:$B,0)) -> 0 | M1555: =INDEX('xUS TME'!L:L,MATCH('xUS Opp Value'!$B110,'xUS TME'!$B:$B,0)) -> 1.43 | N1555: =INDEX('xUS TME'!K:K,MATCH('xUS Opp Value'!$B110,'xUS TME'!$B:$B,0)) -> 0.19 | O1555: =INDEX('xUS TME'!I:I,MATCH('xUS Opp Value'!$B110,'xUS TME'!$B:$B,0)) -> 0 | P1555: =INDEX('xUS TME'!M:M,MATCH('xUS Opp Value'!$B110,'xUS TME'!$B:$B,0)) -> UAE Dirham | Q1555: =INDEX('xUS TME'!N:N,MATCH('xUS Opp Value'!$B1555,'xUS TME'!$B:$B,0)) -> High
A1556: Adyen NV | B1556: =INDEX('xUS TME'!B:B,MATCH('xUS Opp Value'!A1556,'xUS TME'!A:A,0)) -> NL0012969182 | C1556: =INDEX('xUS TME'!C:C,MATCH($B1556,'xUS TME'!$B:$B,0)) -> ADYEN | D1556: =INDEX('xUS TME'!D:D,MATCH(B1556,'xUS TME'!$B:$B,0)) -> 0P0001DHJ2 | E1556: =INDEX('xUS TME'!F:F,MATCH(B1556,'xUS TME'!$B:$B,0)) -> Netherlands | F1556: =INDEX('xUS TME'!G:G,MATCH(B1556,'xUS TME'!$B:$B,0)) -> Financials | G1556: =IFERROR(INDEX(CRIMs!G:G,MATCH(C1556,CRIMs!D:D,0)),0) -> 0.5 | H1556: =IFERROR(INDEX(CRIMs!I:I,MATCH(C1556,CRIMs!D:D,0)),0) -> 0.30007898 | I1556: =INDEX('xUS TME'!E:E,MATCH($B1556,'xUS TME'!$B:$B,0)) -> 0.09 | J1556: =INDEX('xUS TME'!H:H,MATCH(B1556,'xUS TME'!$B:$B,0)) -> 0.53 | K1556: =IFERROR((1/J1556)-1,"") -> 0.88679245 | L1556: =INDEX('xUS TME'!J:J,MATCH('xUS Opp Value'!B174,'xUS TME'!$B:$B,0)) -> 0 | M1556: =INDEX('xUS TME'!L:L,MATCH('xUS Opp Value'!$B174,'xUS TME'!$B:$B,0)) -> 1.44 | N1556: =INDEX('xUS TME'!K:K,MATCH('xUS Opp Value'!$B174,'xUS TME'!$B:$B,0)) -> 0.08 | O1556: =INDEX('xUS TME'!I:I,MATCH('xUS Opp Value'!$B174,'xUS TME'!$B:$B,0)) -> 0 | P1556: =INDEX('xUS TME'!M:M,MATCH('xUS Opp Value'!$B174,'xUS TME'!$B:$B,0)) -> Yen | Q1556: =INDEX('xUS TME'!N:N,MATCH('xUS Opp Value'!$B1556,'xUS TME'!$B:$B,0)) -> High
A1557: Capgemini SE | B1557: =INDEX('xUS TME'!B:B,MATCH('xUS Opp Value'!A1557,'xUS TME'!A:A,0)) -> FR0000125338 | C1557: =INDEX('xUS TME'!C:C,MATCH($B1557,'xUS TME'!$B:$B,0)) -> CAP | D1557: =INDEX('xUS TME'!D:D,MATCH(B1557,'xUS TME'!$B:$B,0)) -> 0P00009WCN | E1557: =INDEX('xUS TME'!F:F,MATCH(B1557,'xUS TME'!$B:$B,0)) -> France | F1557: =INDEX('xUS TME'!G:G,MATCH(B1557,'xUS TME'!$B:$B,0)) -> Information Technology | G1557: =IFERROR(INDEX(CRIMs!G:G,MATCH(C1557,CRIMs!D:D,0)),0) -> 0.75 | H1557: =IFERROR(INDEX(CRIMs!I:I,MATCH(C1557,CRIMs!D:D,0)),0) -> 0 | I1557: =INDEX('xUS TME'!E:E,MATCH($B1557,'xUS TME'!$B:$B,0)) -> 0.06 | J1557: =INDEX('xUS TME'!H:H,MATCH(B1557,'xUS TME'!$B:$B,0)) -> 0.67 | K1557: =IFERROR((1/J1557)-1,"") -> 0.49253731 | L1557: =INDEX('xUS TME'!J:J,MATCH('xUS Opp Value'!B303,'xUS TME'!$B:$B,0)) -> 13.01 | M1557: =INDEX('xUS TME'!L:L,MATCH('xUS Opp Value'!$B303,'xUS TME'!$B:$B,0)) -> 2.64 | N1557: =INDEX('xUS TME'!K:K,MATCH('xUS Opp Value'!$B303,'xUS TME'!$B:$B,0)) -> 0.11 | O1557: =INDEX('xUS TME'!I:I,MATCH('xUS Opp Value'!$B303,'xUS TME'!$B:$B,0)) -> 0 | P1557: =INDEX('xUS TME'!M:M,MATCH('xUS Opp Value'!$B303,'xUS TME'!$B:$B,0)) -> Czech Koruna | Q1557: =INDEX('xUS TME'!N:N,MATCH('xUS Opp Value'!$B1557,'xUS TME'!$B:$B,0)) -> High
A1558: Geely Automobile Holdings Ltd | B1558: =INDEX('xUS TME'!B:B,MATCH('xUS Opp Value'!A1558,'xUS TME'!A:A,0)) -> KYG3777B1032 | C1558: =INDEX('xUS TME'!C:C,MATCH($B1558,'xUS TME'!$B:$B,0)) -> 175 | D1558: =INDEX('xUS TME'!D:D,MATCH(B1558,'xUS TME'!$B:$B,0)) -> 0P00009RSU | E1558: =INDEX('xUS TME'!F:F,MATCH(B1558,'xUS TME'!$B:$B,0)) -> China | F1558: =INDEX('xUS TME'!G:G,MATCH(B1558,'xUS TME'!$B:$B,0)) -> Consumer Discretionary | G1558: =IFERROR(INDEX(CRIMs!G:G,MATCH(C1558,CRIMs!D:D,0)),0) -> 0 | H1558: =IFERROR(INDEX(CRIMs!I:I,MATCH(C1558,CRIMs!D:D,0)),0) -> 0 | I1558: =INDEX('xUS TME'!E:E,MATCH($B1558,'xUS TME'!$B:$B,0)) -> 0.05 | J1558: =INDEX('xUS TME'!H:H,MATCH(B1558,'xUS TME'!$B:$B,0)) -> 0.96 | K1558: =IFERROR((1/J1558)-1,"") -> 0.041666667 | L1558: =INDEX('xUS TME'!J:J,MATCH('xUS Opp Value'!B573,'xUS TME'!$B:$B,0)) -> 30.3 | M1558: =INDEX('xUS TME'!L:L,MATCH('xUS Opp Value'!$B573,'xUS TME'!$B:$B,0)) -> 5.39 | N1558: =INDEX('xUS TME'!K:K,MATCH('xUS Opp Value'!$B573,'xUS TME'!$B:$B,0)) -> 0.19 | O1558: =INDEX('xUS TME'!I:I,MATCH('xUS Opp Value'!$B573,'xUS TME'!$B:$B,0)) -> 0 | P1558: =INDEX('xUS TME'!M:M,MATCH('xUS Opp Value'!$B573,'xUS TME'!$B:$B,0)) -> Indian Rupee | Q1558: =INDEX('xUS TME'!N:N,MATCH('xUS Opp Value'!$B1558,'xUS TME'!$B:$B,0)) -> High
A1559: Anhui Gujing Distillery Co Ltd Class A | B1559: =INDEX('xUS TME'!B:B,MATCH('xUS Opp Value'!A1559,'xUS TME'!A:A,0)) -> CNE000000MD5 | C1559: =INDEX('xUS TME'!C:C,MATCH($B1559,'xUS TME'!$B:$B,0)) -> 596 | D1559: =INDEX('xUS TME'!D:D,MATCH(B1559,'xUS TME'!$B:$B,0)) -> 0P00007WVC | E1559: =INDEX('xUS TME'!F:F,MATCH(B1559,'xUS TME'!$B:$B,0)) -> China | F1559: =INDEX('xUS TME'!G:G,MATCH(B1559,'xUS TME'!$B:$B,0)) -> Consumer Staples | G1559: =IFERROR(INDEX(CRIMs!G:G,MATCH(C1559,CRIMs!D:D,0)),0) -> 0 | H1559: =IFERROR(INDEX(CRIMs!I:I,MATCH(C1559,CRIMs!D:D,0)),0) -> 0 | I1559: =INDEX('xUS TME'!E:E,MATCH($B1559,'xUS TME'!$B:$B,0)) -> 0 | J1559: =INDEX('xUS TME'!H:H,MATCH(B1559,'xUS TME'!$B:$B,0)) -> 0.53 | K1559: =IFERROR((1/J1559)-1,"") -> 0.88679245 | L1559: =INDEX('xUS TME'!J:J,MATCH('xUS Opp Value'!B1854,'xUS TME'!$B:$B,0)) -> 11.24 | M1559: =INDEX('xUS TME'!L:L,MATCH('xUS Opp Value'!$B1854,'xUS TME'!$B:$B,0)) -> 1.11 | N1559: =INDEX('xUS TME'!K:K,MATCH('xUS Opp Value'!$B1854,'xUS TME'!$B:$B,0)) -> 0.14 | O1559: =INDEX('xUS TME'!I:I,MATCH('xUS Opp Value'!$B1854,'xUS TME'!$B:$B,0)) -> None | P1559: =INDEX('xUS TME'!M:M,MATCH('xUS Opp Value'!$B1854,'xUS TME'!$B:$B,0)) -> Yen | Q1559: =INDEX('xUS TME'!N:N,MATCH('xUS Opp Value'!$B1559,'xUS TME'!$B:$B,0)) -> High
A1560: SF Holding Co Ltd Ordinary Shares - Class H | B1560: =INDEX('xUS TME'!B:B,MATCH('xUS Opp Value'!A1560,'xUS TME'!A:A,0)) -> CNE100006NF4 | C1560: =INDEX('xUS TME'!C:C,MATCH($B1560,'xUS TME'!$B:$B,0)) -> 6936 | D1560: =INDEX('xUS TME'!D:D,MATCH(B1560,'xUS TME'!$B:$B,0)) -> 0P0001U5L6 | E1560: =INDEX('xUS TME'!F:F,MATCH(B1560,'xUS TME'!$B:$B,0)) -> China | F1560: =INDEX('xUS TME'!G:G,MATCH(B1560,'xUS TME'!$B:$B,0)) -> Industrials | G1560: =IFERROR(INDEX(CRIMs!G:G,MATCH(C1560,CRIMs!D:D,0)),0) -> 0 | H1560: =IFERROR(INDEX(CRIMs!I:I,MATCH(C1560,CRIMs!D:D,0)),0) -> 0 | I1560: =INDEX('xUS TME'!E:E,MATCH($B1560,'xUS TME'!$B:$B,0)) -> 0 | J1560: =INDEX('xUS TME'!H:H,MATCH(B1560,'xUS TME'!$B:$B,0)) -> 0.6 | K1560: =IFERROR((1/J1560)-1,"") -> 0.66666667 | L1560: =INDEX('xUS TME'!J:J,MATCH('xUS Opp Value'!B1863,'xUS TME'!$B:$B,0)) -> 6.51 | M1560: =INDEX('xUS TME'!L:L,MATCH('xUS Opp Value'!$B1863,'xUS TME'!$B:$B,0)) -> 1.23 | N1560: =INDEX('xUS TME'!K:K,MATCH('xUS Opp Value'!$B1863,'xUS TME'!$B:$B,0)) -> 0.19 | O1560: =INDEX('xUS TME'!I:I,MATCH('xUS Opp Value'!$B1863,'xUS TME'!$B:$B,0)) -> None | P1560: =INDEX('xUS TME'!M:M,MATCH('xUS Opp Value'!$B1863,'xUS TME'!$B:$B,0)) -> Yuan Renminbi | Q1560: =INDEX('xUS TME'!N:N,MATCH('xUS Opp Value'!$B1560,'xUS TME'!$B:$B,0)) -> High
A1561: Kuaishou Technology Ordinary Shares - Class B | B1561: =INDEX('xUS TME'!B:B,MATCH('xUS Opp Value'!A1561,'xUS TME'!A:A,0)) -> KYG532631028 | C1561: =INDEX('xUS TME'!C:C,MATCH($B1561,'xUS TME'!$B:$B,0)) -> 1024 | D1561: =INDEX('xUS TME'!D:D,MATCH(B1561,'xUS TME'!$B:$B,0)) -> 0P0001LL6L | E1561: =INDEX('xUS TME'!F:F,MATCH(B1561,'xUS TME'!$B:$B,0)) -> China | F1561: =INDEX('xUS TME'!G:G,MATCH(B1561,'xUS TME'!$B:$B,0)) -> Communication Services | G1561: =IFERROR(INDEX(CRIMs!G:G,MATCH(C1561,CRIMs!D:D,0)),0) -> 0 | H1561: =IFERROR(INDEX(CRIMs!I:I,MATCH(C1561,CRIMs!D:D,0)),0) -> 0 | I1561: =INDEX('xUS TME'!E:E,MATCH($B1561,'xUS TME'!$B:$B,0)) -> 0.05 | J1561: =INDEX('xUS TME'!H:H,MATCH(B1561,'xUS TME'!$B:$B,0)) -> 0.49 | K1561: =IFERROR((1/J1561)-1,"") -> 1.0408163 | L1561: =INDEX('xUS TME'!J:J,MATCH('xUS Opp Value'!B271,'xUS TME'!$B:$B,0)) -> 9.28 | M1561: =INDEX('xUS TME'!L:L,MATCH('xUS Opp Value'!$B271,'xUS TME'!$B:$B,0)) -> 1.2 | N1561: =INDEX('xUS TME'!K:K,MATCH('xUS Opp Value'!$B271,'xUS TME'!$B:$B,0)) -> 0 | O1561: =INDEX('xUS TME'!I:I,MATCH('xUS Opp Value'!$B271,'xUS TME'!$B:$B,0)) -> 0 | P1561: =INDEX('xUS TME'!M:M,MATCH('xUS Opp Value'!$B271,'xUS TME'!$B:$B,0)) -> Won | Q1561: =INDEX('xUS TME'!N:N,MATCH('xUS Opp Value'!$B1561,'xUS TME'!$B:$B,0)) -> Very High
A1562: Universal Music Group NV | B1562: =INDEX('xUS TME'!B:B,MATCH('xUS Opp Value'!A1562,'xUS TME'!A:A,0)) -> NL0015000IY2 | C1562: =INDEX('xUS TME'!C:C,MATCH($B1562,'xUS TME'!$B:$B,0)) -> UMG | D1562: =INDEX('xUS TME'!D:D,MATCH(B1562,'xUS TME'!$B:$B,0)) -> 0P0001NBPU | E1562: =INDEX('xUS TME'!F:F,MATCH(B1562,'xUS TME'!$B:$B,0)) -> Netherlands | F1562: =INDEX('xUS TME'!G:G,MATCH(B1562,'xUS TME'!$B:$B,0)) -> Communication Services | G1562: =IFERROR(INDEX(CRIMs!G:G,MATCH(C1562,CRIMs!D:D,0)),0) -> 0.5 | H1562: =IFERROR(INDEX(CRIMs!I:I,MATCH(C1562,CRIMs!D:D,0)),0) -> 0.45611446 | I1562: =INDEX('xUS TME'!E:E,MATCH($B1562,'xUS TME'!$B:$B,0)) -> 0.06 | J1562: =INDEX('xUS TME'!H:H,MATCH(B1562,'xUS TME'!$B:$B,0)) -> 0.63 | K1562: =IFERROR((1/J1562)-1,"") -> 0.58730159 | L1562: =INDEX('xUS TME'!J:J,MATCH('xUS Opp Value'!B348,'xUS TME'!$B:$B,0)) -> 0 | M1562: =INDEX('xUS TME'!L:L,MATCH('xUS Opp Value'!$B348,'xUS TME'!$B:$B,0)) -> 1.14 | N1562: =INDEX('xUS TME'!K:K,MATCH('xUS Opp Value'!$B348,'xUS TME'!$B:$B,0)) -> 0.1 | O1562: =INDEX('xUS TME'!I:I,MATCH('xUS Opp Value'!$B348,'xUS TME'!$B:$B,0)) -> 0 | P1562: =INDEX('xUS TME'!M:M,MATCH('xUS Opp Value'!$B348,'xUS TME'!$B:$B,0)) -> Yen | Q1562: =INDEX('xUS TME'!N:N,MATCH('xUS Opp Value'!$B1562,'xUS TME'!$B:$B,0)) -> Medium
A1563: Coloplast AS Class B | B1563: =INDEX('xUS TME'!B:B,MATCH('xUS Opp Value'!A1563,'xUS TME'!A:A,0)) -> DK0060448595 | C1563: =INDEX('xUS TME'!C:C,MATCH($B1563,'xUS TME'!$B:$B,0)) -> COLO B | D1563: =INDEX('xUS TME'!D:D,MATCH(B1563,'xUS TME'!$B:$B,0)) -> 0P0000A5K4 | E1563: =INDEX('xUS TME'!F:F,MATCH(B1563,'xUS TME'!$B:$B,0)) -> Denmark | F1563: =INDEX('xUS TME'!G:G,MATCH(B1563,'xUS TME'!$B:$B,0)) -> Health Care | G1563: =IFERROR(INDEX(CRIMs!G:G,MATCH(C1563,CRIMs!D:D,0)),0) -> 0.75 | H1563: =IFERROR(INDEX(CRIMs!I:I,MATCH(C1563,CRIMs!D:D,0)),0) -> 0.55676722 | I1563: =INDEX('xUS TME'!E:E,MATCH($B1563,'xUS TME'!$B:$B,0)) -> 0.03 | J1563: =INDEX('xUS TME'!H:H,MATCH(B1563,'xUS TME'!$B:$B,0)) -> 0.56 | K1563: =IFERROR((1/J1563)-1,"") -> 0.78571429 | L1563: =INDEX('xUS TME'!J:J,MATCH('xUS Opp Value'!B601,'xUS TME'!$B:$B,0)) -> 6.82 | M1563: =INDEX('xUS TME'!L:L,MATCH('xUS Opp Value'!$B601,'xUS TME'!$B:$B,0)) -> 0.92 | N1563: =INDEX('xUS TME'!K:K,MATCH('xUS Opp Value'!$B601,'xUS TME'!$B:$B,0)) -> 0.26 | O1563: =INDEX('xUS TME'!I:I,MATCH('xUS Opp Value'!$B601,'xUS TME'!$B:$B,0)) -> 0 | P1563: =INDEX('xUS TME'!M:M,MATCH('xUS Opp Value'!$B601,'xUS TME'!$B:$B,0)) -> Hong Kong Dollar | Q1563: =INDEX('xUS TME'!N:N,MATCH('xUS Opp Value'!$B1563,'xUS TME'!$B:$B,0)) -> Medium
A1564: Luzhou Laojiao Co Ltd Class A | B1564: =INDEX('xUS TME'!B:B,MATCH('xUS Opp Value'!A1564,'xUS TME'!A:A,0)) -> CNE000000GF2 | C1564: =INDEX('xUS TME'!C:C,MATCH($B1564,'xUS TME'!$B:$B,0)) -> 568 | D1564: =INDEX('xUS TME'!D:D,MATCH(B1564,'xUS TME'!$B:$B,0)) -> 0P00007WUR | E1564: =INDEX('xUS TME'!F:F,MATCH(B1564,'xUS TME'!$B:$B,0)) -> China | F1564: =INDEX('xUS TME'!G:G,MATCH(B1564,'xUS TME'!$B:$B,0)) -> Consumer Staples | G1564: =IFERROR(INDEX(CRIMs!G:G,MATCH(C1564,CRIMs!D:D,0)),0) -> 0 | H1564: =IFERROR(INDEX(CRIMs!I:I,MATCH(C1564,CRIMs!D:D,0)),0) -> 0 | I1564: =INDEX('xUS TME'!E:E,MATCH($B1564,'xUS TME'!$B:$B,0)) -> 0.01 | J1564: =INDEX('xUS TME'!H:H,MATCH(B1564,'xUS TME'!$B:$B,0)) -> 0.58 | K1564: =IFERROR((1/J1564)-1,"") -> 0.72413793 | L1564: =INDEX('xUS TME'!J:J,MATCH('xUS Opp Value'!B1498,'xUS TME'!$B:$B,0)) -> 0 | M1564: =INDEX('xUS TME'!L:L,MATCH('xUS Opp Value'!$B1498,'xUS TME'!$B:$B,0)) -> 1.13 | N1564: =INDEX('xUS TME'!K:K,MATCH('xUS Opp Value'!$B1498,'xUS TME'!$B:$B,0)) -> 0.11 | O1564: =INDEX('xUS TME'!I:I,MATCH('xUS Opp Value'!$B1498,'xUS TME'!$B:$B,0)) -> 0 | P1564: =INDEX('xUS TME'!M:M,MATCH('xUS Opp Value'!$B1498,'xUS TME'!$B:$B,0)) -> Yuan Renminbi | Q1564: =INDEX('xUS TME'!N:N,MATCH('xUS Opp Value'!$B1564,'xUS TME'!$B:$B,0)) -> Medium
A1565: SAP SE | B1565: =INDEX('xUS TME'!B:B,MATCH('xUS Opp Value'!A1565,'xUS TME'!A:A,0)) -> DE0007164600 | C1565: =INDEX('xUS TME'!C:C,MATCH($B1565,'xUS TME'!$B:$B,0)) -> SAP | D1565: =INDEX('xUS TME'!D:D,MATCH(B1565,'xUS TME'!$B:$B,0)) -> 0P00009QRW | E1565: =INDEX('xUS TME'!F:F,MATCH(B1565,'xUS TME'!$B:$B,0)) -> Germany | F1565: =INDEX('xUS TME'!G:G,MATCH(B1565,'xUS TME'!$B:$B,0)) -> Information Technology | G1565: =IFERROR(INDEX(CRIMs!G:G,MATCH(C1565,CRIMs!D:D,0)),0) -> 0.5 | H1565: =IFERROR(INDEX(CRIMs!I:I,MATCH(C1565,CRIMs!D:D,0)),0) -> 0.99460378 | I1565: =INDEX('xUS TME'!E:E,MATCH($B1565,'xUS TME'!$B:$B,0)) -> 0.53 | J1565: =INDEX('xUS TME'!H:H,MATCH(B1565,'xUS TME'!$B:$B,0)) -> 0.53 | K1565: =IFERROR((1/J1565)-1,"") -> 0.88679245 | L1565: =INDEX('xUS TME'!J:J,MATCH('xUS Opp Value'!B19,'xUS TME'!$B:$B,0)) -> 14.93 | M1565: =INDEX('xUS TME'!L:L,MATCH('xUS Opp Value'!$B19,'xUS TME'!$B:$B,0)) -> 2.92 | N1565: =INDEX('xUS TME'!K:K,MATCH('xUS Opp Value'!$B19,'xUS TME'!$B:$B,0)) -> 0.12 | O1565: =INDEX('xUS TME'!I:I,MATCH('xUS Opp Value'!$B19,'xUS TME'!$B:$B,0)) -> 0 | P1565: =INDEX('xUS TME'!M:M,MATCH('xUS Opp Value'!$B19,'xUS TME'!$B:$B,0)) -> Yen | Q1565: =INDEX('xUS TME'!N:N,MATCH('xUS Opp Value'!$B1565,'xUS TME'!$B:$B,0)) -> Medium
A1566: Barratt Redrow PLC | B1566: =INDEX('xUS TME'!B:B,MATCH('xUS Opp Value'!A1566,'xUS TME'!A:A,0)) -> GB0000811801 | C1566: =INDEX('xUS TME'!C:C,MATCH($B1566,'xUS TME'!$B:$B,0)) -> BTRW | D1566: =INDEX('xUS TME'!D:D,MATCH(B1566,'xUS TME'!$B:$B,0)) -> 0P00007NZR | E1566: =INDEX('xUS TME'!F:F,MATCH(B1566,'xUS TME'!$B:$B,0)) -> United Kingdom | F1566: =INDEX('xUS TME'!G:G,MATCH(B1566,'xUS TME'!$B:$B,0)) -> Consumer Discretionary | G1566: =IFERROR(INDEX(CRIMs!G:G,MATCH(C1566,CRIMs!D:D,0)),0) -> 0 | H1566: =IFERROR(INDEX(CRIMs!I:I,MATCH(C1566,CRIMs!D:D,0)),0) -> 0 | I1566: =INDEX('xUS TME'!E:E,MATCH($B1566,'xUS TME'!$B:$B,0)) -> 0.01 | J1566: =INDEX('xUS TME'!H:H,MATCH(B1566,'xUS TME'!$B:$B,0)) -> 0.5 | K1566: =IFERROR((1/J1566)-1,"") -> 1 | L1566: =INDEX('xUS TME'!J:J,MATCH('xUS Opp Value'!B903,'xUS TME'!$B:$B,0)) -> 0 | M1566: =INDEX('xUS TME'!L:L,MATCH('xUS Opp Value'!$B903,'xUS TME'!$B:$B,0)) -> 3.68 | N1566: =INDEX('xUS TME'!K:K,MATCH('xUS Opp Value'!$B903,'xUS TME'!$B:$B,0)) -> 0.16 | O1566: =INDEX('xUS TME'!I:I,MATCH('xUS Opp Value'!$B903,'xUS TME'!$B:$B,0)) -> 0 | P1566: =INDEX('xUS TME'!M:M,MATCH('xUS Opp Value'!$B903,'xUS TME'!$B:$B,0)) -> Hong Kong Dollar | Q1566: =INDEX('xUS TME'!N:N,MATCH('xUS Opp Value'!$B1566,'xUS TME'!$B:$B,0)) -> High
A1567: Thomson Reuters Corp | B1567: =INDEX('xUS TME'!B:B,MATCH('xUS Opp Value'!A1567,'xUS TME'!A:A,0)) -> CA8849038085 | C1567: =INDEX('xUS TME'!C:C,MATCH($B1567,'xUS TME'!$B:$B,0)) -> TRI | D1567: =INDEX('xUS TME'!D:D,MATCH(B1567,'xUS TME'!$B:$B,0)) -> 0P00006896 | E1567: =INDEX('xUS TME'!F:F,MATCH(B1567,'xUS TME'!$B:$B,0)) -> Canada | F1567: =INDEX('xUS TME'!G:G,MATCH(B1567,'xUS TME'!$B:$B,0)) -> Industrials | G1567: =IFERROR(INDEX(CRIMs!G:G,MATCH(C1567,CRIMs!D:D,0)),0) -> 0 | H1567: =IFERROR(INDEX(CRIMs!I:I,MATCH(C1567,CRIMs!D:D,0)),0) -> 0 | I1567: =INDEX('xUS TME'!E:E,MATCH($B1567,'xUS TME'!$B:$B,0)) -> 0.04 | J1567: =INDEX('xUS TME'!H:H,MATCH(B1567,'xUS TME'!$B:$B,0)) -> 0.6 | K1567: =IFERROR((1/J1567)-1,"") -> 0.66666667 | L1567: =INDEX('xUS TME'!J:J,MATCH('xUS Opp Value'!B501,'xUS TME'!$B:$B,0)) -> 0 | M1567: =INDEX('xUS TME'!L:L,MATCH('xUS Opp Value'!$B501,'xUS TME'!$B:$B,0)) -> 2.08 | N1567: =INDEX('xUS TME'!K:K,MATCH('xUS Opp Value'!$B501,'xUS TME'!$B:$B,0)) -> 0.12 | O1567: =INDEX('xUS TME'!I:I,MATCH('xUS Opp Value'!$B501,'xUS TME'!$B:$B,0)) -> 0 | P1567: =INDEX('xUS TME'!M:M,MATCH('xUS Opp Value'!$B501,'xUS TME'!$B:$B,0)) -> Saudi Riyal | Q1567: =INDEX('xUS TME'!N:N,MATCH('xUS Opp Value'!$B1567,'xUS TME'!$B:$B,0)) -> Medium
A1568: JD Logistics Inc | B1568: =INDEX('xUS TME'!B:B,MATCH('xUS Opp Value'!A1568,'xUS TME'!A:A,0)) -> KYG5074S1012 | C1568: =INDEX('xUS TME'!C:C,MATCH($B1568,'xUS TME'!$B:$B,0)) -> 02618 | D1568: =INDEX('xUS TME'!D:D,MATCH(B1568,'xUS TME'!$B:$B,0)) -> 0P0001MHR7 | E1568: =INDEX('xUS TME'!F:F,MATCH(B1568,'xUS TME'!$B:$B,0)) -> China | F1568: =INDEX('xUS TME'!G:G,MATCH(B1568,'xUS TME'!$B:$B,0)) -> Industrials | G1568: =IFERROR(INDEX(CRIMs!G:G,MATCH(C1568,CRIMs!D:D,0)),0) -> 0 | H1568: =IFERROR(INDEX(CRIMs!I:I,MATCH(C1568,CRIMs!D:D,0)),0) -> 0 | I1568: =INDEX('xUS TME'!E:E,MATCH($B1568,'xUS TME'!$B:$B,0)) -> 0.01 | J1568: =INDEX('xUS TME'!H:H,MATCH(B1568,'xUS TME'!$B:$B,0)) -> 0.83 | K1568: =IFERROR((1/J1568)-1,"") -> 0.20481928 | L1568: =INDEX('xUS TME'!J:J,MATCH('xUS Opp Value'!B1291,'xUS TME'!$B:$B,0)) -> 0 | M1568: =INDEX('xUS TME'!L:L,MATCH('xUS Opp Value'!$B1291,'xUS TME'!$B:$B,0)) -> 3.8 | N1568: =INDEX('xUS TME'!K:K,MATCH('xUS Opp Value'!$B1291,'xUS TME'!$B:$B,0)) -> -0.21 | O1568: =INDEX('xUS TME'!I:I,MATCH('xUS Opp Value'!$B1291,'xUS TME'!$B:$B,0)) -> Narrow | P1568: =INDEX('xUS TME'!M:M,MATCH('xUS Opp Value'!$B1291,'xUS TME'!$B:$B,0)) -> Hong Kong Dollar | Q1568: =INDEX('xUS TME'!N:N,MATCH('xUS Opp Value'!$B1568,'xUS TME'!$B:$B,0)) -> High
A1569: TELUS Corp | B1569: =INDEX('xUS TME'!B:B,MATCH('xUS Opp Value'!A1569,'xUS TME'!A:A,0)) -> CA87971M1032 | C1569: =INDEX('xUS TME'!C:C,MATCH($B1569,'xUS TME'!$B:$B,0)) -> T | D1569: =INDEX('xUS TME'!D:D,MATCH(B1569,'xUS TME'!$B:$B,0)) -> 0P00006893 | E1569: =INDEX('xUS TME'!F:F,MATCH(B1569,'xUS TME'!$B:$B,0)) -> Canada | F1569: =INDEX('xUS TME'!G:G,MATCH(B1569,'xUS TME'!$B:$B,0)) -> Communication Services | G1569: =IFERROR(INDEX(CRIMs!G:G,MATCH(C1569,CRIMs!D:D,0)),0) -> 0 | H1569: =IFERROR(INDEX(CRIMs!I:I,MATCH(C1569,CRIMs!D:D,0)),0) -> 0 | I1569: =INDEX('xUS TME'!E:E,MATCH($B1569,'xUS TME'!$B:$B,0)) -> 0.02 | J1569: =INDEX('xUS TME'!H:H,MATCH(B1569,'xUS TME'!$B:$B,0)) -> 0.55 | K1569: =IFERROR((1/J1569)-1,"") -> 0.81818182 | L1569: =INDEX('xUS TME'!J:J,MATCH('xUS Opp Value'!B879,'xUS TME'!$B:$B,0)) -> 0 | M1569: =INDEX('xUS TME'!L:L,MATCH('xUS Opp Value'!$B879,'xUS TME'!$B:$B,0)) -> 6 | N1569: =INDEX('xUS TME'!K:K,MATCH('xUS Opp Value'!$B879,'xUS TME'!$B:$B,0)) -> 0.14 | O1569: =INDEX('xUS TME'!I:I,MATCH('xUS Opp Value'!$B879,'xUS TME'!$B:$B,0)) -> 0 | P1569: =INDEX('xUS TME'!M:M,MATCH('xUS Opp Value'!$B879,'xUS TME'!$B:$B,0)) -> Indian Rupee | Q1569: =INDEX('xUS TME'!N:N,MATCH('xUS Opp Value'!$B1569,'xUS TME'!$B:$B,0)) -> Low
...

Sheet CRIMs
A1: Account View
A2: Security | D2: Ticker | E2: Price | F2: Status Text | G2: Tgt % | H2: Min % | I2: Pre-Trd Exp % | J2: Max % | K2: Pre-Trd Exp % | L2: Pre-Trd Var % | M2: Pre-Trd AUM, $ | N2: F | O2: Post-Trd Exp % | P2: Post-Trd Var % | Q2: Post-Trd AUM, $ | R2: Trade $ | S2: Limit Price | T2: Trd % of Fund | U2: Trd % of Cash | V2: Trd Shares | W2: Post-Trd $ | X2: Exchange | Y2: Price | AC2: Overrides | AD2: Ticker
A3: INTL EQ - Global Ex US Opportunistic Value | G3: 100 | I3: 100 | K3: 100 | L3: 0 | M3: 2.6292322e+08 | O3: 100 | P3: - | Q3: 2.6292322e+08 | R3: 0 | T3: 0 | U3: 0 | V3: 2400000 | W3: 2400000 | AC3: AMERICA MOVIL SAB DE CV COM SER 'B' NPV | AD3: AMXB
B4: Cash | G4: 1 | I4: 0.27 | K4: 0.27 | L4: -0.73 | M4: 714281.32 | O4: 0.27 | P4: -0.73 | Q4: 714281.32 | R4: 0 | T4: 0 | U4: 0 | V4: 2400000 | W4: 2400000 | AC4: FOMENTO ECONOMICO MEXICANO SAB DE C UNITS (REP 1'B'& 4'D' SHS) | AD4: FEMSAUBD
B5: Investments | G5: 99 | I5: 99.73 | K5: 99.73 | L5: 0.73 | M5: 2.6220894e+08 | O5: 99.73 | P5: 0.73 | Q5: 2.6220894e+08 | R5: 0 | T5: 0 | U5: 0 | V5: 0 | W5: 0 | AC5: GRUPO FINANCIERO BANORTE COM NPV SERIES O | AD5: GFNORTEO | AL5: ADYEN NV EUR0.01 | AM5: ADYEN | AN5: =AT5=AM5 -> TRUE | AP5: Adyen NV | AQ5: ADYEN | AS5: Adyen NV | AT5: ADYEN | AU5: 0.5 | AW5: NOVO NORDISK A/S SER'B'DKK0.1 | AX5: NOVO B | AY5: 249.8 | BA5: 1 | BC5: 0.6904204
C6: ADVANTEST CORP NPV | D6: 6857 | E6: 17925 | I6: 0 | J6: -0.36444518 | K6: 0.42 | L6: -0.08 | M6: 1097566.4 | O6: 0.42 | P6: -0.08 | Q6: 1097566.4 | R6: 0 | T6: 0 | U6: 0 | V6: 0 | W6: 0 | X6: AMS | Y6: 1353 | AC6: NAVER CORP KRW100 | AD6: 35420 | AL6: AIA GROUP LIMITED NPV | AM6: 1299 | AN6: =AT6=AM6 -> TRUE | AP6: AIA Group Ltd | AQ6: 1299 | AS6: AIA Group Ltd | AT6: 1299 | AU6: 1.25 | AW6: NEXI SPA NPV | AX6: NEXI | AY6: 3.02 | BA6: 0.75 | BC6: 0.46469446
C7: ADYEN NV EUR0.01 | D7: ADYEN | E7: 858.8 | G7: 0.5 | I7: 0.30007898 | J7: -0.3451257 | K7: 1.19 | L7: -0.06 | M7: 3129513.9 | O7: 1.19 | P7: -0.06 | Q7: 3129513.9 | R7: 0 | T7: 0 | U7: 0 | V7: 0 | W7: 0 | X7: HKG | Y7: 71.7 | AC7: SAMSUNG ELECTRONICS CO KRW100 | AD7: 5930 | AL7: AKZO NOBEL NV EUR0.50(POST REV SPLIT) | AM7: AKZA | AN7: =AT7=AM7 -> TRUE | AP7: Akzo Nobel NV | AQ7: AKZA | AS7: Akzo Nobel NV | AT7: AKZA | AU7: 0.5 | AW7: ADYEN NV EUR0.01 | AX7: ADYEN | AY7: 926.5 | BA7: 0.5 | BC7: 0.32603709
C8: AIA GROUP LTD NPV | D8: 1299 | E8: 88.95 | G8: 1.25 | I8: 1.2737969 | J8: -0.28085947 | K8: 0.46 | L8: -0.04 | M8: 1207254.8 | O8: 0.46 | P8: -0.04 | Q8: 1207254.8 | R8: 0 | T8: 0 | U8: 0 | V8: 0 | W8: 0 | X8: AMS | Y8: 60.34 | AC8: SK HYNIX INC KRW5000 | AD8: 660 | AL8: ALCON AG CHF0.04 | AM8: ALC | AN8: =AT8=AM8 -> TRUE | AP8: Alcon Inc | AQ8: ALC | AS8: Alcon Inc | AT8: ALC | AU8: 0.5 | AW8: AIA GROUP LIMITED NPV | AX8: 1299 | AY8: 86.45 | BA8: 1.25 | BC8: 1.264114
C9: AKZO NOBEL NV EUR0.50(POST REV SPLIT) | D9: AKZA | E9: 52.12 | G9: 0.5 | I9: 0.4051121 | J9: -0.23077977 | K9: 0.47 | L9: -0.03 | M9: 1228070.2 | O9: 0.47 | P9: -0.03 | Q9: 1228070.2 | R9: 0 | T9: 0 | U9: 0 | V9: 0 | W9: 0 | X9: SWX | Y9: 58.94 | AC9: WAL-MART DE MEXICO SAB DE CV COM NPV | AD9: WALMEX | AL9: ALIBABA GROUP HOLDING LTD USD0.000003125 | AM9: 9988 | AN9: =AT9=AM9 -> TRUE | AP9: Alibaba Group Holding Ltd Ordinary Shares | AQ9: 9988 | AS9: Alibaba Group Holding Ltd Ordinary Shares | AT9: 9988 | AU9: 1.75 | AW9: AKZO NOBEL NV EUR0.50(POST REV SPLIT) | AX9: AKZA | AY9: 52 | BA9: 0.5 | BC9: 0.40705416
C10: ALCON AG CHF0.04 | D10: ALC | E10: 61.6 | G10: 0.5 | I10: 0.47299925 | J10: -0.18002009 | K10: 1.52 | L10: -0.23 | M10: 4003566.4 | O10: 1.52 | P10: -0.23 | Q10: 4003566.4 | R10: 0 | T10: 0 | U10: 0 | V10: 0 | W10: 0 | X10: HKG | Y10: 166.5 | AC10: WOORI FINANCIAL GROUP INC KRW5000 | AD10: 316140 | AL10: AMBEV SA COM NPV | AM10: ABEV3 | AN10: =AT10=AM10 -> TRUE | AP10: Ambev SA | AQ10: ABEV3 | AS10: Ambev SA | AT10: ABEV3 | AU10: 1.25 | AW10: ALCON AG CHF0.04 | AX10: ALC | AY10: 62.56 | BA10: 0.5 | BC10: 0.49537571
C11: ALIBABA GROUP HLDG USD0.000003125 | D11: 9988 | E11: 125.5 | G11: 2 | I11: 2.0253896 | J11: -0.17297054 | K11: 1.35 | L11: 0.1 | M11: 3537739.2 | O11: 1.35 | P11: 0.1 | Q11: 3537739.2 | R11: 0 | T11: 0 | U11: 0 | V11: 0 | W11: 0 | X11: BVMF | Y11: 12.46 | AC11: Sonic Healthcare Ltd | AD11: SKHCF | AE11: CHANGE IN MAIN SHEET | AL11: AMERICA MOVIL SAB DE CV COM SER 'B' NPV | AM11: AMXB | AN11: =AT11=AM11 -> TRUE | AP11: America Movil SAB de CV Ordinary Shares - Class B | AQ11: AMXB | AS11: America Movil SAB de CV Ordinary Shares - Class B | AT11: AMXB | AU11: 0.5 | AW11: ALIBABA GROUP HOLDING LTD USD0.000003125 | AX11: 9988 | AY11: 133.2 | BA11: 1.75 | BC11: 1.6678824
C12: AMBEV SA COM NPV | D12: ABEV3 | E12: 16.12 | G12: 1.25 | I12: 1.4736183 | J12: -0.17041907 | K12: 0.51 | L12: 0.01 | M12: 1352654 | O12: 0.51 | P12: 0.01 | Q12: 1352654 | R12: 0 | T12: 0 | U12: 0 | V12: 0 | W12: 0 | X12: MEX | Y12: 19.13 | AC12: Midea | AD12: 333 | AL12: ANZ GROUP HOLDINGS LIMITED NPV | AM12: ANZ | AN12: =AT12=AM12 -> TRUE | AP12: ANZ Group Holdings Ltd | AQ12: ANZ | AS12: ANZ Group Holdings Ltd | AT12: ANZ | AU12: 0.5 | AW12: AMBEV SA COM NPV | AX12: ABEV3 | AY12: 15.43 | BA12: 1.25 | BC12: 1.4014753
C13: AMERICA MOVIL SAB COM SER 'B' NPV | D13: AMXB | E13: 23.58 | G13: 0.5 | I13: 0.64542459 | J13: -0.16867132 | K13: 0.56 | L13: 0.06 | M13: 1464453.4 | O13: 0.56 | P13: 0.06 | Q13: 1464453.4 | R13: 0 | T13: 0 | U13: 0 | V13: 0 | W13: 0 | X13: ASX | Y13: 33.39 | AL13: ASM INTERNATIONAL NV EUR0.04 | AM13: ASM | AN13: =AT13=AM13 -> TRUE | AP13: ASM International NV | AQ13: ASM | AS13: ASM International NV | AT13: ASM | AU13: 0.75 | AW13: AMERICA MOVIL SAB DE CV COM SER 'B' NPV | AX13: AMXB | AY13: 20.96 | BA13: 0.5 | BC13: 0.57347817
C14: ANZ GROUP HLDGS LI NPV | D14: ANZ | E14: 38.84 | G14: 0.5 | I14: 0.59911795 | J14: -0.16777091 | K14: 0.69 | L14: -0.06 | M14: 1817359.2 | O14: 0.69 | P14: -0.06 | Q14: 1817359.2 | R14: 0 | T14: 0 | U14: 0 | V14: 0 | W14: 0 | X14: LSE | Y14: 49.99 | AL14: ASML HOLDING NV EUR0.09 | AM14: ASML | AN14: =AT14=AM14 -> TRUE | AP14: ASML Holding NV | AQ14: ASML | AS14: ASML Holding NV | AT14: ASML | AU14: 2 | AW14: ANZ GROUP HOLDINGS LIMITED NPV | AX14: ANZ | AY14: 37.02 | BA14: 0.5 | BC14: 0.58889945
C15: ASM INTL NV EUR0.04 | D15: ASM | E15: 757.8 | G15: 0.75 | I15: 0.800635 | J15: -0.15098721 | K15: 0.73 | L15: -0.02 | M15: 1906647.1 | O15: 0.73 | P15: -0.02 | Q15: 1906647.1 | R15: 0 | T15: 0 | U15: 0 | V15: 0 | W15: 0 | X15: AMS | Y15: 812.8 | AC15: Change in Main Cheet | AL15: ASX LTD NPV | AM15: ASX | AN15: =AT15=AM15 -> TRUE | AP15: ASX Ltd | AQ15: ASX | AS15: ASX Ltd | AT15: ASX | AU15: 0.5 | AW15: ASM INTERNATIONAL NV EUR0.04 | AX15: ASM | AY15: 722.2 | BA15: 0.75 | BC15: 0.7684498
C16: ASML HOLDING NV EUR0.09 | D16: ASML | E16: 1270 | G16: 2 | I16: 2.0080099 | J16: -0.14234123 | K16: 1.88 | L16: -0.12 | M16: 4941077.8 | O16: 1.88 | P16: -0.12 | Q16: 4941077.8 | R16: 0 | T16: 0 | U16: 0 | V16: 0 | W16: 0 | X16: ASX | Y16: 58.71 | AC16: Elm co (7203) | AL16: B3 SA - BRASIL BOLSA BALCAO COM NPV | AM16: B3SA3 | AN16: =AT16=AM16 -> TRUE | AP16: B3 SA - Brasil Bolsa Balcao | AQ16: B3SA3 | AS16: B3 SA - Brasil Bolsa Balcao | AT16: B3SA3 | AU16: 0.75 | AW16: ASML HOLDING NV EUR0.09 | AX16: ASML | AY16: 1198.8 | BA16: 2 | BC16: 1.9089164
C17: ASX LTD NPV | D17: ASX | E17: 58.43 | G17: 0.5 | I17: 0.61128467 | J17: -0.13665251 | K17: 0.56 | L17: 0.06 | M17: 1478631.9 | O17: 0.56 | P17: 0.06 | Q17: 1478631.9 | R17: 0 | T17: 0 | U17: 0 | V17: 0 | W17: 0 | X17: LSE | Y17: 20.12 | AC17: 2269 (there are two) | AL17: BAE SYSTEMS ORD GBP0.025 | AM17: BA. | AN17: =AT17=AM17 -> TRUE | AP17: BAE Systems PLC | AQ17: BA. | AS17: BAE Systems PLC | AT17: BA. | AU17: 1.25 | AW17: ASX LTD NPV | AX17: ASX | AY17: 49.25 | BA17: 0.5 | BC17: 0.53135586
C18: B3 SA COM NPV | D18: B3SA3 | E18: 19.51 | G18: 0.75 | I18: 1.0363536 | J18: -0.13073569 | K18: 0.87 | L18: 0.12 | M18: 2286998.5 | O18: 0.87 | P18: 0.12 | Q18: 2286998.5 | R18: 0 | T18: 0 | U18: 0 | V18: 0 | W18: 0 | X18: HKG | Y18: 129.1 | AC18: Two RIOs | AL18: BANCO BILBAO VIZCAYA ARGENTAR EUR0.49 | AM18: BBVA | AN18: =AT18=AM18 -> TRUE | AP18: Banco Bilbao Vizcaya Argentaria SA | AQ18: BBVA | AS18: Banco Bilbao Vizcaya Argentaria SA | AT18: BBVA | AU18: 0.75 | AW18: B3 SA - BRASIL BOLSA BALCAO COM NPV | AX18: B3SA3 | AY18: 17.99 | BA18: 0.75 | BC18: 0.94947042
C19: BAE SYSTEMS ORD GBP0.025 | D19: BA. | E19: 21.94 | G19: 1.25 | I19: 1.2770011 | J19: -0.12441022 | K19: 1.1 | L19: -0.15 | M19: 2894407.3 | O19: 1.1 | P19: -0.15 | Q19: 2894407.3 | R19: 0 | T19: 0 | U19: 0 | V19: 0 | W19: 0 | X19: MAD | Y19: 16.465 | AC19: eni two | AL19: BANCO BRADESCO SA PRF NPV | AM19: BBDC4 | AN19: =AT19=AM19 -> TRUE | AP19: Bank Bradesco SA Participating Preferred | AQ19: BBDC4 | AS19: Bank Bradesco SA Participating Preferred | AT19: BBDC4 | AU19: 0.5 | AW19: BAE SYSTEMS ORD GBP0.025 | AX19: BA. | AY19: 22.28 | BA19: 1.25 | BC19: 1.3166801
C20: BANCO BILBAO VIZCA EUR0.49 | D20: BBVA | E20: 19.705 | G20: 0.75 | I20: 0.68530022 | J20: -0.10331919 | K20: 0.92 | L20: -0.08 | M20: 2423126.1 | O20: 0.92 | P20: -0.08 | Q20: 2423126.1 | R20: 0 | T20: 0 | U20: 0 | V20: 0 | W20: 0 | X20: BVMF | Y20: 17.66 | AL20: BANK MANDIRI (PERSERO) TBK IDR125 | AM20: BMRI | AN20: =AT20=AM20 -> FALSE | AP20: Bank of Montreal | AQ20: BMO | AS20: Bank of Montreal | AT20: BMO | AU20: 0.5 | AW20: BANCO BILBAO VIZCAYA ARGENTAR EUR0.49 | AX20: BBVA | AY20: 18.85 | BA20: 0.75 | BC20: 0.66022784
C21: BANK MANDIRI (PERSERO) TBK IDR125 | D21: BMRI | E21: 4670 | G21: 0.75 | I21: 0.73243823 | J21: -0.094523824 | K21: 0.7 | L21: -0.05 | M21: 1830925.6 | O21: 0.7 | P21: -0.05 | Q21: 1830925.6 | R21: 0 | T21: 0 | U21: 0 | V21: 0 | W21: 0 | X21: JK | Y21: 4420 | AL21: BANK OF MONTREAL COM NPV | AM21: BMO | AN21: =AT20=AM21 -> TRUE | AP21: Bayer AG | AQ21: BAYN | AS21: Bayer AG | AT21: BAYN | AU21: 0.5 | AW21: BANCO BRADESCO SA PRF NPV | AX21: BBDC4 | AY21: 19.94 | BA21: 0.5 | BC21: 0.59277552
C22: BANK MONTREAL MEDIUM COM | D22: BMO | E22: 199.73 | G22: 0.5 | I22: 0.54202322 | J22: -0.08662125 | K22: 0.6 | L22: 0.1 | M22: 1570122.4 | O22: 0.6 | P22: 0.1 | Q22: 1570122.4 | R22: 0 | T22: 0 | U22: 0 | V22: 0 | W22: 0 | X22: TSE | Y22: 182 | AL22: BAYER AG NPV (REGD) | AM22: BAYN | AN22: =AT21=AM22 -> TRUE | AP22: Bayerische Motoren Werke AG | AQ22: BMW | AS22: Bayerische Motoren Werke AG | AT22: BMW | AU22: 0.5 | AW22: BANK MANDIRI (PERSERO) TBK IDR125 | AX22: BMRI | AY22: 4880 | BA22: 0.75 | BC22: 0.79071949
C23: BAYER AG NPV (REGD) | D23: BAYN | E23: 40.12 | G23: 0.5 | I23: 0.46918021 | J23: -0.086515955 | K23: 0.78 | L23: 0.03 | M23: 2043592.9 | O23: 0.78 | P23: 0.03 | Q23: 2043592.9 | R23: 0 | T23: 0 | U23: 0 | V23: 0 | W23: 0 | X23: XET | Y23: 27.25 | AL23: BAYERISCHE MOTOREN WERKE AG EUR1 | AM23: BMW | AN23: =AT22=AM23 -> TRUE | AP23: BNP Paribas Act. Cat.A | AQ23: BNP | AS23: BNP Paribas Act. Cat.A | AT23: BNP | AU23: 1.5 | AW23: BANK OF MONTREAL COM NPV | AX23: BMO | AY23: 192.99 | BA23: 0.5 | BC23: 0.54326352
